Workbook
Name _Hlk22631867: 'CDS Definitions'!$A$103

Sheet CDS-A
A1: Question Number | B1: Question | C1: Answer | D1: Section | E1: Sub-Section | F1: Category | G1: Student Group | H1: Cohort | I1: Residency | J1: Unit load | K1: Gender | L1: Value type
A6: A01 | B6: Name: | C6: Sara Lazenby | D6: General Information | E6: Respondent Information | F6: All | G6: All | H6: All | I6: All | J6: All | K6: All | L6: Text
A7: A02 | B7: Title: | C7: Distinguished Institutional Policy Analyst | D7: General Information | E7: Respondent Information | F7: All | G7: All | H7: All | I7: All | J7: All | K7: All | L7: Text
A8: A03 | B8: Office: | C8: Office of Data, Academic Planning & Institutional Research | D8: General Information | E8: Respondent Information | F8: All | G8: All | H8: All | I8: All | J8: All | K8: All | L8: Text
A9: A04 | B9: Mailing Address: | C9: 170 Bascom Hall, 500 Lincoln Drive | D9: General Information | E9: Respondent Information | F9: All | G9: All | H9: All | I9: All | J9: All | K9: All | L9: Text
A10: A05 | B10: City/State/Zip/Country: | C10: Madison, WI, 53706 | D10: General Information | E10: Respondent Information | F10: All | G10: All | H10: All | I10: All | J10: All | K10: All | L10: Text
A11: A06 | B11: Phone: | C11: 608-263-5945 | D11: General Information | E11: Respondent Information | F11: All | G11: All | H11: All | I11: All | J11: All | K11: All | L11: Text
A12: A07 | B12: Fax: | C12: n/a | D12: General Information | E12: Respondent Information | F12: All | G12: All | H12: All | I12: All | J12: All | K12: All | L12: Text
A13: A08 | B13: E-mail Address: | C13: sara.lazenby@wisc.edu | D13: General Information | E13: Respondent Information | F13: All | G13: All | H13: All | I13: All | J13: All | K13: All | L13: Email Address
A16: A09 | B16: Are your responses to the CDS posted for reference on your institution's Web site? | C16: Y | D16: General Information | E16: Respondent Information | F16: All | G16: All | H16: All | I16: All | J16: All | K16: All | L16: YN
A18: A010 | B18: If yes, please provide the URL of the corresponding Web page: | C18: https://data.wisc.edu/common-data-set-and-rankings/ | D18: General Information | E18: Respondent Information | F18: All | G18: All | H18: All | I18: All | J18: All | K18: All | L18: URL
A20: A0A | B20: We invite you to indicate if there are items on the CDS for which you cannot use the requested analytic convention, cannot provide data for the cohort requested, whose methodology is unclear, or about which you have questions or comments in general. This information will not be published but will help the publishers further refine CDS items. | D20: General Information | E20: Respondent Information | F20: All | G20: All | H20: All | I20: All | J20: All | K20: All | L20: Text
A24: A101 | B24: Name of College/University: | C24: University of Wisconsin--Madison | D24: General Information | E24: Address Information | F24: All | G24: All | H24: All | I24: All | J24: All | K24: All | L24: Text
A25: A102 | B25: Mailing Address: | C25: 500 Lincoln Drive | D25: General Information | E25: Address Information | F25: All | G25: All | H25: All | I25: All | J25: All | K25: All | L25: Text
A26: A103 | B26: City/State/Zip/Country: | C26: Madison, WI 53706 | D26: General Information | E26: Address Information | F26: All | G26: All | H26: All | I26: All | J26: All | K26: All | L26: Text
A27: A104 | B27: Street Address (if different): | D27: General Information | E27: Address Information | F27: All | G27: All | H27: All | I27: All | J27: All | K27: All | L27: Text
A28: A105 | B28: City/State/Zip/Country: | D28: General Information | E28: Address Information | F28: All | G28: All | H28: All | I28: All | J28: All | K28: All | L28: Text
A29: A106 | B29: Main Phone Number: | C29: 608-263-2400 | D29: General Information | E29: Address Information | F29: All | G29: All | H29: All | I29: All | J29: All | K29: All | L29: Text
A30: A107 | B30: WWW Home Page Address: | C30: https://www.wisc.edu | D30: General Information | E30: Address Information | F30: All | G30: All | H30: All | I30: All | J30: All | K30: All | L30: Text
A31: A108 | B31: Admissions Phone Number: | C31: 608-262-3691 | D31: General Information | E31: Address Information | F31: All | G31: All | H31: All | I31: All | J31: All | K31: All | L31: Text
A32: A109 | B32: Admissions Toll-Free Phone Number: | D32: General Information | E32: Address Information | F32: All | G32: All | H32: All | I32: All | J32: All | K32: All | L32: Text
A33: A110 | B33: Admissions Office Mailing Address: | C33: 702 West Johnson Street, Suite 1101 | D33: General Information | E33: Address Information | F33: All | G33: All | H33: All | I33: All | J33: All | K33: All | L33: Text
A34: A111 | B34: City/State/Zip/Country: | C34: Madison, WI 53715 | D34: General Information | E34: Address Information | F34: All | G34: All | H34: All | I34: All | J34: All | K34: All | L34: Text
A35: A112 | B35: Admissions E-mail Address: | C35: onwisconsin@admissions.wisc.edu | D35: General Information | E35: Address Information | F35: All | G35: All | H35: All | I35: All | J35: All | K35: All | L35: Email Address
A37: A113 | B37: If there is a separate URL for your school’s online application, please specify: | C37: https://admissions.wisc.edu/apply-as-a-freshman/ | D37: General Information | E37: Address Information | F37: All | G37: All | H37: All | I37: All | J37: All | K37: All | L37: URL
A39: A114 | B39: If you have a mailing address other than the above to which applications should be sent, please provide: | D39: General Information | E39: Address Information | F39: All | G39: All | H39: All | I39: All | J39: All | K39: All | L39: Text
A43: A201 | B43: Public | C43: x | D43: General Information | E43: Institutional Control | F43: All | G43: All | H43: All | I43: All | J43: All | K43: All | L43: x
A44: A202 | B44: Private (nonprofit) | D44: General Information | E44: Institutional Control | F44: All | G44: All | H44: All | I44: All | J44: All | K44: All | L44: x
A45: A203 | B45: Proprietary | D45: General Information | E45: Institutional Control | F45: All | G45: All | H45: All | I45: All | J45: All | K45: All | L45: x
A48: A301 | B48: Coeducational college | C48: x | D48: General Information | E48: Classification | F48: All | G48: All | H48: All | I48: All | J48: All | K48: All | L48: x
A49: A302 | B49: Men's college | D49: General Information | E49: Classification | F49: All | G49: All | H49: All | I49: All | J49: All | K49: All | L49: x
A50: A303 | B50: Women's college | D50: General Information | E50: Classification | F50: All | G50: All | H50: All | I50: All | J50: All | K50: All | L50: x
A53: A401 | B53: Semester | C53: x | D53: General Information | E53: Academic Year | F53: All | G53: All | H53: All | I53: All | J53: All | K53: All | L53: x
A54: A402 | B54: Quarter | D54: General Information | E54: Academic Year | F54: All | G54: All | H54: All | I54: All | J54: All | K54: All | L54: x
A55: A403 | B55: Trimester | D55: General Information | E55: Academic Year | F55: All | G55: All | H55: All | I55: All | J55: All | K55: All | L55: x
A56: A404 | B56: 4-1-4 | D56: General Information | E56: Academic Year | F56: All | G56: All | H56: All | I56: All | J56: All | K56: All | L56: x
A57: A405 | B57: Continuous | D57: General Information | E57: Academic Year | F57: All | G57: All | H57: All | I57: All | J57: All | K57: All | L57: x
A59: A406 | B59: Differs by program (describe): | D59: General Information | E59: Academic Year | F59: All | G59: All | H59: All | I59: All | J59: All | K59: All | L59: Text
A60: A407 | B60: Other (describe) | D60: General Information | E60: Academic Year | F60: All | G60: All | H60: All | I60: All | J60: All | K60: All | L60: Text
A63: A501 | B63: Certificate | C63: x | D63: General Information | E63: Degrees Offered | F63: All | G63: All | H63: All | I63: All | J63: All | K63: All | L63: x
A64: A502 | B64: Diploma | D64: General Information | E64: Degrees Offered | F64: All | G64: All | H64: All | I64: All | J64: All | K64: All | L64: x
A65: A503 | B65: Associate | D65: General Information | E65: Degrees Offered | F65: All | G65: All | H65: All | I65: All | J65: All | K65: All | L65: x
A66: A504 | B66: Transfer Associate | D66: General Information | E66: Degrees Offered | F66: All | G66: All | H66: All | I66: All | J66: All | K66: All | L66: x
A67: A505 | B67: Terminal Associate | D67: General Information | E67: Degrees Offered | F67: All | G67: All | H67: All | I67: All | J67: All | K67: All | L67: x
A68: A506 | B68: Bachelor's | C68: x | D68: General Information | E68: Degrees Offered | F68: All | G68: All | H68: All | I68: All | J68: All | K68: All | L68: x
A69: A507 | B69: Postbachelor's certificate | C69: x | D69: General Information | E69: Degrees Offered | F69: All | G69: All | H69: All | I69: All | J69: All | K69: All | L69: x
A70: A508 | B70: Master's | C70: x | D70: General Information | E70: Degrees Offered | F70: All | G70: All | H70: All | I70: All | J70: All | K70: All | L70: x
A71: A509 | B71: Post-master's certificate | C71: x | D71: General Information | E71: Degrees Offered | F71: All | G71: All | H71: All | I71: All | J71: All | K71: All | L71: x
A72: A510 | B72: Doctoral degree research/scholarship | C72: x | D72: General Information | E72: Degrees Offered | F72: All | G72: All | H72: All | I72: All | J72: All | K72: All | L72: x
A73: A511 | B73: Doctoral degree – professional practice | C73: x | D73: General Information | E73: Degrees Offered | F73: All | G73: All | H73: All | I73: All | J73: All | K73: All | L73: x
A74: A512 | B74: Doctoral degree -- other | D74: General Information | E74: Degrees Offered | F74: All | G74: All | H74: All | I74: All | J74: All | K74: All | L74: x
A77: A601 | B77: If you have a diversity, equity, and inclusion office or department, please provide the URL of the corresponding Web page: | C77: https://diversity.wisc.edu | D77: General Information | E77: DEI | F77: All | G77: All | H77: All | I77: All | J77: All | K77: All | L77: URL

Sheet CDS-B
A1: Question Number | B1: Question | C1: Answer | D1: Section | E1: Sub-Section | F1: Category | G1: Student Group | H1: Cohort | I1: Residency | J1: Unit load | K1: Gender | L1: Value type
A16: B101 | B16: Degree-seeking, first-time first-year students: men | C16: 3768 | D16: Enrollment And Persistence | E16: Institutional Enrollment | F16: Degree-seeking | G16: Undergraduates | H16: First-time, first-year | I16: All | J16: FT | K16: Men | L16: Number
A17: B102 | B17: Degree-seeking, first-time first-year students: women | C17: 4722 | D17: Enrollment And Persistence | E17: Institutional Enrollment | F17: Degree-seeking | G17: Undergraduates | H17: First-time, first-year | I17: All | J17: FT | K17: Women | L17: Number
A18: B103 | B18: Degree-seeking, first-time first-year students: another gender | C18: 1 | D18: Enrollment And Persistence | E18: Institutional Enrollment | F18: Degree-seeking | G18: Undergraduates | H18: First-time, first-year | I18: All | J18: FT | K18: Another Gender | L18: Number
A19: B104 | B19: Degree-seeking, first-time first-year students: unknown | C19: 0 | D19: Enrollment And Persistence | E19: Institutional Enrollment | F19: Degree-seeking | G19: Undergraduates | H19: First-time, first-year | I19: All | J19: FT | K19: Unknown | L19: Number
A21: B105 | B21: Other first-year, degree-seeking: men | C21: 0 | D21: Enrollment And Persistence | E21: Institutional Enrollment | F21: Degree-seeking | G21: Undergraduates | H21: Other first-year | I21: All | J21: FT | K21: Men | L21: Number
A22: B106 | B22: Other first-year, degree-seeking: women | C22: 0 | D22: Enrollment And Persistence | E22: Institutional Enrollment | F22: Degree-seeking | G22: Undergraduates | H22: Other first-year | I22: All | J22: FT | K22: Women | L22: Number
A23: B107 | B23: Other first-year, degree-seeking: another gender | C23: 0 | D23: Enrollment And Persistence | E23: Institutional Enrollment | F23: Degree-seeking | G23: Undergraduates | H23: Other first-year | I23: All | J23: FT | K23: Another Gender | L23: Number
A24: B108 | B24: Other first-year, degree-seeking: unknown | C24: 0 | D24: Enrollment And Persistence | E24: Institutional Enrollment | F24: Degree-seeking | G24: Undergraduates | H24: Other first-year | I24: All | J24: FT | K24: Unknown | L24: Number
A26: B109 | B26: All other degree-seeking: men | C26: 12535 | D26: Enrollment And Persistence | E26: Institutional Enrollment | F26: Degree-seeking | G26: Undergraduates | H26: All other | I26: All | J26: FT | K26: Men | L26: Number
A27: B110 | B27: All other degree-seeking: women | C27: 14167 | D27: Enrollment And Persistence | E27: Institutional Enrollment | F27: Degree-seeking | G27: Undergraduates | H27: All other | I27: All | J27: FT | K27: Women | L27: Number
A28: B111 | B28: All other degree-seeking: another gender | C28: 3 | D28: Enrollment And Persistence | E28: Institutional Enrollment | F28: Degree-seeking | G28: Undergraduates | H28: All other | I28: All | J28: FT | K28: Another Gender | L28: Number
A29: B112 | B29: All other degree-seeking: unknown | D29: Enrollment And Persistence | E29: Institutional Enrollment | F29: Degree-seeking | G29: Undergraduates | H29: All other | I29: All | J29: FT | K29: Unknown | L29: Number
A31: B113 | B31: Total degree-seeking: men | C31: =SUM(C26,C21,C16) | D31: Enrollment And Persistence | E31: Institutional Enrollment | F31: Degree-seeking | G31: Undergraduates | H31: Total | I31: All | J31: FT | K31: Men | L31: Number
A32: B114 | B32: Total degree-seeking: women | C32: =SUM(C27,C22,C17) | D32: Enrollment And Persistence | E32: Institutional Enrollment | F32: Degree-seeking | G32: Undergraduates | H32: Total | I32: All | J32: FT | K32: Women | L32: Number
A33: B115 | B33: Total degree-seeking: another gender | C33: =SUM(C28,C23,C18) | D33: Enrollment And Persistence | E33: Institutional Enrollment | F33: Degree-seeking | G33: Undergraduates | H33: Total | I33: All | J33: FT | K33: Another Gender | L33: Number
A34: B116 | B34: Total degree-seeking: unknown | C34: =SUM(C29,C24,C19) | D34: Enrollment And Persistence | E34: Institutional Enrollment | F34: Degree-seeking | G34: Undergraduates | H34: Total | I34: All | J34: FT | K34: Unknown | L34: Number
A36: B117 | B36: All other undergraduates enrolled in credit courses: men | C36: 175 | D36: Enrollment And Persistence | E36: Institutional Enrollment | F36: Enrolled in Credit Courses | G36: Undergraduates | H36: All other | I36: All | J36: FT | K36: Men | L36: Number
A37: B118 | B37: All other undergraduates enrolled in credit courses: women | C37: 137 | D37: Enrollment And Persistence | E37: Institutional Enrollment | F37: Enrolled in Credit Courses | G37: Undergraduates | H37: All other | I37: All | J37: FT | K37: Women | L37: Number
A38: B119 | B38: All other undergraduates enrolled in credit courses: another gender | C38: 0 | D38: Enrollment And Persistence | E38: Institutional Enrollment | F38: Enrolled in Credit Courses | G38: Undergraduates | H38: All other | I38: All | J38: FT | K38: Another Gender | L38: Number
A39: B120 | B39: All other undergraduates enrolled in credit courses: unknown | C39: 0 | D39: Enrollment And Persistence | E39: Institutional Enrollment | F39: Enrolled in Credit Courses | G39: Undergraduates | H39: All other | I39: All | J39: FT | K39: Unknown | L39: Number
A41: B121 | B41: Total undergraduate Full-Time Students: men | C41: =SUM(C31,C36) | D41: Enrollment And Persistence | E41: Institutional Enrollment | F41: All | G41: Undergraduates | H41: Total | I41: All | J41: FT | K41: Men | L41: Number
A42: B122 | B42: Total undergraduate Full-Time Students: women | C42: =SUM(C32,C37) | D42: Enrollment And Persistence | E42: Institutional Enrollment | F42: All | G42: Undergraduates | H42: Total | I42: All | J42: FT | K42: Women | L42: Number
A43: B123 | B43: Total undergraduate Full-Time Students: another gender | C43: =SUM(C33,C38) | D43: Enrollment And Persistence | E43: Institutional Enrollment | F43: All | G43: Undergraduates | H43: Total | I43: All | J43: FT | K43: Another Gender | L43: Number
A44: B124 | B44: Total undergraduate Full-Time Students: unknown | C44: =SUM(C34,C39) | D44: Enrollment And Persistence | E44: Institutional Enrollment | F44: All | G44: Undergraduates | H44: Total | I44: All | J44: FT | K44: Unknown | L44: Number
A47: B125 | B47: Degree-seeking, first-time first-year students: men | C47: 11 | D47: Enrollment And Persistence | E47: Institutional Enrollment | F47: Degree-seeking | G47: Undergraduates | H47: First-time, first-year | I47: All | J47: PT | K47: Men | L47: Number
A48: B126 | B48: Degree-seeking, first-time first-year students: women | C48: 12 | D48: Enrollment And Persistence | E48: Institutional Enrollment | F48: Degree-seeking | G48: Undergraduates | H48: First-time, first-year | I48: All | J48: PT | K48: Women | L48: Number
A49: B127 | B49: Degree-seeking, first-time first-year students: another gender | C49: 0 | D49: Enrollment And Persistence | E49: Institutional Enrollment | F49: Degree-seeking | G49: Undergraduates | H49: First-time, first-year | I49: All | J49: PT | K49: Another Gender | L49: Number
A50: B128 | B50: Degree-seeking, first-time first-year students: unknown | C50: 0 | D50: Enrollment And Persistence | E50: Institutional Enrollment | F50: Degree-seeking | G50: Undergraduates | H50: First-time, first-year | I50: All | J50: PT | K50: Unknown | L50: Number
A52: B129 | B52: Other first-year, degree-seeking: men | C52: 0 | D52: Enrollment And Persistence | E52: Institutional Enrollment | F52: Degree-seeking | G52: Undergraduates | H52: Other first-year | I52: All | J52: PT | K52: Men | L52: Number
A53: B130 | B53: Other first-year, degree-seeking: women | C53: 0 | D53: Enrollment And Persistence | E53: Institutional Enrollment | F53: Degree-seeking | G53: Undergraduates | H53: Other first-year | I53: All | J53: PT | K53: Women | L53: Number
A54: B131 | B54: Other first-year, degree-seeking: another gender | C54: 0 | D54: Enrollment And Persistence | E54: Institutional Enrollment | F54: Degree-seeking | G54: Undergraduates | H54: Other first-year | I54: All | J54: PT | K54: Another Gender | L54: Number
A55: B132 | B55: Other first-year, degree-seeking: unknown | C55: 0 | D55: Enrollment And Persistence | E55: Institutional Enrollment | F55: Degree-seeking | G55: Undergraduates | H55: Other first-year | I55: All | J55: PT | K55: Unknown | L55: Number
A57: B133 | B57: All other degree-seeking: men | C57: 886 | D57: Enrollment And Persistence | E57: Institutional Enrollment | F57: Degree-seeking | G57: Undergraduates | H57: All other | I57: All | J57: PT | K57: Men | L57: Number
A58: B134 | B58: All other degree-seeking: women | C58: 797 | D58: Enrollment And Persistence | E58: Institutional Enrollment | F58: Degree-seeking | G58: Undergraduates | H58: All other | I58: All | J58: PT | K58: Women | L58: Number
A59: B135 | B59: All other degree-seeking: another gender | C59: 0 | D59: Enrollment And Persistence | E59: Institutional Enrollment | F59: Degree-seeking | G59: Undergraduates | H59: All other | I59: All | J59: PT | K59: Another Gender | L59: Number
A60: B136 | B60: All other degree-seeking: unknown | C60: 0 | D60: Enrollment And Persistence | E60: Institutional Enrollment | F60: Degree-seeking | G60: Undergraduates | H60: All other | I60: All | J60: PT | K60: Unknown | L60: Number
A62: B137 | B62: Total degree-seeking: men | C62: =SUM(C57,C52,C47) | D62: Enrollment And Persistence | E62: Institutional Enrollment | F62: Degree-seeking | G62: Undergraduates | H62: Total | I62: All | J62: PT | K62: Men | L62: Number
A63: B138 | B63: Total degree-seeking: women | C63: =SUM(C58,C53,C48) | D63: Enrollment And Persistence | E63: Institutional Enrollment | F63: Degree-seeking | G63: Undergraduates | H63: Total | I63: All | J63: PT | K63: Women | L63: Number
A64: B139 | B64: Total degree-seeking: another gender | C64: =SUM(C59,C54,C49) | D64: Enrollment And Persistence | E64: Institutional Enrollment | F64: Degree-seeking | G64: Undergraduates | H64: Total | I64: All | J64: PT | K64: Another Gender | L64: Number
A65: B140 | B65: Total degree-seeking: unknown | C65: =SUM(C60,C55,C50) | D65: Enrollment And Persistence | E65: Institutional Enrollment | F65: Degree-seeking | G65: Undergraduates | H65: Total | I65: All | J65: PT | K65: Unknown | L65: Number
A67: B141 | B67: All other undergraduates enrolled in credit courses: men | C67: 960 | D67: Enrollment And Persistence | E67: Institutional Enrollment | F67: Enrolled in Credit Courses | G67: Undergraduates | H67: All other undergraduates | I67: All | J67: PT | K67: Men | L67: Number
A68: B142 | B68: All other undergraduates enrolled in credit courses: women | C68: 907 | D68: Enrollment And Persistence | E68: Institutional Enrollment | F68: Enrolled in Credit Courses | G68: Undergraduates | H68: All other undergraduates | I68: All | J68: PT | K68: Women | L68: Number
A69: B143 | B69: All other undergraduates enrolled in credit courses: another gender | C69: 2 | D69: Enrollment And Persistence | E69: Institutional Enrollment | F69: Enrolled in Credit Courses | G69: Undergraduates | H69: All other undergraduates | I69: All | J69: PT | K69: Another Gender | L69: Number
A70: B144 | B70: All other undergraduates enrolled in credit courses: unknown | C70: 0 | D70: Enrollment And Persistence | E70: Institutional Enrollment | F70: Enrolled in Credit Courses | G70: Undergraduates | H70: All other undergraduates | I70: All | J70: PT | K70: Unknown | L70: Number
A72: B145 | B72: Total undergraduate Part-Time Students: men | C72: =SUM(C62,C67) | D72: Enrollment And Persistence | E72: Institutional Enrollment | F72: All | G72: Undergraduates | H72: Total | I72: All | J72: PT | K72: Men | L72: Number
A73: B146 | B73: Total undergraduate Part-Time Students: women | C73: =SUM(C63,C68) | D73: Enrollment And Persistence | E73: Institutional Enrollment | F73: All | G73: Undergraduates | H73: Total | I73: All | J73: PT | K73: Women | L73: Number
A74: B147 | B74: Total undergraduate Part-Time Students: another gender | C74: =SUM(C64,C69) | D74: Enrollment And Persistence | E74: Institutional Enrollment | F74: All | G74: Undergraduates | H74: Total | I74: All | J74: PT | K74: Another Gender | L74: Number
A75: B148 | B75: Total undergraduate Part-Time Students: unknown | C75: =SUM(C65,C70) | D75: Enrollment And Persistence | E75: Institutional Enrollment | F75: All | G75: Undergraduates | H75: Total | I75: All | J75: PT | K75: Unknown | L75: Number
A78: B149 | B78: Total undergraduate students: men | C78: =SUM(C72,C41) | D78: Enrollment And Persistence | E78: Institutional Enrollment | F78: All | G78: Undergraduates | H78: Total understand | I78: All | J78: All | K78: Men | L78: Number
A79: B150 | B79: Total undergraduate students: women | C79: =SUM(C73,C42) | D79: Enrollment And Persistence | E79: Institutional Enrollment | F79: All | G79: Undergraduates | H79: Total understand | I79: All | J79: All | K79: Women | L79: Number
A80: B151 | B80: Total undergraduate students: another gender | C80: =SUM(C74,C43) | D80: Enrollment And Persistence | E80: Institutional Enrollment | F80: All | G80: Undergraduates | H80: Total understand | I80: All | J80: All | K80: Another Gender | L80: Number
A81: B152 | B81: Total undergraduate students: unknown | C81: =SUM(C75,C44) | D81: Enrollment And Persistence | E81: Institutional Enrollment | F81: All | G81: Undergraduates | H81: Total understand | I81: All | J81: All | K81: Unknown | L81: Number
A84: B153 | B84: Degree-seeking, first-time: men | C84: 1501 | D84: Enrollment And Persistence | E84: Institutional Enrollment | F84: Degree-seeking | G84: Graduates | H84: First-time | I84: All | J84: FT | K84: Men | L84: Number
A85: B154 | B85: Degree-seeking, first-time: women | C85: 1566 | D85: Enrollment And Persistence | E85: Institutional Enrollment | F85: Degree-seeking | G85: Graduates | H85: First-time | I85: All | J85: FT | K85: Women | L85: Number
A86: B155 | B86: Degree-seeking, first-time: another gender | C86: 0 | D86: Enrollment And Persistence | E86: Institutional Enrollment | F86: Degree-seeking | G86: Graduates | H86: First-time | I86: All | J86: FT | K86: Another Gender | L86: Number
A87: B156 | B87: Degree-seeking, first-time: unknown | C87: 1 | D87: Enrollment And Persistence | E87: Institutional Enrollment | F87: Degree-seeking | G87: Graduates | H87: First-time | I87: All | J87: FT | K87: Unknown | L87: Number
A89: B157 | B89: All other degree-seeking: men | C89: 3538 | D89: Enrollment And Persistence | E89: Institutional Enrollment | F89: Degree-seeking | G89: Graduates | H89: All other | I89: All | J89: FT | K89: Men | L89: Number
A90: B158 | B90: All other degree-seeking: women | C90: 4206 | D90: Enrollment And Persistence | E90: Institutional Enrollment | F90: Degree-seeking | G90: Graduates | H90: All other | I90: All | J90: FT | K90: Women | L90: Number
A91: B159 | B91: All other degree-seeking: another gender | C91: 0 | D91: Enrollment And Persistence | E91: Institutional Enrollment | F91: Degree-seeking | G91: Graduates | H91: All other | I91: All | J91: FT | K91: Another Gender | L91: Number
A92: B160 | B92: All other degree-seeking: unknown | C92: 0 | D92: Enrollment And Persistence | E92: Institutional Enrollment | F92: Degree-seeking | G92: Graduates | H92: All other | I92: All | J92: FT | K92: Unknown | L92: Number
A94: B161 | B94: All other graduates enrolled in credit courses: men | C94: 0 | D94: Enrollment And Persistence | E94: Institutional Enrollment | F94: Enrolled in Credit Courses | G94: Graduates | H94: All other | I94: All | J94: FT | K94: Men | L94: Number
A95: B162 | B95: All other graduates enrolled in credit courses: women | C95: 0 | D95: Enrollment And Persistence | E95: Institutional Enrollment | F95: Enrolled in Credit Courses | G95: Graduates | H95: All other | I95: All | J95: FT | K95: Women | L95: Number
A96: B163 | B96: All other graduates enrolled in credit courses: another gender | C96: 0 | D96: Enrollment And Persistence | E96: Institutional Enrollment | F96: Enrolled in Credit Courses | G96: Graduates | H96: All other | I96: All | J96: FT | K96: Another Gender | L96: Number
A97: B164 | B97: All other graduates enrolled in credit courses: unknown | C97: 0 | D97: Enrollment And Persistence | E97: Institutional Enrollment | F97: Enrolled in Credit Courses | G97: Graduates | H97: All other | I97: All | J97: FT | K97: Unknown | L97: Number
A99: B165 | B99: Total graduate Full-Time Students: men | C99: =SUM(C94,C89,C84) | D99: Enrollment And Persistence | E99: All | F99: Full-Time | G99: Graduates | H99: Total | I99: All | J99: FT | K99: Men | L99: Number
A100: B166 | B100: Total graduate Full-Time Students: women | C100: =SUM(C95,C90,C85) | D100: Enrollment And Persistence | E100: All | F100: Full-Time | G100: Graduates | H100: Total | I100: All | J100: FT | K100: Women | L100: Number
A101: B167 | B101: Total graduate Full-Time Students: another gender | C101: =SUM(C96,C91,C86) | D101: Enrollment And Persistence | E101: All | F101: Full-Time | G101: Graduates | H101: Total | I101: All | J101: FT | K101: Another Gender | L101: Number
A102: B168 | B102: Total graduate Full-Time Students: unknown | C102: =SUM(C97,C92,C87) | D102: Enrollment And Persistence | E102: All | F102: Full-Time | G102: Graduates | H102: Total | I102: All | J102: FT | K102: Unknown | L102: Number
A105: B169 | B105: Degree-seeking, first-time: men | C105: 208 | D105: Enrollment And Persistence | E105: Institutional Enrollment | F105: Degree-seeking | G105: Graduates | H105: First-time | I105: All | J105: PT | K105: Men | L105: Number
A106: B170 | B106: Degree-seeking, first-time: women | C106: 160 | D106: Enrollment And Persistence | E106: Institutional Enrollment | F106: Degree-seeking | G106: Graduates | H106: First-time | I106: All | J106: PT | K106: Women | L106: Number
A107: B171 | B107: Degree-seeking, first-time: another gender | C107: 0 | D107: Enrollment And Persistence | E107: Institutional Enrollment | F107: Degree-seeking | G107: Graduates | H107: First-time | I107: All | J107: PT | K107: Another Gender | L107: Number
A108: B172 | B108: Degree-seeking, first-time: unknown | C108: 0 | D108: Enrollment And Persistence | E108: Institutional Enrollment | F108: Degree-seeking | G108: Graduates | H108: First-time | I108: All | J108: PT | K108: Unknown | L108: Number
A110: B173 | B110: All other degree-seeking: men | C110: 870 | D110: Enrollment And Persistence | E110: Institutional Enrollment | F110: Degree-seeking | G110: Graduates | H110: All other | I110: All | J110: PT | K110: Men | L110: Number
A111: B174 | B111: All other degree-seeking: women | C111: 964 | D111: Enrollment And Persistence | E111: Institutional Enrollment | F111: Degree-seeking | G111: Graduates | H111: All other | I111: All | J111: PT | K111: Women | L111: Number
A112: B175 | B112: All other degree-seeking: another gender | C112: 0 | D112: Enrollment And Persistence | E112: Institutional Enrollment | F112: Degree-seeking | G112: Graduates | H112: All other | I112: All | J112: PT | K112: Another Gender | L112: Number
A113: B176 | B113: All other degree-seeking: unknown | C113: 0 | D113: Enrollment And Persistence | E113: Institutional Enrollment | F113: Degree-seeking | G113: Graduates | H113: All other | I113: All | J113: PT | K113: Unknown | L113: Number
A115: B177 | B115: All other graduates enrolled in credit courses: men | C115: 0 | D115: Enrollment And Persistence | E115: Institutional Enrollment | F115: Enrolled in Credit Courses | G115: Graduates | H115: All other | I115: All | J115: PT | K115: Men | L115: Number
A116: B178 | B116: All other graduates enrolled in credit courses: women | C116: 0 | D116: Enrollment And Persistence | E116: Institutional Enrollment | F116: Enrolled in Credit Courses | G116: Graduates | H116: All other | I116: All | J116: PT | K116: Women | L116: Number
A117: B179 | B117: All other graduates enrolled in credit courses: another gender | C117: 0 | D117: Enrollment And Persistence | E117: Institutional Enrollment | F117: Enrolled in Credit Courses | G117: Graduates | H117: All other | I117: All | J117: PT | K117: Another Gender | L117: Number
A118: B180 | B118: All other graduates enrolled in credit courses: unknown | C118: 0 | D118: Enrollment And Persistence | E118: Institutional Enrollment | F118: Enrolled in Credit Courses | G118: Graduates | H118: All other | I118: All | J118: PT | K118: Unknown | L118: Number
A120: B181 | B120: Total graduate Part-Time Students: men | C120: =SUM(C115,C110,C105) | D120: Enrollment And Persistence | E120: Institutional Enrollment | F120: All | G120: Graduates | H120: Total | I120: All | J120: PT | K120: Men | L120: Number
A121: B182 | B121: Total graduate Part-Time Students: women | C121: =SUM(C116,C111,C106) | D121: Enrollment And Persistence | E121: Institutional Enrollment | F121: All | G121: Graduates | H121: Total | I121: All | J121: PT | K121: Women | L121: Number
A122: B183 | B122: Total graduate Part-Time Students: another gender | C122: =SUM(C117,C112,C107) | D122: Enrollment And Persistence | E122: Institutional Enrollment | F122: All | G122: Graduates | H122: Total | I122: All | J122: PT | K122: Another Gender | L122: Number
A123: B184 | B123: Total graduate Part-Time Students: unknown | C123: =SUM(C118,C113,C108) | D123: Enrollment And Persistence | E123: Institutional Enrollment | F123: All | G123: Graduates | H123: Total | I123: All | J123: PT | K123: Unknown | L123: Number
A126: B185 | B126: Total Graduate Students: men | C126: =SUM(C120,C99) | D126: Enrollment And Persistence | E126: Institutional Enrollment | F126: All | G126: Graduates | H126: Total | I126: All | J126: All | K126: Men | L126: Number
A127: B186 | B127: Total Graduate Students: women | C127: =SUM(C121,C100) | D127: Enrollment And Persistence | E127: Institutional Enrollment | F127: All | G127: Graduates | H127: Total | I127: All | J127: All | K127: Women | L127: Number
A128: B187 | B128: Total Graduate Students: another gender | C128: =SUM(C122,C101) | D128: Enrollment And Persistence | E128: Institutional Enrollment | F128: All | G128: Graduates | H128: Total | I128: All | J128: All | K128: Another Gender | L128: Number
A129: B188 | B129: Total Graduate Students: unknown | C129: =SUM(C123,C102) | D129: Enrollment And Persistence | E129: Institutional Enrollment | F129: All | G129: Graduates | H129: Total | I129: All | J129: All | K129: Unknown | L129: Number
A132: B189 | B132: Total All Students: men | C132: =SUM(C126,C78) | D132: Enrollment And Persistence | E132: Institutional Enrollment | F132: All | G132: All Students | H132: Total | I132: All | J132: All | K132: Men | L132: Number
A133: B190 | B133: Total All Students: women | C133: =SUM(C127,C79) | D133: Enrollment And Persistence | E133: Institutional Enrollment | F133: All | G133: All Students | H133: Total | I133: All | J133: All | K133: Women | L133: Number
A134: B191 | B134: Total All Students: another gender | C134: =SUM(C128,C80) | D134: Enrollment And Persistence | E134: Institutional Enrollment | F134: All | G134: All Students | H134: Total | I134: All | J134: All | K134: Another Gender | L134: Number
A135: B192 | B135: Total All Students: unknown | C135: =SUM(C129,C81) | D135: Enrollment And Persistence | E135: Institutional Enrollment | F135: All | G135: All Students | H135: Total | I135: All | J135: All | K135: Unknown | L135: Number
A137: B193 | B137: Total all undergraduates | C137: =SUM(C78:C81) | D137: Enrollment And Persistence | E137: Institutional Enrollment | F137: All | G137: Undergraduates | H137: Total | I137: All | J137: All | K137: All | L137: Number
A138: B194 | B138: Total all graduate | C138: =SUM(C126:C129) | D138: Enrollment And Persistence | E138: Institutional Enrollment | F138: All | G138: Graduates | H138: Total | I138: All | J138: All | K138: All | L138: Number
A139: B195 | B139: Grand Total All Students | C139: =SUM(C137:C138) | D139: Enrollment And Persistence | E139: Institutional Enrollment | F139: All | G139: All Students | H139: Total | I139: All | J139: All | K139: All | L139: Number
A170: B201 | B170: Nonresidents | C170: 688 | D170: Enrollment And Persistence | E170: Enrollment by Racial/Ethnic Category | F170: Degree-seeking | G170: Undergraduates | H170: First-time, first-year | I170: Nonresidents | J170: All | K170: All | L170: Number
A171: B202 | B171: Hispanic/Latino | C171: 721 | D171: Enrollment And Persistence | E171: Enrollment by Racial/Ethnic Category | F171: Degree-seeking | G171: Undergraduates | H171: First-time, first-year | I171: Domestic | J171: All | K171: All | L171: Number
A172: B203 | B172: Black or African American, non-Hispanic | C172: 180 | D172: Enrollment And Persistence | E172: Enrollment by Racial/Ethnic Category | F172: Degree-seeking | G172: Undergraduates | H172: First-time, first-year | I172: Domestic | J172: All | K172: All | L172: Number
A173: B204 | B173: White, non-Hispanic | C173: 5143 | D173: Enrollment And Persistence | E173: Enrollment by Racial/Ethnic Category | F173: Degree-seeking | G173: Undergraduates | H173: First-time, first-year | I173: Domestic | J173: All | K173: All | L173: Number
...

Sheet CDS-C
A1: Question Number | B1: Question | C1: Answer | D1: Section | E1: Sub-Section | F1: Category | G1: Student Group | H1: Cohort | I1: Residency | J1: Unit load | K1: Gender | L1: Value type
A27: C101 | B27: Total first-time, first-year men who applied | C27: 32863 | D27: First-Time, First-Year Admission | E27: Applications | F27: Applied | G27: Undergraduates | H27: First-time, first-year | I27: All | J27: All | K27: Men | L27: Number
A28: C102 | B28: Total first-time, first-year women who applied | C28: 33050 | D28: First-Time, First-Year Admission | E28: Applications | F28: Applied | G28: Undergraduates | H28: First-time, first-year | I28: All | J28: All | K28: Women | L28: Number
A29: C103 | B29: Total first-time, first-year another gender who applied | C29: 20 | D29: First-Time, First-Year Admission | E29: Applications | F29: Applied | G29: Undergraduates | H29: First-time, first-year | I29: All | J29: All | K29: Another Gender | L29: Number
A30: C104 | B30: Total first-time, first-year unknown gender who applied | C30: 0 | D30: First-Time, First-Year Admission | E30: Applications | F30: Applied | G30: Undergraduates | H30: First-time, first-year | I30: All | J30: All | K30: Unknown | L30: Number
A33: C105 | B33: Total first-time, first-year men who were admitted | C33: 13835 | D33: First-Time, First-Year Admission | E33: Applications | F33: Admitted | G33: Undergraduates | H33: First-time, first-year | I33: All | J33: All | K33: Men | L33: Number
A34: C106 | B34: Total first-time, first-year women who were admitted | C34: 15940 | D34: First-Time, First-Year Admission | E34: Applications | F34: Admitted | G34: Undergraduates | H34: First-time, first-year | I34: All | J34: All | K34: Women | L34: Number
A35: C107 | B35: Total first-time, first-year another gender who were admitted | C35: 9 | D35: First-Time, First-Year Admission | E35: Applications | F35: Admitted | G35: Undergraduates | H35: First-time, first-year | I35: All | J35: All | K35: Another Gender | L35: Number
A36: C108 | B36: Total first-time, first-year unknown gender who were admitted | C36: 0 | D36: First-Time, First-Year Admission | E36: Applications | F36: Admitted | G36: Undergraduates | H36: First-time, first-year | I36: All | J36: All | K36: Unknown | L36: Number
A39: C109 | B39: Total full-time, first-time, first-year men who enrolled | C39: 3768 | D39: First-Time, First-Year Admission | E39: Applications | F39: Enrolled | G39: Undergraduates | H39: First-time, first-year | I39: All | J39: All | K39: Men | L39: Number
A40: C110 | B40: Total part-time, first-time, first-year men who enrolled | C40: 11 | D40: First-Time, First-Year Admission | E40: Applications | F40: Enrolled | G40: Undergraduates | H40: First-time, first-year | I40: All | J40: PT | K40: Men | L40: Number
A41: C111 | B41: Total full-time, first-time, first-year women who enrolled | C41: 4722 | D41: First-Time, First-Year Admission | E41: Applications | F41: Enrolled | G41: Undergraduates | H41: First-time, first-year | I41: All | J41: FT | K41: Women | L41: Number
A42: C112 | B42: Total part-time, first-time, first-year women who enrolled | C42: 12 | D42: First-Time, First-Year Admission | E42: Applications | F42: Enrolled | G42: Undergraduates | H42: First-time, first-year | I42: All | J42: PT | K42: Women | L42: Number
... A46: C116 | B46: Total part-time, first-time, first-year unknown gender who enrolled | C46: 0 | D46: First-Time, First-Year Admission | E46: Applications | F46: Enrolled | G46: Undergraduates | H46: First-time, first-year | I46: All | J46: PT | K46: Unknown | L46: Number
A49: C117 | B49: Total first-time, first-year students who applied | C49: =SUM(C27:C30) | D49: First-Time, First-Year Admission | E49: Applications | F49: Applied | G49: Undergraduates | H49: First-time, first-year | I49: All | J49: All | K49: All | L49: Number
A50: C118 | B50: Total first-time, first-year students who were admitted | C50: =SUM(C33:C36) | D50: First-Time, First-Year Admission | E50: Applications | F50: Admitted | G50: Undergraduates | H50: First-time, first-year | I50: All | J50: All | K50: All | L50: Number
A51: C119 | B51: Total first-time, first-year students who enrolled | C51: =SUM(C39:C46) | D51: First-Time, First-Year Admission | E51: Applications | F51: Enrolled | G51: Undergraduates | H51: First-time, first-year | I51: All | J51: All | K51: All | L51: Number
A60: C120 | B60: Total first-time, first-year who applied | D60: First-Time, First-Year Admission | E60: Applications | F60: Applied | G60: Undergraduates | H60: First-time, first-year | I60: In-State | J60: All | K60: All | L60: Number
A61: C121 | B61: Total first-time, first-year who were admitted | D61: First-Time, First-Year Admission | E61: Applications | F61: Admitted | G61: Undergraduates | H61: First-time, first-year | I61: In-State | J61: All | K61: All | L61: Number
A62: C122 | B62: Total first-time, first-year who enrolled | D62: First-Time, First-Year Admission | E62: Applications | F62: Enrolled | G62: Undergraduates | H62: First-time, first-year | I62: In-State | J62: All | K62: All | L62: Number
A65: C123 | B65: Total first-time, first-year who applied | D65: First-Time, First-Year Admission | E65: Applications | F65: Applied | G65: Undergraduates | H65: First-time, first-year | I65: Out-of-State | J65: All | K65: All | L65: Number
A66: C124 | B66: Total first-time, first-year who were admitted | D66: First-Time, First-Year Admission | E66: Applications | F66: Admitted | G66: Undergraduates | H66: First-time, first-year | I66: Out-of-State | J66: All | K66: All | L66: Number
A67: C125 | B67: Total first-time, first-year who enrolled | D67: First-Time, First-Year Admission | E67: Applications | F67: Enrolled | G67: Undergraduates | H67: First-time, first-year | I67: Out-of-State | J67: All | K67: All | L67: Number
A70: C126 | B70: Total first-time, first-year who applied | D70: First-Time, First-Year Admission | E70: Applications | F70: Applied | G70: Undergraduates | H70: First-time, first-year | I70: Nonresidents | J70: All | K70: All | L70: Number
A71: C127 | B71: Total first-time, first-year who were admitted | D71: First-Time, First-Year Admission | E71: Applications | F71: Admitted | G71: Undergraduates | H71: First-time, first-year | I71: Nonresidents | J71: All | K71: All | L71: Number
A72: C128 | B72: Total first-time, first-year who enrolled | D72: First-Time, First-Year Admission | E72: Applications | F72: Enrolled | G72: Undergraduates | H72: First-time, first-year | I72: Nonresidents | J72: All | K72: All | L72: Number
A75: C129 | B75: Total first-time, first-year who applied | D75: First-Time, First-Year Admission | E75: Applications | F75: Applied | G75: Undergraduates | H75: First-time, first-year | I75: Unknown | J75: All | K75: All | L75: Number
A76: C130 | B76: Total first-time, first-year who were admitted | D76: First-Time, First-Year Admission | E76: Applications | F76: Admitted | G76: Undergraduates | H76: First-time, first-year | I76: Unknown | J76: All | K76: All | L76: Number
A77: C131 | B77: Total first-time, first-year who enrolled | D77: First-Time, First-Year Admission | E77: Applications | F77: Enrolled | G77: Undergraduates | H77: First-time, first-year | I77: Unknown | J77: All | K77: All | L77: Number
A85: C201 | B85: Do you have a policy of placing students on a waiting list? | C85: Y | D85: First-Time, First-Year Admission | E85: Wait List | F85: Policy | G85: Undergraduates | H85: First-time, first-year | I85: All | J85: All | K85: All | L85: YN
A91: C202 | B91: Number of qualified applicants offered a place on waiting list: | C91: 12584 | D91: First-Time, First-Year Admission | E91: Wait List | F91: Applied | G91: Undergraduates | H91: First-time, first-year | I91: All | J91: All | K91: All | L91: Number
A92: C203 | B92: Number accepting a place on the waiting list: | C92: 7644 | D92: First-Time, First-Year Admission | E92: Wait List | F92: Accepting Offer | G92: Undergraduates | H92: First-time, first-year | I92: All | J92: All | K92: All | L92: Number
A93: C204 | B93: Number of wait-listed students admitted: | C93: 493 | D93: First-Time, First-Year Admission | E93: Wait List | F93: Admitted | G93: Undergraduates | H93: First-time, first-year | I93: All | J93: All | K93: All | L93: Number
A96: C205 | B96: Is your waiting list ranked? | C96: N | D96: First-Time, First-Year Admission | E96: Wait List | F96: Policy | G96: Undergraduates | H96: First-time, first-year | I96: All | J96: All | K96: All | L96: YN
A97: C206 | B97: If yes, do you release that information to students? | D97: First-Time, First-Year Admission | E97: Wait List | F97: Policy | G97: Undergraduates | H97: First-time, first-year | I97: All | J97: All | K97: All | L97: YN
A98: C207 | B98: Do you release that information to school counselors? | D98: First-Time, First-Year Admission | E98: Wait List | F98: Policy | G98: Undergraduates | H98: First-time, first-year | I98: All | J98: All | K98: All | L98: YN
A110: C301 | B110: High school diploma is required and GED is accepted | C110: X | D110: First-Time, First-Year Admission | E110: Admissions Requirements | F110: High School completion | G110: Undergraduates | H110: First-time, first-year | I110: All | J110: All | K110: All | L110: x
A111: C302 | B111: High school diploma is required and GED is not accepted | D111: First-Time, First-Year Admission | E111: Admissions Requirements | F111: High School completion | G111: Undergraduates | H111: First-time, first-year | I111: All | J111: All | K111: All | L111: x
A112: C303 | B112: High school diploma or equivalent is not required | D112: First-Time, First-Year Admission | E112: Admissions Requirements | F112: High School completion | G112: Undergraduates | H112: First-time, first-year | I112: All | J112: All | K112: All | L112: x
A118: C401 | B118: Require | C118: x | D118: First-Time, First-Year Admission | E118: Admissions Requirements | F118: College-preparatory Program | G118: Undergraduates | H118: First-time, first-year | I118: All | J118: All | K118: All | L118: x
A119: C402 | B119: Recommend | D119: First-Time, First-Year Admission | E119: Admissions Requirements | F119: College-preparatory Program | G119: Undergraduates | H119: First-time, first-year | I119: All | J119: All | K119: All | L119: x
A120: C403 | B120: Neither require nor recommend | D120: First-Time, First-Year Admission | E120: Admissions Requirements | F120: College-preparatory Program | G120: Undergraduates | H120: First-time, first-year | I120: All | J120: All | K120: All | L120: x
A131: C501 | B131: Total academic units | C131: 17 | D131: First-Time, First-Year Admission | E131: Admissions Requirements | F131: High School Units Required | G131: Undergraduates | H131: First-time, first-year | I131: All | J131: All | K131: All | L131: Carnegie units
A132: C502 | B132: English | C132: 4 | D132: First-Time, First-Year Admission | E132: Admissions Requirements | F132: High School Units Required | G132: Undergraduates | H132: First-time, first-year | I132: All | J132: All | K132: All | L132: Carnegie units
A133: C503 | B133: Mathematics | C133: 3 | D133: First-Time, First-Year Admission | E133: Admissions Requirements | F133: High School Units Required | G133: Undergraduates | H133: First-time, first-year | I133: All | J133: All | K133: All | L133: Carnegie units
A134: C504 | B134: Science | C134: 3 | D134: First-Time, First-Year Admission | E134: Admissions Requirements | F134: High School Units Required | G134: Undergraduates | H134: First-time, first-year | I134: All | J134: All | K134: All | L134: Carnegie units
A135: C505 | B135: Of these, units that must be lab | D135: First-Time, First-Year Admission | E135: Admissions Requirements | F135: High School Units Required | G135: Undergraduates | H135: First-time, first-year | I135: All | J135: All | K135: All | L135: Carnegie units
A136: C506 | B136: Foreign language | C136: 2 | D136: First-Time, First-Year Admission | E136: Admissions Requirements | F136: High School Units Required | G136: Undergraduates | H136: First-time, first-year | I136: All | J136: All | K136: All | L136: Carnegie units
A137: C507 | B137: Social studies | C137: 3 | D137: First-Time, First-Year Admission | E137: Admissions Requirements | F137: High School Units Required | G137: Undergraduates | H137: First-time, first-year | I137: All | J137: All | K137: All | L137: Carnegie units
A138: C508 | B138: History | D138: First-Time, First-Year Admission | E138: Admissions Requirements | F138: High School Units Required | G138: Undergraduates | H138: First-time, first-year | I138: All | J138: All | K138: All | L138: Carnegie units
A139: C509 | B139: Academic electives | D139: First-Time, First-Year Admission | E139: Admissions Requirements | F139: High School Units Required | G139: Undergraduates | H139: First-time, first-year | I139: All | J139: All | K139: All | L139: Carnegie units
A140: C510 | B140: Computer Science | D140: First-Time, First-Year Admission | E140: Admissions Requirements | F140: High School Units Required | G140: Undergraduates | H140: First-time, first-year | I140: All | J140: All | K140: All | L140: Carnegie units
A141: C511 | B141: Visual/Performing Arts | D141: First-Time, First-Year Admission | E141: Admissions Requirements | F141: High School Units Required | G141: Undergraduates | H141: First-time, first-year | I141: All | J141: All | K141: All | L141: Carnegie units
A143: C512 | B143: Other (specify) | C143: 2 additional academic/fine arts electives | D143: First-Time, First-Year Admission | E143: Admissions Requirements | F143: High School Units Required | G143: Undergraduates | H143: First-time, first-year | I143: All | J143: All | K143: All | L143: Text
A145: C513 | B145: Total academic units | C145: 22 | D145: First-Time, First-Year Admission | E145: Admissions Requirements | F145: High School Units Recommended | G145: Undergraduates | H145: First-time, first-year | I145: All | J145: All | K145: All | L145: Carnegie units
A146: C514 | B146: English | C146: 4 | D146: First-Time, First-Year Admission | E146: Admissions Requirements | F146: High School Units Recommended | G146: Undergraduates | H146: First-time, first-year | I146: All | J146: All | K146: All | L146: Carnegie units
A147: C515 | B147: Mathematics | C147: 4 | D147: First-Time, First-Year Admission | E147: Admissions Requirements | F147: High School Units Recommended | G147: Undergraduates | H147: First-time, first-year | I147: All | J147: All | K147: All | L147: Carnegie units
A148: C516 | B148: Science | C148: 4 | D148: First-Time, First-Year Admission | E148: Admissions Requirements | F148: High School Units Recommended | G148: Undergraduates | H148: First-time, first-year | I148: All | J148: All | K148: All | L148: Carnegie units
A149: C517 | B149: Of these, units that must be lab | C149: 2 | D149: First-Time, First-Year Admission | E149: Admissions Requirements | F149: High School Units Recommended | G149: Undergraduates | H149: First-time, first-year | I149: All | J149: All | K149: All | L149: Carnegie units
A150: C518 | B150: Foreign language | C150: 2 | D150: First-Time, First-Year Admission | E150: Admissions Requirements | F150: High School Units Recommended | G150: Undergraduates | H150: First-time, first-year | I150: All | J150: All | K150: All | L150: Carnegie units
A151: C519 | B151: Social studies | C151: 4 | D151: First-Time, First-Year Admission | E151: Admissions Requirements | F151: High School Units Recommended | G151: Undergraduates | H151: First-time, first-year | I151: All | J151: All | K151: All | L151: Carnegie units
A152: C520 | B152: History | D152: First-Time, First-Year Admission | E152: Admissions Requirements | F152: High School Units Recommended | G152: Undergraduates | H152: First-time, first-year | I152: All | J152: All | K152: All | L152: Carnegie units
A153: C521 | B153: Academic electives | D153: First-Time, First-Year Admission | E153: Admissions Requirements | F153: High School Units Recommended | G153: Undergraduates | H153: First-time, first-year | I153: All | J153: All | K153: All | L153: Carnegie units
A154: C522 | B154: Computer Science | D154: First-Time, First-Year Admission | E154: Admissions Requirements | F154: High School Units Recommended | G154: Undergraduates | H154: First-time, first-year | I154: All | J154: All | K154: All | L154: Carnegie units
A155: C523 | B155: Visual/Performing Arts | D155: First-Time, First-Year Admission | E155: Admissions Requirements | F155: High School Units Recommended | G155: Undergraduates | H155: First-time, first-year | I155: All | J155: All | K155: All | L155: Carnegie units
A156: C524 | B156: Other (specify) | C156: 2 additional academic/fine arts electives | D156: First-Time, First-Year Admission | E156: Admissions Requirements | F156: High School Units Recommended | G156: Undergraduates | H156: First-time, first-year | I156: All | J156: All | K156: All | L156: Carnegie units
A167: C601 | B167: Open admission policy as described above for all students | D167: First-Time, First-Year Admission | E167: Basis for Selection | F167: High School Completion | G167: Undergraduates | H167: First-time, first-year | I167: All | J167: All | K167: All | L167: x
A171: C602 | B171: selective admission for out-of-state students | D171: First-Time, First-Year Admission | E171: Basis for Selection | F171: High School Completion | G171: Undergraduates | H171: First-time, first-year | I171: All | J171: All | K171: All | L171: x
A172: C603 | B172: selective admission to some programs | D172: First-Time, First-Year Admission | E172: Basis for Selection | F172: High School Completion | G172: Undergraduates | H172: First-time, first-year | I172: All | J172: All | K172: All | L172: x
A174: C604 | B174: other (explain): | D174: First-Time, First-Year Admission | E174: Basis for Selection | F174: High School Completion | G174: Undergraduates | H174: First-time, first-year | I174: All | J174: All | K174: All | L174: x
C179: Very Important
C180: Important
C181: Considered
C182: Not Considered
A186: C701 | B186: Rigor of secondary school record | C186: Very Important | D186: First-Time, First-Year Admission | E186: Basis for Selection | F186: Academic Factors | G186: Undergraduates | H186: First-time, first-year | I186: All | J186: All | K186: All | L186: Text
A187: C702 | B187: Class rank | C187: Considered | D187: First-Time, First-Year Admission | E187: Basis for Selection | F187: Academic Factors | G187: Undergraduates | H187: First-time, first-year | I187: All | J187: All | K187: All | L187: Text
A188: C703 | B188: Academic GPA | C188: Very Important | D188: First-Time, First-Year Admission | E188: Basis for Selection | F188: Academic Factors | G188: Undergraduates | H188: First-time, first-year | I188: All | J188: All | K188: All | L188: Text
A189: C704 | B189: Standardized test scores | C189: Considered | D189: First-Time, First-Year Admission | E189: Basis for Selection | F189: Academic Factors | G189: Undergraduates | H189: First-time, first-year | I189: All | J189: All | K189: All | L189: Text
A190: C705 | B190: Application Essay | C190: Important | D190: First-Time, First-Year Admission | E190: Basis for Selection | F190: Academic Factors | G190: Undergraduates | H190: First-time, first-year | I190: All | J190: All | K190: All | L190: Text
A191: C706 | B191: Recommendation(s) | C191: Important | D191: First-Time, First-Year Admission | E191: Basis for Selection | F191: Academic Factors | G191: Undergraduates | H191: First-time, first-year | I191: All | J191: All | K191: All | L191: Text
A194: C707 | B194: Interview | C194: Not Considered | D194: First-Time, First-Year Admission | E194: Basis for Selection | F194: Nonacademic Factors | G194: Undergraduates | H194: First-time, first-year | I194: All | J194: All | K194: All | L194: Text
A195: C708 | B195: Extracurricular activities | C195: Important | D195: First-Time, First-Year Admission | E195: Basis for Selection | F195: Nonacademic Factors | G195: Undergraduates | H195: First-time, first-year | I195: All | J195: All | K195: All | L195: Text
A196: C709 | B196: Talent/ability | C196: Considered | D196: First-Time, First-Year Admission | E196: Basis for Selection | F196: Nonacademic Factors | G196: Undergraduates | H196: First-time, first-year | I196: All | J196: All | K196: All | L196: Text
A197: C710 | B197: Character/personal qualities | C197: Important | D197: First-Time, First-Year Admission | E197: Basis for Selection | F197: Nonacademic Factors | G197: Undergraduates | H197: First-time, first-year | I197: All | J197: All | K197: All | L197: Text
A198: C711 | B198: First generation | C198: Considered | D198: First-Time, First-Year Admission | E198: Basis for Selection | F198: Nonacademic Factors | G198: Undergraduates | H198: First-time, first-year | I198: All | J198: All | K198: All | L198: Text
A199: C712 | B199: Alumni/ae relation | C199: Not Considered | D199: First-Time, First-Year Admission | E199: Basis for Selection | F199: Nonacademic Factors | G199: Undergraduates | H199: First-time, first-year | I199: All | J199: All | K199: All | L199: Text
... A211: C801 | B211: Does your institution make use of SAT or ACT scores in admission decisions for first-time, first-year, degree-seeking applicants? | C211: Y | D211: First-Time, First-Year Admission | E211: Entrance Exams | F211: SAT and ACT Policies | G211: Undergraduates | H211: First-time, first-year | I211: All | J211: All | K211: All | L211: YN
C213: Required to be considered for admission
C214: Required for some
C215: Recommended
C216: Not required for admission, but considered if submitted
C217: Not considered for admission, even if submitted
A221: C802 | B221: SAT or ACT | C221: Not required for admission, but considered if submitted | D221: First-Time, First-Year Admission | E221: Entrance Exams | F221: SAT and ACT Policies | G221: Undergraduates | H221: First-time, first-year | I221: All | J221: All | K221: All | L221: Text
A222: C803 | B222: ACT Only | D222: First-Time, First-Year Admission | E222: Entrance Exams | F222: SAT and ACT Policies | G222: Undergraduates | H222: First-time, first-year | I222: All | J222: All | K222: All | L222: Text
A223: C804 | B223: SAT Only | D223: First-Time, First-Year Admission | E223: Entrance Exams | F223: SAT and ACT Policies | G223: Undergraduates | H223: First-time, first-year | I223: All | J223: All | K223: All | L223: Text
A230: C8D | B230: In addition, does your institution use applicants' test scores for academic advising? | C230: N | D230: First-Time, First-Year Admission | E230: Entrance Exams | F230: SAT and ACT Policies | G230: Undergraduates | H230: First-time, first-year | I230: All | J230: All | K230: All | L230: YN
A232: C8E | B232: Latest date by which SAT or ACT scores must be received for fall-term admission | C232: 46044 | D232: First-Time, First-Year Admission | E232: Entrance Exams | F232: SAT and ACT Policies | G232: Undergraduates | H232: First-time, first-year | I232: All | J232: All | K232: All | L232: YN
A234: C8F | B234: If necessary, use this space to clarify your test policies (e.g., if tests are recommended for some students, or if tests are not required of some students due to differences by academic program, student academic background, or if other examinations may be considered in lieu of the SAT and ACT): | C234: Including scores from either the ACT or the SAT with your application is optional for students applying for admission through the spring 2027 term, with an application deadline of October 1, 2026. You will not be disadvantaged in our evaluation process if you do not include these scores for consideration in your application. You will indicate your choice regarding including test scores at the time of application. The choice that you indicate on your application is final. If choosing to include ACT or SAT test scores with your application, submit your official scores directly from the testing site. | D234: First-Time, First-Year Admission | E234: Entrance Exams | F234: SAT and ACT Policies | G234: Undergraduates | H234: First-time, first-year | I234: All | J234: All | K234: All | L234: YN
A237: C8G | B237: Please indicate which tests your institution uses for placement (e.g., state tests): | D237: First-Time, First-Year Admission | E237: Entrance Exams | F237: SAT and ACT Policies | G237: Undergraduates | H237: First-time, first-year | I237: All | J237: All | K237: All | L237: x
A238: C8G01 | B238: SAT | D238: First-Time, First-Year Admission | E238: Entrance Exams | F238: SAT and ACT Policies | G238: Undergraduates | H238: First-time, first-year | I238: All | J238: All | K238: All | L238: x
...

Sheet CDS-D
A1: Question Number | B1: Question | C1: Answer | D1: Section | E1: Sub-Section | F1: Category | G1: Student Group | H1: Cohort | I1: Residency | J1: Unit load | K1: Gender | L1: Value type
A9: D101 | B9: Does your institution enroll transfer students? (If no, please skip to Section E) | C9: Y | D9: Transfer Admission | E9: Fall Applicants | F9: All | G9: Undergraduates | H9: Transfer | I9: All | J9: All | K9: All | L9: YN
A10: D102 | B10: If yes, may transfer students earn advanced standing credit by transferring credits earned from course work completed at other colleges/universities? | C10: Y | D10: Transfer Admission | E10: Fall Applicants | F10: All | G10: Undergraduates | H10: Transfer | I10: All | J10: All | K10: All | L10: YN
A19: D201 | B19: Men | C19: 2496 | D19: Transfer Admission | E19: Fall Applicants | F19: Applied | G19: Undergraduates | H19: Transfer | I19: All | J19: All | K19: Men | L19: Number
A20: D202 | B20: Women | C20: 2020 | D20: Transfer Admission | E20: Fall Applicants | F20: Applied | G20: Undergraduates | H20: Transfer | I20: All | J20: All | K20: Women | L20: Number
A21: D203 | B21: Another Gender | C21: 0 | D21: Transfer Admission | E21: Fall Applicants | F21: Applied | G21: Undergraduates | H21: Transfer | I21: All | J21: All | K21: Another Gender | L21: Number
A22: D204 | B22: Unknown | C22: 0 | D22: Transfer Admission | E22: Fall Applicants | F22: Applied | G22: Undergraduates | H22: Transfer | I22: All | J22: All | K22: Unknown | L22: Number
A23: D205 | B23: Total | C23: =SUM(C19:C22) | D23: Transfer Admission | E23: Fall Applicants | F23: Applied | G23: Undergraduates | H23: Transfer | I23: All | J23: All | K23: All | L23: Number
A27: D206 | B27: Men | C27: 1386 | D27: Transfer Admission | E27: Fall Applicants | F27: Admitted | G27: Undergraduates | H27: Transfer | I27: All | J27: All | K27: Men | L27: Number
A28: D207 | B28: Women | C28: 1121 | D28: Transfer Admission | E28: Fall Applicants | F28: Admitted | G28: Undergraduates | H28: Transfer | I28: All | J28: All | K28: Women | L28: Number
A29: D208 | B29: Another Gender | C29: 0 | D29: Transfer Admission | E29: Fall Applicants | F29: Admitted | G29: Undergraduates | H29: Transfer | I29: All | J29: All | K29: Another Gender | L29: Number
A30: D209 | B30: Unknown | C30: 0 | D30: Transfer Admission | E30: Fall Applicants | F30: Admitted | G30: Undergraduates | H30: Transfer | I30: All | J30: All | K30: Unknown | L30: Number
A31: D210 | B31: Total | C31: =SUM(C27:C29) | D31: Transfer Admission | E31: Fall Applicants | F31: Admitted | G31: Undergraduates | H31: Transfer | I31: All | J31: All | K31: All | L31: Number
A34: D211 | B34: Men | C34: 746 | D34: Transfer Admission | E34: Fall Applicants | F34: Enrolled | G34: Undergraduates | H34: Transfer | I34: All | J34: All | K34: Men | L34: Number
A35: D212 | B35: Women | C35: 627 | D35: Transfer Admission | E35: Fall Applicants | F35: Enrolled | G35: Undergraduates | H35: Transfer | I35: All | J35: All | K35: Women | L35: Number
A36: D213 | B36: Another Gender | C36: 0 | D36: Transfer Admission | E36: Fall Applicants | F36: Enrolled | G36: Undergraduates | H36: Transfer | I36: All | J36: All | K36: Another Gender | L36: Number
A37: D214 | B37: Unknown | C37: 0 | D37: Transfer Admission | E37: Fall Applicants | F37: Enrolled | G37: Undergraduates | H37: Transfer | I37: All | J37: All | K37: Unknown | L37: Number
A38: D215 | B38: Total | C38: =SUM(C34:C36) | D38: Transfer Admission | E38: Fall Applicants | F38: Enrolled | G38: Undergraduates | H38: Transfer | I38: All | J38: All | K38: All | L38: Number
A44: D301 | B44: Fall | C44: x | D44: Transfer Admission | E44: Application for Admission | F44: Fall | G44: Undergraduates | H44: Transfer | I44: All | J44: All | K44: All | L44: x
A45: D302 | B45: Winter | D45: Transfer Admission | E45: Application for Admission | F45: Winter | G45: Undergraduates | H45: Transfer | I45: All | J45: All | K45: All | L45: x
A46: D303 | B46: Spring | C46: x | D46: Transfer Admission | E46: Application for Admission | F46: Spring | G46: Undergraduates | H46: Transfer | I46: All | J46: All | K46: All | L46: x
A47: D304 | B47: Summer | D47: Transfer Admission | E47: Application for Admission | F47: Summer | G47: Undergraduates | H47: Transfer | I47: All | J47: All | K47: All | L47: x
A50: D401 | B50: Must a transfer applicant have a minimum number of credits completed or else must apply as an entering first-year student? | C50: Y | D50: Transfer Admission | E50: Application for Admission | F50: Min Credits | G50: Undergraduates | H50: Transfer | I50: All | J50: All | K50: All | L50: YN
A55: D402 | B55: Number | C55: 24 | D55: Transfer Admission | E55: Transfer Credit Policies | F55: Min Credits | G55: Undergraduates | H55: Transfer | I55: All | J55: All | K55: All | L55: Number
A56: D403 | B56: Unit Type | C56: Credits | D56: Transfer Admission | E56: Transfer Credit Policies | F56: Min Credits | G56: Undergraduates | H56: Transfer | I56: All | J56: All | K56: All | L56: Unit Type
C59: Required of All
C60: Recommended of All
C61: Recommended of Some
C62: Required of Some
C63: Not Required
A66: D501 | B66: High school transcript | C66: Required of All | D66: Transfer Admission | E66: Application for Admission | F66: Requirements | G66: Undergraduates | H66: Transfer | I66: All | J66: All | K66: All | L66: Text
A67: D502 | B67: College transcript(s) | C67: Required of All | D67: Transfer Admission | E67: Application for Admission | F67: Requirements | G67: Undergraduates | H67: Transfer | I67: All | J67: All | K67: All | L67: Text
A68: D503 | B68: Essay or personal statement | C68: Required of All | D68: Transfer Admission | E68: Application for Admission | F68: Requirements | G68: Undergraduates | H68: Transfer | I68: All | J68: All | K68: All | L68: Text
A69: D504 | B69: Interview | C69: Not Required | D69: Transfer Admission | E69: Application for Admission | F69: Requirements | G69: Undergraduates | H69: Transfer | I69: All | J69: All | K69: All | L69: Text
A70: D505 | B70: Standardized test scores | C70: Not Required | D70: Transfer Admission | E70: Application for Admission | F70: Requirements | G70: Undergraduates | H70: Transfer | I70: All | J70: All | K70: All | L70: Text
A71: D506 | B71: Statement of good standing from prior institution(s) | C71: Not Required | D71: Transfer Admission | E71: Application for Admission | F71: Requirements | G71: Undergraduates | H71: Transfer | I71: All | J71: All | K71: All | L71: Text
A74: D601 | B74: If a minimum high school grade point average is required of transfer applicants, specify (on a 4.0 scale): | D74: Transfer Admission | E74: Application for Admission | F74: Requirements | G74: Undergraduates | H74: Transfer | I74: All | J74: All | K74: All | L74: Round to Nearest Hundredths
A77: D701 | B77: If a minimum college grade point average is required of transfer applicants, specify (on a 4.0 scale): | D77: Transfer Admission | E77: Application for Admission | F77: Requirements | G77: Undergraduates | H77: Transfer | I77: All | J77: All | K77: All | L77: Round to Nearest Hundredths
A80: D801 | B80: List any other application requirements specific to transfer applicants: | D80: Transfer Admission | E80: Application for Admission | F80: Requirements | G80: Undergraduates | H80: Transfer | I80: All | J80: All | K80: All | L80: Text
A88: D901 | B88: Fall | C88: 46054 | D88: Transfer Admission | E88: Application for Admission | F88: Dates | G88: Undergraduates | H88: Transfer | I88: All | J88: All | K88: All | L88: MM-DD
A89: D902 | B89: Winter | D89: Transfer Admission | E89: Application for Admission | F89: Dates | G89: Undergraduates | H89: Transfer | I89: All | J89: All | K89: All | L89: MM-DD
A90: D903 | B90: Spring | D90: Transfer Admission | E90: Application for Admission | F90: Dates | G90: Undergraduates | H90: Transfer | I90: All | J90: All | K90: All | L90: MM-DD
A91: D904 | B91: Summer | D91: Transfer Admission | E91: Application for Admission | F91: Dates | G91: Undergraduates | H91: Transfer | I91: All | J91: All | K91: All | L91: MM-DD
A94: D905 | B94: Fall | C94: 46082 | D94: Transfer Admission | E94: Application for Admission | F94: Dates | G94: Undergraduates | H94: Transfer | I94: All | J94: All | K94: All | L94: MM-DD
A95: D906 | B95: Winter | D95: Transfer Admission | E95: Application for Admission | F95: Dates | G95: Undergraduates | H95: Transfer | I95: All | J95: All | K95: All | L95: MM-DD
A96: D907 | B96: Spring | C96: 45931 | D96: Transfer Admission | E96: Application for Admission | F96: Dates | G96: Undergraduates | H96: Transfer | I96: All | J96: All | K96: All | L96: MM-DD
A97: D908 | B97: Summer | D97: Transfer Admission | E97: Application for Admission | F97: Dates | G97: Undergraduates | H97: Transfer | I97: All | J97: All | K97: All | L97: MM-DD
A100: D909 | B100: Fall | C100: 46112 | D100: Transfer Admission | E100: Application for Admission | F100: Dates | G100: Undergraduates | H100: Transfer | I100: All | J100: All | K100: All | L100: MM-DD
A101: D910 | B101: Winter | D101: Transfer Admission | E101: Application for Admission | F101: Dates | G101: Undergraduates | H101: Transfer | I101: All | J101: All | K101: All | L101: MM-DD
A102: D911 | B102: Spring | C102: 46022 | D102: Transfer Admission | E102: Application for Admission | F102: Dates | G102: Undergraduates | H102: Transfer | I102: All | J102: All | K102: All | L102: MM-DD
A103: D912 | B103: Summer | D103: Transfer Admission | E103: Application for Admission | F103: Dates | G103: Undergraduates | H103: Transfer | I103: All | J103: All | K103: All | L103: MM-DD
A106: D913 | B106: Fall | C106: 46174 | D106: Transfer Admission | E106: Application for Admission | F106: Dates | G106: Undergraduates | H106: Transfer | I106: All | J106: All | K106: All | L106: MM-DD
A107: D914 | B107: Winter | D107: Transfer Admission | E107: Application for Admission | F107: Dates | G107: Undergraduates | H107: Transfer | I107: All | J107: All | K107: All | L107: MM-DD
A108: D915 | B108: Spring | C108: 46006 | D108: Transfer Admission | E108: Application for Admission | F108: Dates | G108: Undergraduates | H108: Transfer | I108: All | J108: All | K108: All | L108: MM-DD
A109: D916 | B109: Summer | D109: Transfer Admission | E109: Application for Admission | F109: Dates | G109: Undergraduates | H109: Transfer | I109: All | J109: All | K109: All | L109: MM-DD
A112: D917 | B112: Fall | D112: Transfer Admission | E112: Application for Admission | F112: Dates | G112: Undergraduates | H112: Transfer | I112: All | J112: All | K112: All | L112: MM-DD
A113: D918 | B113: Winter | D113: Transfer Admission | E113: Application for Admission | F113: Dates | G113: Undergraduates | H113: Transfer | I113: All | J113: All | K113: All | L113: MM-DD
A114: D919 | B114: Spring | D114: Transfer Admission | E114: Application for Admission | F114: Dates | G114: Undergraduates | H114: Transfer | I114: All | J114: All | K114: All | L114: MM-DD
A115: D920 | B115: Summer | D115: Transfer Admission | E115: Application for Admission | F115: Dates | G115: Undergraduates | H115: Transfer | I115: All | J115: All | K115: All | L115: MM-DD
A118: D1001 | B118: Does an open admission policy, if reported, apply to transfer students? | C118: N | D118: Transfer Admission | E118: Application for Admission | F118: Requirements | G118: Undergraduates | H118: Transfer | I118: All | J118: All | K118: All | L118: YN
A121: D1101 | B121: Describe additional requirements for transfer admission, if applicable: | C121: See https://admissions.wisc.edu/transfer-agreements/ for transfer agreements | D121: Transfer Admission | E121: Application for Admission | F121: Requirements | G121: Undergraduates | H121: Transfer | I121: All | J121: All | K121: All | L121: Text
A129: D1201 | B129: Report the lowest grade earned for any course that may be transferred for credit: | C129: D | D129: Transfer Admission | E129: Transfer Credit Policies | F129: Min Grade | G129: Undergraduates | H129: Transfer | I129: All | J129: All | K129: All | L129: Text
A133: D1301 | B133: Number | C133: 72 | D133: Transfer Admission | E133: Transfer Credit Policies | F133: Max Credits from Two-Year | G133: Undergraduates | H133: Transfer | I133: All | J133: All | K133: All | L133: Number
A134: D1302 | B134: Unit Type | C134: Credits | D134: Transfer Admission | E134: Transfer Credit Policies | F134: Max Credits from Two-Year | G134: Undergraduates | H134: Transfer | I134: All | J134: All | K134: All | L134: Unit Type
A138: D1401 | B138: Number | D138: Transfer Admission | E138: Transfer Credit Policies | F138: Max Credits from Four-Year | G138: Undergraduates | H138: Transfer | I138: All | J138: All | K138: All | L138: Number
A139: D1402 | B139: Unit Type | D139: Transfer Admission | E139: Transfer Credit Policies | F139: Max Credits from Four-Year | G139: Undergraduates | H139: Transfer | I139: All | J139: All | K139: All | L139: Unit Type
A142: D1501 | B142: Minimum number of credits that transfers must complete at your institution to earn an associate degree: | D142: Transfer Admission | E142: Transfer Credit Policies | F142: Min Credits | G142: Undergraduates | H142: Transfer | I142: All | J142: All | K142: All | L142: Number
A145: D1601 | B145: Minimum number of credits that transfers must complete at your institution to earn a bachelor’s degree: | C145: 30 | D145: Transfer Admission | E145: Transfer Credit Policies | F145: Min Credits | G145: Undergraduates | H145: Transfer | I145: All | J145: All | K145: All | L145: Number
A148: D1701 | B148: Describe other transfer credit policies: | C148: We have several transfer agreements with institutions: https://admissions.wisc.edu/transfer‐ agreements/ | D148: Transfer Admission | E148: Transfer Credit Policies | F148: Other Credit | G148: Undergraduates | H148: Transfer | I148: All | J148: All | K148: All | L148: Text
A157: D1801 | B157: American Council on Education (ACE) | C157: Y | D157: Transfer Admission | E157: Transfer Credit Policies | F157: Military Service Credits | G157: Undergraduates | H157: Transfer | I157: All | J157: All | K157: All | L157: YN
A158: D1802 | B158: College Level Examination Program (CLEP) | C158: Y | D158: Transfer Admission | E158: Transfer Credit Policies | F158: Military Service Credits | G158: Undergraduates | H158: Transfer | I158: All | J158: All | K158: All | L158: YN
A159: D1803 | B159: DANTES Subject Standardized Tests (DSST) | D159: Transfer Admission | E159: Transfer Credit Policies | F159: Military Service Credits | G159: Undergraduates | H159: Transfer | I159: All | J159: All | K159: All | L159: YN
A163: D1901 | B163: Number | D163: Transfer Admission | E163: Transfer Credit Policies | F163: ACE Evaluated | G163: Undergraduates | H163: Transfer | I163: All | J163: All | K163: All | L163: Number
A164: D1902 | B164: Unit Type | D164: Transfer Admission | E164: Transfer Credit Policies | F164: ACE Evaluated | G164: Undergraduates | H164: Transfer | I164: All | J164: All | K164: All | L164: Unit Type
A168: D2001 | B168: Number | C168: 16 | D168: Transfer Admission | E168: Transfer Credit Policies | F168: DoD Supported | G168: Undergraduates | H168: Transfer | I168: All | J168: All | K168: All | L168: Number
A169: D2002 | B169: Unit Type | C169: Credits | D169: Transfer Admission | E169: Transfer Credit Policies | F169: DoD Supported | G169: Undergraduates | H169: Transfer | I169: All | J169: All | K169: All | L169: Unit Type
A172: D2101 | B172: Are the military/veteran credit transfer policies published on your website? | C172: Y | D172: Transfer Admission | E172: Transfer Credit Policies | F172: Military Service | G172: Undergraduates | H172: Transfer | I172: All | J172: All | K172: All | L172: YN
A174: D2102 | B174: If yes, please provide the URL where the policy can be located: | C174: https://admissions.wisc.edu/veterans-and-active-military/ | D174: Transfer Admission | E174: Transfer Credit Policies | F174: Military Service | G174: Undergraduates | H174: Transfer | I174: All | J174: All | K174: All | L174: URL
A177: D2202 | B177: Describe other military/veteran transfer credit policies unique to your institution: | D177: Transfer Admission | E177: Transfer Credit Policies | F177: Military Service | G177: Undergraduates | H177: Transfer | I177: All | J177: All | K177: All | L177: Text

Sheet CDS-E
A1: Question Number | B1: Question | C1: Answer | D1: Section | E1: Sub-Section | F1: Category | G1: Student Group | H1: Cohort | I1: Residency | J1: Unit load | K1: Gender | L1: Value type
A10: E101 | B10: Accelerated program | C10: x | D10: Academic Offerings and Policies | E10: Special Study Options | F10: All | G10: All | H10: All | I10: All | J10: All | K10: All | L10: x
A11: E102 | B11: Comprehensive transition and postsecondary program for students with intellectual disabilities | D11: Academic Offerings and Policies | E11: Special Study Options | F11: All | G11: All | H11: All | I11: All | J11: All | K11: All | L11: x
A12: E103 | B12: Cross-registration | D12: Academic Offerings and Policies | E12: Special Study Options | F12: All | G12: All | H12: All | I12: All | J12: All | K12: All | L12: x
A13: E104 | B13: Distance learning | C13: x | D13: Academic Offerings and Policies | E13: Special Study Options | F13: All | G13: All | H13: All | I13: All | J13: All | K13: All | L13: x
A14: E105 | B14: Double major | C14: x | D14: Academic Offerings and Policies | E14: Special Study Options | F14: All | G14: All | H14: All | I14: All | J14: All | K14: All | L14: x
A15: E106 | B15: Dual enrollment | D15: Academic Offerings and Policies | E15: Special Study Options | F15: All | G15: All | H15: All | I15: All | J15: All | K15: All | L15: x
A16: E107 | B16: English as a Second Language (ESL) | D16: Academic Offerings and Policies | E16: Special Study Options | F16: All | G16: All | H16: All | I16: All | J16: All | K16: All | L16: x
A17: E108 | B17: Exchange student program (domestic) | C17: x | D17: Academic Offerings and Policies | E17: Special Study Options | F17: All | G17: All | H17: All | I17: All | J17: All | K17: All | L17: x
A18: E109 | B18: External degree program | D18: Academic Offerings and Policies | E18: Special Study Options | F18: All | G18: All | H18: All | I18: All | J18: All | K18: All | L18: x
A19: E110 | B19: Honors Program | C19: x | D19: Academic Offerings and Policies | E19: Special Study Options | F19: All | G19: All | H19: All | I19: All | J19: All | K19: All | L19: x
A20: E111 | B20: Independent study | C20: x | D20: Academic Offerings and Policies | E20: Special Study Options | F20: All | G20: All | H20: All | I20: All | J20: All | K20: All | L20: x
A21: E112 | B21: Internships | C21: x | D21: Academic Offerings and Policies | E21: Special Study Options | F21: All | G21: All | H21: All | I21: All | J21: All | K21: All | L21: x
A22: E113 | B22: Liberal arts/career combination | C22: x | D22: Academic Offerings and Policies | E22: Special Study Options | F22: All | G22: All | H22: All | I22: All | J22: All | K22: All | L22: x
A23: E114 | B23: Student-designed major | C23: x | D23: Academic Offerings and Policies | E23: Special Study Options | F23: All | G23: All | H23: All | I23: All | J23: All | K23: All | L23: x
A24: E115 | B24: Study abroad | C24: x | D24: Academic Offerings and Policies | E24: Special Study Options | F24: All | G24: All | H24: All | I24: All | J24: All | K24: All | L24: x
A25: E116 | B25: Teacher certification program | C25: x | D25: Academic Offerings and Policies | E25: Special Study Options | F25: All | G25: All | H25: All | I25: All | J25: All | K25: All | L25: x
A26: E117 | B26: Undergraduate Research | C26: x | D26: Academic Offerings and Policies | E26: Special Study Options | F26: All | G26: All | H26: All | I26: All | J26: All | K26: All | L26: x
A27: E118 | B27: Weekend college | D27: Academic Offerings and Policies | E27: Special Study Options | F27: All | G27: All | H27: All | I27: All | J27: All | K27: All | L27: x
A29: E119 | B29: Other (specify): | D29: Academic Offerings and Policies | E29: Special Study Options | F29: All | G29: All | H29: All | I29: All | J29: All | K29: All | L29: Text
A39: E301 | B39: Arts/fine arts | D39: Academic Offerings and Policies | E39: Required Course Work | F39: All | G39: All | H39: All | I39: All | J39: All | K39: All | L39: x
A40: E302 | B40: Computer literacy | D40: Academic Offerings and Policies | E40: Required Course Work | F40: All | G40: All | H40: All | I40: All | J40: All | K40: All | L40: x
A41: E303 | B41: English (including composition) | C41: x | D41: Academic Offerings and Policies | E41: Required Course Work | F41: All | G41: All | H41: All | I41: All | J41: All | K41: All | L41: x
A42: E304 | B42: Foreign languages | C42: x | D42: Academic Offerings and Policies | E42: Required Course Work | F42: All | G42: All | H42: All | I42: All | J42: All | K42: All | L42: x
A43: E305 | B43: History | C43: x | D43: Academic Offerings and Policies | E43: Required Course Work | F43: All | G43: All | H43: All | I43: All | J43: All | K43: All | L43: x
A44: E306 | B44: Physical Education | D44: Academic Offerings and Policies | E44: Required Course Work | F44: All | G44: All | H44: All | I44: All | J44: All | K44: All | L44: x
A45: E307 | B45: Humanities | C45: x | D45: Academic Offerings and Policies | E45: Required Course Work | F45: All | G45: All | H45: All | I45: All | J45: All | K45: All | L45: x
A46: E308 | B46: Intensive writing | C46: x | D46: Academic Offerings and Policies | E46: Required Course Work | F46: All | G46: All | H46: All | I46: All | J46: All | K46: All | L46: x
A47: E309 | B47: Mathematics | C47: x | D47: Academic Offerings and Policies | E47: Required Course Work | F47: All | G47: All | H47: All | I47: All | J47: All | K47: All | L47: x
A48: E310 | B48: Philosophy | D48: Academic Offerings and Policies | E48: Required Course Work | F48: All | G48: All | H48: All | I48: All | J48: All | K48: All | L48: x
A49: E311 | B49: Sciences (biological or physical) | C49: x | D49: Academic Offerings and Policies | E49: Required Course Work | F49: All | G49: All | H49: All | I49: All | J49: All | K49: All | L49: x
A50: E312 | B50: Social science | C50: x | D50: Academic Offerings and Policies | E50: Required Course Work | F50: All | G50: All | H50: All | I50: All | J50: All | K50: All | L50: x
A52: E313 | B52: Other (describe): | C52: Ethnic Studies Requirement | D52: Academic Offerings and Policies | E52: Required Course Work | F52: All | G52: All | H52: All | I52: All | J52: All | K52: All | L52: Text

Sheet CDS-F
A1: Question Number | B1: Question | C1: Answer | D1: Section | E1: Sub-Section | F1: Category | G1: Student Group | H1: Cohort | I1: Residency | J1: Unit load | K1: Gender | L1: Value type
A10: F101 | B10: Percent who are from out of state (exclude international/nonresidents from the numerator and denominator) | C10: 51 | D10: Student Life | E10: Percent Participating | F10: Degree-Seeking | G10: Undergraduates | H10: First-time, first-year | I10: All | J10: All | K10: All | L10: Nearest 1%
A11: F102 | B11: Percent of men who join fraternities | C11: 9 | D11: Student Life | E11: Percent Participating | F11: Degree-Seeking | G11: Undergraduates | H11: First-time, first-year | I11: All | J11: All | K11: All | L11: Nearest 1%
A12: F103 | B12: Percent of women who join sororities | C12: 8 | D12: Student Life | E12: Percent Participating | F12: Degree-Seeking | G12: Undergraduates | H12: First-time, first-year | I12: All | J12: All | K12: All | L12: Nearest 1%
A13: F104 | B13: Percent who live in college-owned, -operated, or -affiliated housing | C13: 93 | D13: Student Life | E13: Percent Participating | F13: Degree-Seeking | G13: Undergraduates | H13: First-time, first-year | I13: All | J13: All | K13: All | L13: Nearest 1%
A14: F105 | B14: Percent who live off campus or commute | C14: 7 | D14: Student Life | E14: Percent Participating | F14: Degree-Seeking | G14: Undergraduates | H14: First-time, first-year | I14: All | J14: All | K14: All | L14: Nearest 1%
A15: F106 | B15: Percent of students age 25 and older | C15: 0 | D15: Student Life | E15: Percent Participating | F15: Degree-Seeking | G15: Undergraduates | H15: First-time, first-year | I15: All | J15: All | K15: All | L15: Nearest 1%
A18: F107 | B18: Average age of full-time students | C18: 18 | D18: Student Life | E18: Average Age | F18: Degree-Seeking | G18: Undergraduates | H18: First-time, first-year | I18: All | J18: All | K18: All | L18: Whole Number or Round to Nearest Tenths
A19: F108 | B19: Average age of all students (full- and part-time) | C19: 18 | D19: Student Life | E19: Average Age | F19: Degree-Seeking | G19: Undergraduates | H19: First-time, first-year | I19: All | J19: All | K19: All | L19: Whole Number or Round to Nearest Tenths
A22: F109 | B22: Percent who are from out of state (exclude international/nonresidents from the numerator and denominator) | C22: 46 | D22: Student Life | E22: Percent Participating | F22: Degree-Seeking | G22: Undergraduates | H22: Undergraduates | I22: All | J22: All | K22: All | L22: Nearest 1%
A23: F110 | B23: Percent of men who join fraternities | C23: 9 | D23: Student Life | E23: Percent Participating | F23: Degree-Seeking | G23: Undergraduates | H23: Undergraduates | I23: All | J23: All | K23: All | L23: Nearest 1%
A24: F111 | B24: Percent of women who join sororities | C24: 8 | D24: Student Life | E24: Percent Participating | F24: Degree-Seeking | G24: Undergraduates | H24: Undergraduates | I24: All | J24: All | K24: All | L24: Nearest 1%
A25: F112 | B25: Percent who live in college-owned, -operated, or -affiliated housing | C25: 25 | D25: Student Life | E25: Percent Participating | F25: Degree-Seeking | G25: Undergraduates | H25: Undergraduates | I25: All | J25: All | K25: All | L25: Nearest 1%
... A31: F116 | B31: Average age of all students (full- and part-time) | C31: 20 | D31: Student Life | E31: Average Age | F31: Degree-Seeking | G31: Undergraduates | H31: Undergraduates | I31: All | J31: All | K31: All | L31: Whole Number or Round to Nearest Tenths
A37: F201 | B37: Campus Ministries | D37: Student Life | E37: Activities Offered | F37: All | G37: All | H37: All | I37: All | J37: All | K37: All | L37: x
A38: F202 | B38: Choral groups | C38: x | D38: Student Life | E38: Activities Offered | F38: All | G38: All | H38: All | I38: All | J38: All | K38: All | L38: x
A39: F203 | B39: Concert band | C39: x | D39: Student Life | E39: Activities Offered | F39: All | G39: All | H39: All | I39: All | J39: All | K39: All | L39: x
A40: F204 | B40: Dance | C40: x | D40: Student Life | E40: Activities Offered | F40: All | G40: All | H40: All | I40: All | J40: All | K40: All | L40: x
A41: F205 | B41: Drama/theater | C41: x | D41: Student Life | E41: Activities Offered | F41: All | G41: All | H41: All | I41: All | J41: All | K41: All | L41: x
A42: F206 | B42: International Student Organization | C42: x | D42: Student Life | E42: Activities Offered | F42: All | G42: All | H42: All | I42: All | J42: All | K42: All | L42: x
A43: F207 | B43: Jazz band | C43: x | D43: Student Life | E43: Activities Offered | F43: All | G43: All | H43: All | I43: All | J43: All | K43: All | L43: x
A44: F208 | B44: Literary magazine | C44: x | D44: Student Life | E44: Activities Offered | F44: All | G44: All | H44: All | I44: All | J44: All | K44: All | L44: x
A45: F209 | B45: Marching band | C45: x | D45: Student Life | E45: Activities Offered | F45: All | G45: All | H45: All | I45: All | J45: All | K45: All | L45: x
A46: F210 | B46: Model UN | D46: Student Life | E46: Activities Offered | F46: All | G46: All | H46: All | I46: All | J46: All | K46: All | L46: x
A47: F211 | B47: Music ensembles | C47: x | D47: Student Life | E47: Activities Offered | F47: All | G47: All | H47: All | I47: All | J47: All | K47: All | L47: x
A48: F212 | B48: Musical theater | C48: x | D48: Student Life | E48: Activities Offered | F48: All | G48: All | H48: All | I48: All | J48: All | K48: All | L48: x
A49: F213 | B49: Opera | C49: x | D49: Student Life | E49: Activities Offered | F49: All | G49: All | H49: All | I49: All | J49: All | K49: All | L49: x
A50: F214 | B50: Pep band | C50: x | D50: Student Life | E50: Activities Offered | F50: All | G50: All | H50: All | I50: All | J50: All | K50: All | L50: x
A51: F215 | B51: Radio station | C51: x | D51: Student Life | E51: Activities Offered | F51: All | G51: All | H51: All | I51: All | J51: All | K51: All | L51: x
A52: F216 | B52: Student government | C52: x | D52: Student Life | E52: Activities Offered | F52: All | G52: All | H52: All | I52: All | J52: All | K52: All | L52: x
A53: F217 | B53: Student newspaper | C53: x | D53: Student Life | E53: Activities Offered | F53: All | G53: All | H53: All | I53: All | J53: All | K53: All | L53: x
A54: F218 | B54: Student-run film society | C54: x | D54: Student Life | E54: Activities Offered | F54: All | G54: All | H54: All | I54: All | J54: All | K54: All | L54: x
A55: F219 | B55: Symphony orchestra | C55: x | D55: Student Life | E55: Activities Offered | F55: All | G55: All | H55: All | I55: All | J55: All | K55: All | L55: x
A56: F220 | B56: Television station | C56: x | D56: Student Life | E56: Activities Offered | F56: All | G56: All | H56: All | I56: All | J56: All | K56: All | L56: x
A57: F221 | B57: Yearbook | C57: x | D57: Student Life | E57: Activities Offered | F57: All | G57: All | H57: All | I57: All | J57: All | K57: All | L57: x
A64: F301 | B64: On Campus | C64: x | D64: Student Life | E64: ROTC | F64: Army | G64: All | H64: All | I64: All | J64: All | K64: All | L64: x
A65: F302 | B65: At Cooperating Institution | D65: Student Life | E65: ROTC | F65: Army | G65: All | H65: All | I65: All | J65: All | K65: All | L65: x
A67: F303 | B67: Name of Cooperating Institution | D67: Student Life | E67: ROTC | F67: Army | G67: All | H67: All | I67: All | J67: All | K67: All | L67: Text
A70: F304 | B70: Marine Option (for Naval ROTC) | C70: x | D70: Student Life | E70: ROTC | F70: Army | G70: All | H70: All | I70: All | J70: All | K70: All | L70: x
A71: F305 | B71: On Campus | C71: x | D71: Student Life | E71: ROTC | F71: Army | G71: All | H71: All | I71: All | J71: All | K71: All | L71: x
A72: F306 | B72: At Cooperating Institution | D72: Student Life | E72: ROTC | F72: Army | G72: All | H72: All | I72: All | J72: All | K72: All | L72: x
A74: F307 | B74: Name of Cooperating Institution | D74: Student Life | E74: ROTC | F74: Army | G74: All | H74: All | I74: All | J74: All | K74: All | L74: Text
A77: F308 | B77: On Campus | C77: x | D77: Student Life | E77: ROTC | F77: Army | G77: All | H77: All | I77: All | J77: All | K77: All | L77: x
A78: F309 | B78: At Cooperating Institution | D78: Student Life | E78: ROTC | F78: Army | G78: All | H78: All | I78: All | J78: All | K78: All | L78: x
A80: F310 | B80: Name of Cooperating Institution | D80: Student Life | E80: ROTC | F80: Army | G80: All | H80: All | I80: All | J80: All | K80: All | L80: Text
A87: F401 | B87: Coed dorms | C87: x | D87: Student Life | E87: Housing | F87: All | G87: All | H87: All | I87: All | J87: All | K87: All | L87: x
A88: F402 | B88: Men's dorms | C88: x | D88: Student Life | E88: Housing | F88: All | G88: All | H88: All | I88: All | J88: All | K88: Men | L88: x
A89: F403 | B89: Women's dorms | C89: x | D89: Student Life | E89: Housing | F89: All | G89: All | H89: All | I89: All | J89: All | K89: Women | L89: x
A90: F404 | B90: Apartments for married students | D90: Student Life | E90: Housing | F90: All | G90: All | H90: All | I90: All | J90: All | K90: All | L90: x
A91: F405 | B91: Apartments for single students | D91: Student Life | E91: Housing | F91: All | G91: All | H91: All | I91: All | J91: All | K91: All | L91: x
A92: F406 | B92: Special housing for disabled students | D92: Student Life | E92: Housing | F92: All | G92: All | H92: All | I92: All | J92: All | K92: All | L92: x
A93: F407 | B93: Special housing for international students | C93: x | D93: Student Life | E93: Housing | F93: All | G93: All | H93: All | I93: All | J93: All | K93: All | L93: x
A94: F408 | B94: Fraternity/sorority housing | C94: x | D94: Student Life | E94: Housing | F94: All | G94: All | H94: All | I94: All | J94: All | K94: All | L94: x
A95: F409 | B95: Cooperative housing | D95: Student Life | E95: Housing | F95: All | G95: All | H95: All | I95: All | J95: All | K95: All | L95: x
A96: F410 | B96: Theme housing | C96: x | D96: Student Life | E96: Housing | F96: All | G96: All | H96: All | I96: All | J96: All | K96: All | L96: x
A97: F411 | B97: Wellness housing | D97: Student Life | E97: Housing | F97: All | G97: All | H97: All | I97: All | J97: All | K97: All | L97: x
A98: F412 | B98: Living Learning Communities | C98: x | D98: Student Life | E98: Housing | F98: All | G98: All | H98: All | I98: All | J98: All | K98: All | L98: x
A100: F413 | B100: Other housing options (specify): | C100: Apartments for student families | D100: Student Life | E100: Housing | F100: All | G100: All | H100: All | I100: All | J100: All | K100: All | L100: Text

Sheet CDS-G
A1: Question Number | B1: Question | C1: Answer | D1: Section | E1: Sub-Section | F1: Category | G1: Student Group | H1: Cohort | I1: Residency | J1: Unit load | K1: Gender | L1: Value type
A7: G001 | B7: Please provide the URL of your institution’s net price calculator: | C7: https://app.meadowfi.com/wisconsin | D7: Annual Expenses | E7: Information | F7: All | G7: All | H7: All | I7: All | J7: All | K7: All | L7: URL
A9: G002 | B9: If your institution's 2025-2026 academic year costs of attendance are not available at this time please respond. | C9: x | D9: Annual Expenses | E9: Information | F9: All | G9: All | H9: All | I9: All | J9: All | K9: All | L9: x
A11: G003 | B11: Please provide an approximate date (i.e., month/day) when your institution's final 2025-2026 academic year costs of attendance will be available: | C11: 45870 | D11: Annual Expenses | E11: Information | F11: All | G11: All | H11: All | I11: All | J11: All | K11: All | L11: MM-DD
A26: G101 | B26: Tuition | D26: Annual Expenses | E26: Private Tuition | F26: Full-Time | G26: Undergraduate | H26: First-year | I26: All | J26: All | K26: All | L26: Nearest $1
A29: G102 | B29: Tuition | D29: Annual Expenses | E29: Private Tuition | F29: Full-Time | G29: Undergraduate | H29: Undergraduates | I29: All | J29: All | K29: All | L29: Nearest $1
A32: G103 | B32: Tuition: In-district | C32: 10506.48 | D32: Annual Expenses | E32: Public Tuition | F32: Full-Time | G32: Undergraduate | H32: First-year | I32: All | J32: All | K32: All | L32: Nearest $1
A33: G104 | B33: Tuition: In-state (out-of-district): | C33: 10506.48 | D33: Annual Expenses | E33: Public Tuition | F33: Full-Time | G33: Undergraduate | H33: First-year | I33: All | J33: All | K33: All | L33: Nearest $1
A34: G105 | B34: Tuition: Out-of-state: | C34: 42530.88 | D34: Annual Expenses | E34: Public Tuition | F34: Full-Time | G34: Undergraduate | H34: First-year | I34: All | J34: All | K34: All | L34: Nearest $1
A35: G106 | B35: Tuition: Non-resident | C35: 43530.96 | D35: Annual Expenses | E35: Public Tuition | F35: Full-Time | G35: Undergraduate | H35: First-year | I35: All | J35: All | K35: All | L35: Nearest $1
A38: G107 | B38: Tuition: In-district | C38: 10506.48 | D38: Annual Expenses | E38: Public Tuition | F38: Full-Time | G38: Undergraduate | H38: Undergraduates | I38: All | J38: All | K38: All | L38: Nearest $1
A39: G108 | B39: Tuition: In-state (out-of-district): | C39: 10506.48 | D39: Annual Expenses | E39: Public Tuition | F39: Full-Time | G39: Undergraduate | H39: Undergraduates | I39: All | J39: All | K39: All | L39: Nearest $1
A40: G109 | B40: Tuition: Out-of-state: | C40: 42530.88 | D40: Annual Expenses | E40: Public Tuition | F40: Full-Time | G40: Undergraduate | H40: Undergraduates | I40: All | J40: All | K40: All | L40: Nearest $1
A41: G110 | B41: Tuition: Non-resident | C41: 43530.96 | D41: Annual Expenses | E41: Public Tuition | F41: Full-Time | G41: Undergraduate | H41: Undergraduates | I41: All | J41: All | K41: All | L41: Nearest $1
A44: G111 | B44: Required Fees: | C44: 1659.98 | D44: Annual Expenses | E44: All Institutions Expenses | F44: Full-Time | G44: Undergraduate | H44: First-year | I44: All | J44: All | K44: All | L44: Nearest $1
A45: G112 | B45: Food and housing (on-campus): | C45: 14520 | D45: Annual Expenses | E45: All Institutions Expenses | F45: Full-Time | G45: Undergraduate | H45: First-year | I45: All | J45: All | K45: All | L45: Nearest $1
A46: G113 | B46: Housing Only (on-campus): | D46: Annual Expenses | E46: All Institutions Expenses | F46: Full-Time | G46: Undergraduate | H46: First-year | I46: All | J46: All | K46: All | L46: Nearest $1
A47: G114 | B47: Food Only (on-campus meal plan): | D47: Annual Expenses | E47: All Institutions Expenses | F47: Full-Time | G47: Undergraduate | H47: First-year | I47: All | J47: All | K47: All | L47: Nearest $1
A50: G115 | B50: Required Fees: | C50: 1660 | D50: Annual Expenses | E50: All Institutions Expenses | F50: Full-Time | G50: Undergraduate | H50: Undergraduates | I50: All | J50: All | K50: All | L50: Nearest $1
A51: G116 | B51: Food and housing (on-campus): | C51: 14520 | D51: Annual Expenses | E51: All Institutions Expenses | F51: Full-Time | G51: Undergraduate | H51: Undergraduates | I51: All | J51: All | K51: All | L51: Nearest $1
A52: G117 | B52: Housing Only (on-campus): | D52: Annual Expenses | E52: All Institutions Expenses | F52: Full-Time | G52: Undergraduate | H52: Undergraduates | I52: All | J52: All | K52: All | L52: Nearest $1
A53: G118 | B53: Food Only (on-campus meal plan): | D53: Annual Expenses | E53: All Institutions Expenses | F53: Full-Time | G53: Undergraduate | H53: Undergraduates | I53: All | J53: All | K53: All | L53: Nearest $1
A56: G119 | B56: Comprehensive tuition and food and housing fee (if your college cannot provide separate tuition and food and housing fees): | D56: Annual Expenses | E56: Comprehensive Expenses | F56: Full-Time | G56: Undergraduate | H56: All | I56: All | J56: All | K56: All | L56: Nearest $1
A59: G120 | B59: Other: | D59: Annual Expenses | E59: Comprehensive Expenses | F59: Full-Time | G59: Undergraduate | H59: All | I59: All | J59: All | K59: All | L59: Nearest $1
A62: G201 | B62: Minimum | C62: 12 | D62: Annual Expenses | E62: Credits per Term | F62: Full-Time | G62: Undergraduate | H62: All | I62: All | J62: All | K62: All | L62: Number
A63: G202 | B63: Maximum | C63: 18 | D63: Annual Expenses | E63: Credits per Term | F63: Full-Time | G63: Undergraduate | H63: All | I63: All | J63: All | K63: All | L63: Number
A66: G301 | B66: Do tuition and fees vary by year of study (e.g., sophomore, junior, senior)? | C66: N | D66: Annual Expenses | E66: Tuition Policies | F66: All | G66: All | H66: All | I66: All | J66: All | K66: All | L66: YN
A69: G401 | B69: Do tuition and fees vary by undergraduate instructional program? | C69: Y | D69: Annual Expenses | E69: Tuition Policies | F69: All | G69: All | H69: All | I69: All | J69: All | K69: All | L69: YN
A71: G402 | B71: If yes, what percentage of full-time undergraduates pay more than the tuition and fees reported in G1? | C71: 0.26 | D71: Annual Expenses | E71: Tuition Policies | F71: All | G71: All | H71: All | I71: All | J71: All | K71: All | L71: Nearest 1%
A78: G501 | B78: Books and supplies: | C78: 700 | D78: Annual Expenses | E78: Estimated Expenses | F78: Full-Time | G78: Undergraduate | H78: Residents | I78: All | J78: All | K78: All | L78: Nearest $1
A79: G502 | B79: Transportation: | C79: 600 | D79: Annual Expenses | E79: Estimated Expenses | F79: Full-Time | G79: Undergraduate | H79: Residents | I79: All | J79: All | K79: All | L79: Nearest $1
A80: G503 | B80: Other expenses: | C80: 2638 | D80: Annual Expenses | E80: Estimated Expenses | F80: Full-Time | G80: Undergraduate | H80: Residents | I80: All | J80: All | K80: All | L80: Nearest $1
A83: G504 | B83: Books and supplies: | C83: 700 | D83: Annual Expenses | E83: Estimated Expenses | F83: Full-Time | G83: Undergraduate | H83: Commuters (living at home) | I83: All | J83: All | K83: All | L83: Nearest $1
A84: G505 | B84: Food only: | C84: 4418 | D84: Annual Expenses | E84: Estimated Expenses | F84: Full-Time | G84: Undergraduate | H84: Commuters (living at home) | I84: All | J84: All | K84: All | L84: Nearest $1
A85: G506 | B85: Transportation | C85: 1300 | D85: Annual Expenses | E85: Estimated Expenses | F85: Full-Time | G85: Undergraduate | H85: Commuters (living at home) | I85: All | J85: All | K85: All | L85: Nearest $1
A86: G507 | B86: Other expenses: | C86: 2638 | D86: Annual Expenses | E86: Estimated Expenses | F86: Full-Time | G86: Undergraduate | H86: Commuters (living at home) | I86: All | J86: All | K86: All | L86: Nearest $1
A89: G508 | B89: Books and supplies: | C89: 700 | D89: Annual Expenses | E89: Estimated Expenses | F89: Full-Time | G89: Undergraduate | H89: Commuters (not living at home) | I89: All | J89: All | K89: All | L89: Nearest $1
A90: G509 | B90: Housing only: | D90: Annual Expenses | E90: Estimated Expenses | F90: Full-Time | G90: Undergraduate | H90: Commuters (not living at home) | I90: All | J90: All | K90: All | L90: Nearest $1
A91: G510 | B91: Food only: | D91: Annual Expenses | E91: Estimated Expenses | F91: Full-Time | G91: Undergraduate | H91: Commuters (not living at home) | I91: All | J91: All | K91: All | L91: Nearest $1
A92: G511 | B92: Food and housing total* | C92: 14520 | D92: Annual Expenses | E92: Estimated Expenses | F92: Full-Time | G92: Undergraduate | H92: Commuters (not living at home) | I92: All | J92: All | K92: All | L92: Nearest $1
A93: G512 | B93: Transportation: | C93: 1200 | D93: Annual Expenses | E93: Estimated Expenses | F93: Full-Time | G93: Undergraduate | H93: Commuters (not living at home) | I93: All | J93: All | K93: All | L93: Nearest $1
A94: G513 | B94: Other expenses: | C94: 2638 | D94: Annual Expenses | E94: Estimated Expenses | F94: Full-Time | G94: Undergraduate | H94: Commuters (not living at home) | I94: All | J94: All | K94: All | L94: Nearest $1
A100: G601 | B100: PRIVATE INSTITUTIONS: | D100: Annual Expenses | E100: Per-Credit-Hour Charges | F100: Full-Time | G100: Undergraduate | H100: All | I100: All | J100: All | K100: All | L100: Nearest $1
A101: G602 | B101: PUBLIC INSTITUTIONS: | D101: Annual Expenses | E101: Per-Credit-Hour Charges | F101: Full-Time | G101: Undergraduate | H101: All | I101: All | J101: All | K101: All | L101: Nearest $1
A102: G603 | B102: In-district: | C102: 437.77 | D102: Annual Expenses | E102: Per-Credit-Hour Charges | F102: Full-Time | G102: Undergraduate | H102: All | I102: All | J102: All | K102: All | L102: Nearest $1
A103: G604 | B103: In-state (out-of-district): | C103: 437.77 | D103: Annual Expenses | E103: Per-Credit-Hour Charges | F103: Full-Time | G103: Undergraduate | H103: All | I103: All | J103: All | K103: All | L103: Nearest $1
A104: G605 | B104: Out-of-state: | C104: 1772.12 | D104: Annual Expenses | E104: Per-Credit-Hour Charges | F104: Full-Time | G104: Undergraduate | H104: All | I104: All | J104: All | K104: All | L104: Nearest $1
A105: G606 | B105: NONRESIDENTS: | C105: 1813.79 | D105: Annual Expenses | E105: Per-Credit-Hour Charges | F105: Full-Time | G105: Undergraduate | H105: All | I105: All | J105: All | K105: All | L105: Nearest $1

Sheet CDS-H
A1: Question Number | B1: Question | C1: Answer | D1: Section | E1: Sub-Section | F1: Category | G1: Student Group | H1: Cohort | I1: Residency | J1: Unit load | K1: Gender | L1: Value type
B66: 2024-2025 | C66: x | D66: Financial Aid | E66: Reporting Year | F66: All | G66: All | H66: All | I66: All | J66: All | K66: All | L66: x
A67: H102 | B67: 2023-2024 Final | D67: Financial Aid | E67: Reporting Year | F67: All | G67: All | H67: All | I67: All | J67: All | K67: All | L67: x
A73: H103 | B73: Federal methodology (FM) | C73: x | D73: Financial Aid | E73: Methodology | F73: All | G73: All | H73: All | I73: All | J73: All | K73: All | L73: x
A74: H104 | B74: Institutional methodology (IM) | D74: Financial Aid | E74: Methodology | F74: All | G74: All | H74: All | I74: All | J74: All | K74: All | L74: x
A75: H105 | B75: Both FM and IM | D75: Financial Aid | E75: Methodology | F75: All | G75: All | H75: All | I75: All | J75: All | K75: All | L75: x
B80: Scholarships/Grants
A81: H106 | B81: Federal | C81: 44183661 | D81: Financial Aid | E81: Need-based Aid Awarded | F81: Degree-seeking | G81: Undergraduate | H81: Undergraduates | I81: All | J81: All | K81: All | L81: Nearest $1
A82: H107 | B82: State all states, not only the state in which your institution is located | C82: 15907355 | D82: Financial Aid | E82: Need-based Aid Awarded | F82: Degree-seeking | G82: Undergraduate | H82: Undergraduates | I82: All | J82: All | K82: All | L82: Nearest $1
A83: H108 | B83: Institutional: Endowed scholarships, annual gifts and tuition funded grants, awarded by the college, excluding athletic aid and tuition waivers (which are reported below). | C83: 146719693 | D83: Financial Aid | E83: Need-based Aid Awarded | F83: Degree-seeking | G83: Undergraduate | H83: Undergraduates | I83: All | J83: All | K83: All | L83: Nearest $1
A84: H109 | B84: Scholarships/grants from external sources (e.g. Kiwanis, National Merit) not awarded by the college | C84: 7379772 | D84: Financial Aid | E84: Need-based Aid Awarded | F84: Degree-seeking | G84: Undergraduate | H84: Undergraduates | I84: All | J84: All | K84: All | L84: Nearest $1
A85: H110 | B85: Total Scholarships/Grants | C85: =SUM(C81:C84) | D85: Financial Aid | E85: Need-based Aid Awarded | F85: Degree-seeking | G85: Undergraduate | H85: Undergraduates | I85: All | J85: All | K85: All | L85: Nearest $1
B86: Self-Help
A87: H111 | B87: Student loans from all sources (excluding parent loans) | C87: 25049983 | D87: Financial Aid | E87: Need-based Aid Awarded | F87: Degree-seeking | G87: Undergraduate | H87: Undergraduates | I87: All | J87: All | K87: All | L87: Nearest $1
A88: H112 | B88: Federal Work-Study | C88: 19493365 | D88: Financial Aid | E88: Need-based Aid Awarded | F88: Degree-seeking | G88: Undergraduate | H88: Undergraduates | I88: All | J88: All | K88: All | L88: Nearest $1
A89: H113 | B89: State and other (e.g., institutional) work-study/employment (Note: Excludes Federal Work-Study captured above.) | C89: 0 | D89: Financial Aid | E89: Need-based Aid Awarded | F89: Degree-seeking | G89: Undergraduate | H89: Undergraduates | I89: All | J89: All | K89: All | L89: Nearest $1
A90: H114 | B90: Total Self-Help | C90: =SUM(C87:C89) | D90: Financial Aid | E90: Need-based Aid Awarded | F90: Degree-seeking | G90: Undergraduate | H90: Undergraduates | I90: All | J90: All | K90: All | L90: Nearest $1
A91: H115 | B91: Parent Loans | C91: 8227913 | D91: Financial Aid | E91: Need-based Aid Awarded | F91: Degree-seeking | G91: Undergraduate | H91: Undergraduates | I91: All | J91: All | K91: All | L91: Nearest $1
A92: H116 | B92: Tuition Waivers Note: Reporting is optional. Report tuition waivers in this row if you choose to report them. Do not report tuition waivers elsewhere. | C92: 7620152 | D92: Financial Aid | E92: Need-based Aid Awarded | F92: Degree-seeking | G92: Undergraduate | H92: Undergraduates | I92: All | J92: All | K92: All | L92: Nearest $1
A93: H117 | B93: Athletic Awards | C93: 2026230 | D93: Financial Aid | E93: Need-based Aid Awarded | F93: Degree-seeking | G93: Undergraduate | H93: Undergraduates | I93: All | J93: All | K93: All | L93: Nearest $1
B96: Scholarships/Grants
A97: H118 | B97: Federal | C97: 128962 | D97: Financial Aid | E97: Non-need-based Aid Awarded | F97: Degree-seeking | G97: Undergraduate | H97: Undergraduates | I97: All | J97: All | K97: All | L97: Nearest $1
A98: H119 | B98: State all states, not only the state in which your institution is located | C98: 5005958 | D98: Financial Aid | E98: Non-need-based Aid Awarded | F98: Degree-seeking | G98: Undergraduate | H98: Undergraduates | I98: All | J98: All | K98: All | L98: Nearest $1
A99: H120 | B99: Institutional: Endowed scholarships, annual gifts and tuition funded grants, awarded by the college, excluding athletic aid and tuition waivers (which are reported below). | C99: 24317541 | D99: Financial Aid | E99: Non-need-based Aid Awarded | F99: Degree-seeking | G99: Undergraduate | H99: Undergraduates | I99: All | J99: All | K99: All | L99: Nearest $1
A100: H121 | B100: Scholarships/grants from external sources (e.g. Kiwanis, National Merit) not awarded by the college | C100: 15950097 | D100: Financial Aid | E100: Non-need-based Aid Awarded | F100: Degree-seeking | G100: Undergraduate | H100: Undergraduates | I100: All | J100: All | K100: All | L100: Nearest $1
A101: H122 | B101: Total Scholarships/Grants | C101: =SUM(C97:C100) | D101: Financial Aid | E101: Non-need-based Aid Awarded | F101: Degree-seeking | G101: Undergraduate | H101: Undergraduates | I101: All | J101: All | K101: All | L101: Nearest $1
B102: Self-Help
A103: H123 | B103: Student loans from all sources (excluding parent loans) | C103: 50291283 | D103: Financial Aid | E103: Non-need-based Aid Awarded | F103: Degree-seeking | G103: Undergraduate | H103: Undergraduates | I103: All | J103: All | K103: All | L103: Nearest $1
B104: Federal Work-Study
A105: H124 | B105: State and other (e.g., institutional) work-study/employment (Note: Excludes Federal Work-Study captured above.) | C105: 0 | D105: Financial Aid | E105: Non-need-based Aid Awarded | F105: Degree-seeking | G105: Undergraduate | H105: Undergraduates | I105: All | J105: All | K105: All | L105: Nearest $1
A106: H125 | B106: Total Self-Help | C106: =SUM(C103:C105) | D106: Financial Aid | E106: Non-need-based Aid Awarded | F106: Degree-seeking | G106: Undergraduate | H106: Undergraduates | I106: All | J106: All | K106: All | L106: Nearest $1
A107: H126 | B107: Parent Loans | C107: 23453168 | D107: Financial Aid | E107: Non-need-based Aid Awarded | F107: Degree-seeking | G107: Undergraduate | H107: Undergraduates | I107: All | J107: All | K107: All | L107: Nearest $1
A108: H127 | B108: Tuition Waivers Note: Reporting is optional. Report tuition waivers in this row if you choose to report them. Do not report tuition waivers elsewhere. | C108: 287208 | D108: Financial Aid | E108: Non-need-based Aid Awarded | F108: Degree-seeking | G108: Undergraduate | H108: Undergraduates | I108: All | J108: All | K108: All | L108: Nearest $1
A109: H128 | B109: Athletic Awards | C109: 12718597 | D109: Financial Aid | E109: Non-need-based Aid Awarded | F109: Degree-seeking | G109: Undergraduate | H109: Undergraduates | I109: All | J109: All | K109: All | L109: Nearest $1
A126: H201 | B126: A. Number of degree-seeking undergraduate students (CDS Item B1 if reporting on Fall 2024 cohort) | C126: 8491 | D126: Financial Aid | E126: Students Awarded Aid | F126: Degree-seeking | G126: Undergraduate | H126: First-time, first-year | I126: All | J126: FT | K126: All | L126: Number
A127: H202 | B127: B. Number of students in line a who applied for need-based financial aid | C127: 6175 | D127: Financial Aid | E127: Students Awarded Aid | F127: Degree-seeking | G127: Undergraduate | H127: First-time, first-year | I127: All | J127: FT | K127: All | L127: Number
A128: H203 | B128: C. Number of students in line b who were determined to have financial need | C128: 3001 | D128: Financial Aid | E128: Students Awarded Aid | F128: Degree-seeking | G128: Undergraduate | H128: First-time, first-year | I128: All | J128: FT | K128: All | L128: Number
A129: H204 | B129: D. Number of students in line c who were awarded any financial aid | C129: 2814 | D129: Financial Aid | E129: Students Awarded Aid | F129: Degree-seeking | G129: Undergraduate | H129: First-time, first-year | I129: All | J129: FT | K129: All | L129: Number
A130: H205 | B130: E. Number of students in line d who were awarded any need-based scholarship or grant aid | C130: 2442 | D130: Financial Aid | E130: Students Awarded Aid | F130: Degree-seeking | G130: Undergraduate | H130: First-time, first-year | I130: All | J130: FT | K130: All | L130: Number
A131: H206 | B131: F. Number of students in line d who were awarded any need-based self-help aid | C131: 2220 | D131: Financial Aid | E131: Students Awarded Aid | F131: Degree-seeking | G131: Undergraduate | H131: First-time, first-year | I131: All | J131: FT | K131: All | L131: Number
A132: H207 | B132: G. Number of students in line d who were awarded any non-need-based scholarship or grant aid | C132: 198 | D132: Financial Aid | E132: Students Awarded Aid | F132: Degree-seeking | G132: Undergraduate | H132: First-time, first-year | I132: All | J132: FT | K132: All | L132: Number
A133: H208 | B133: H. Number of students in line d whose need was fully met (exclude PLUS loans, unsubsidized loans, and private alternative loans) | C133: 2192 | D133: Financial Aid | E133: Students Awarded Aid | F133: Degree-seeking | G133: Undergraduate | H133: First-time, first-year | I133: All | J133: FT | K133: All | L133: Number
A135: H209 | B135: I. On average, the percentage of need that was met of students who were awarded any need-based aid. Exclude any aid that was awarded in excess of need as well as any resources that were awarded to replace EFC (PLUS loans, unsubsidized loans, and private alternative loans) | C135: 0.89 | D135: Financial Aid | E135: Students Awarded Aid | F135: Degree-seeking | G135: Undergraduate | H135: First-time, first-year | I135: All | J135: FT | K135: All | L135: Nearest 1%
... A272: H515 | B272: E. Private student loans made by a bank or lender. | C272: 40492 | D272: Financial Aid | E272: Source Type Loan | F272: Average per Borrower | G272: Undergraduate | H272: First-time, first-year | I272: All | J272: All | K272: All | L272: Nearest $1
A280: H601 | B280: Institutional need-based scholarship or grant aid is available | D280: Financial Aid | E280: Aid to Nonresidents | F280: Aid Policy | G280: Undergraduate | H280: All | I280: All | J280: All | K280: All | L280: x
A281: H602 | B281: Institutional non-need-based scholarship or grant aid is available | D281: Financial Aid | E281: Aid to Nonresidents | F281: Aid Policy | G281: Undergraduate | H281: All | I281: All | J281: All | K281: All | L281: x
A282: H603 | B282: Institutional scholarship or grant aid is not available | C282: x | D282: Financial Aid | E282: Aid to Nonresidents | F282: Aid Policy | G282: Undergraduate | H282: All | I282: All | J282: All | K282: All | L282: x
A285: H604 | B285: If institutional financial aid is available for undergraduate degree-seeking nonresidents, provide the number of undergraduate degree-seeking nonresidents who were awarded need-based or non-need-based aid: | D285: Financial Aid | E285: Aid to Nonresidents | F285: Awardees | G285: Undergraduate | H285: All | I285: All | J285: All | K285: All | L285: Number
A288: H605 | B288: Average dollar amount of institutional financial aid awarded to undergraduate degree-seeking nonresidents: | D288: Financial Aid | E288: Aid to Nonresidents | F288: Average Award | G288: Undergraduate | H288: All | I288: All | J288: All | K288: All | L288: Nearest $1
A291: H606 | B291: Total dollar amount of institutional financial aid awarded to undergraduate degree-seeking nonresidents: | D291: Financial Aid | E291: Aid to Nonresidents | F291: Total Amount | G291: Undergraduate | H291: All | I291: All | J291: All | K291: All | L291: Nearest $1
A298: H7101 | B298: Institution’s own financial aid form | D298: Financial Aid | E298: Financial Aid Forms | F298: Applicants | G298: Undergraduate | H298: First-year | I298: Nonresidents | J298: All | K298: All | L298: x
A299: H7102 | B299: CSS/Financial Aid PROFILE | D299: Financial Aid | E299: Financial Aid Forms | F299: Applicants | G299: Undergraduate | H299: First-year | I299: Nonresidents | J299: All | K299: All | L299: x
A301: H7103 | B301: Other (specify): | D301: Financial Aid | E301: Financial Aid Forms | F301: Applicants | G301: Undergraduate | H301: First-year | I301: Nonresidents | J301: All | K301: All | L301: Text
A310: H801 | B310: FAFSA | C310: x | D310: Financial Aid | E310: Financial Aid Forms | F310: Applicants | G310: Undergraduate | H310: First-year | I310: Domestic | J310: All | K310: All | L310: x
A311: H802 | B311: Institution's own financial aid form | D311: Financial Aid | E311: Financial Aid Forms | F311: Applicants | G311: Undergraduate | H311: First-year | I311: Domestic | J311: All | K311: All | L311: x
A312: H803 | B312: CSS PROFILE | D312: Financial Aid | E312: Financial Aid Forms | F312: Applicants | G312: Undergraduate | H312: First-year | I312: Domestic | J312: All | K312: All | L312: x
A313: H804 | B313: State aid form | D313: Financial Aid | E313: Financial Aid Forms | F313: Applicants | G313: Undergraduate | H313: First-year | I313: Domestic | J313: All | K313: All | L313: x
A314: H805 | B314: Noncustodial PROFILE | D314: Financial Aid | E314: Financial Aid Forms | F314: Applicants | G314: Undergraduate | H314: First-year | I314: Domestic | J314: All | K314: All | L314: x
A315: H806 | B315: Business/Farm Supplement | D315: Financial Aid | E315: Financial Aid Forms | F315: Applicants | G315: Undergraduate | H315: First-year | I315: Domestic | J315: All | K315: All | L315: x
A317: H807 | B317: Other (specify): | D317: Financial Aid | E317: Financial Aid Forms | F317: Applicants | G317: Undergraduate | H317: First-year | I317: Domestic | J317: All | K317: All | L317: Text
A324: H901 | B324: Priority date for filing required financial aid forms: | D324: Financial Aid | E324: Financial Aid Deadlines | F324: All | G324: Undergraduate | H324: First-year | I324: All | J324: All | K324: All | L324: MM-DD
A325: H902 | B325: Deadline for filing required financial aid forms: | C325: 46127 | D325: Financial Aid | E325: Financial Aid Deadlines | F325: All | G325: Undergraduate | H325: First-year | I325: All | J325: All | K325: All | L325: MM-DD
A327: H903 | B327: No deadline for filing required forms (applications processed on a rolling basis) | D327: Financial Aid | E327: Financial Aid Deadlines | F327: All | G327: Undergraduate | H327: First-year | I327: All | J327: All | K327: All | L327: x
A333: H1001 | B333: a) Students notified on or about (date): | D333: Financial Aid | E333: Financial Aid Notification | F333: All | G333: Undergraduate | H333: First-year | I333: All | J333: All | K333: All | L333: MM-DD
A337: H1002 | B337: b) Students notified on a rolling basis: | C337: Y | D337: Financial Aid | E337: Financial Aid Notification | F337: All | G337: Undergraduate | H337: First-year | I337: All | J337: All | K337: All | L337: YN
A340: H1003 | B340: If yes, starting date: | D340: Financial Aid | E340: Financial Aid Notification | F340: All | G340: Undergraduate | H340: First-year | I340: All | J340: All | K340: All | L340: MM-DD
A347: H1101 | B347: Students must reply by (date): | D347: Financial Aid | E347: Financial Aid Reply | F347: All | G347: Undergraduate | H347: First-year | I347: All | J347: All | K347: All | L347: MM-DD
A350: H1102 | B350: or within____weeks of notification. | C350: 3 | D350: Financial Aid | E350: Financial Aid Reply | F350: All | G350: Undergraduate | H350: First-year | I350: All | J350: All | K350: All | L350: Number
A359: H1201 | B359: Federal Direct Subsidized Stafford Loans | C359: x | D359: Financial Aid | E359: Aid Available | F359: Loans | G359: Undergraduate | H359: Undergraduates | I359: All | J359: All | K359: All | L359: x
A360: H1202 | B360: Federal Direct Unsubsidized Stafford Loans | C360: x | D360: Financial Aid | E360: Aid Available | F360: Loans | G360: Undergraduate | H360: Undergraduates | I360: All | J360: All | K360: All | L360: x
A361: H1203 | B361: Federal Direct PLUS Loans | C361: x | D361: Financial Aid | E361: Aid Available | F361: Loans | G361: Undergraduate | H361: Undergraduates | I361: All | J361: All | K361: All | L361: x
A362: H1204 | B362: Federal Nursing Loans | C362: x | D362: Financial Aid | E362: Aid Available | F362: Loans | G362: Undergraduate | H362: Undergraduates | I362: All | J362: All | K362: All | L362: x
A363: H1205 | B363: State Loans | D363: Financial Aid | E363: Aid Available | F363: Loans | G363: Undergraduate | H363: Undergraduates | I363: All | J363: All | K363: All | L363: x
A364: H1206 | B364: College/university loans from institutional funds | D364: Financial Aid | E364: Aid Available | F364: Loans | G364: Undergraduate | H364: Undergraduates | I364: All | J364: All | K364: All | L364: x
A366: H1207 | B366: Other (specify): | D366: Financial Aid | E366: Aid Available | F366: Loans | G366: Undergraduate | H366: Undergraduates | I366: All | J366: All | K366: All | L366: Text
A372: H1301 | B372: Federal Pell Grants | C372: x | D372: Financial Aid | E372: Aid Available | F372: Need Based Schl Grt | G372: Undergraduate | H372: Undergraduates | I372: All | J372: All | K372: All | L372: x
A373: H1302 | B373: Federal SEOG | C373: x | D373: Financial Aid | E373: Aid Available | F373: Need Based Schl Grt | G373: Undergraduate | H373: Undergraduates | I373: All | J373: All | K373: All | L373: x
A374: H1303 | B374: State scholarships/grants | C374: x | D374: Financial Aid | E374: Aid Available | F374: Need Based Schl Grt | G374: Undergraduate | H374: Undergraduates | I374: All | J374: All | K374: All | L374: x
A375: H1304 | B375: Private scholarships | C375: x | D375: Financial Aid | E375: Aid Available | F375: Need Based Schl Grt | G375: Undergraduate | H375: Undergraduates | I375: All | J375: All | K375: All | L375: x
A376: H1305 | B376: College/university scholarship or grant aid from institutional funds | C376: x | D376: Financial Aid | E376: Aid Available | F376: Need Based Schl Grt | G376: Undergraduate | H376: Undergraduates | I376: All | J376: All | K376: All | L376: x
A377: H1306 | B377: United Negro College Fund | D377: Financial Aid | E377: Aid Available | F377: Need Based Schl Grt | G377: Undergraduate | H377: Undergraduates | I377: All | J377: All | K377: All | L377: x
A378: H1307 | B378: Federal Nursing Scholarship | D378: Financial Aid | E378: Aid Available | F378: Need Based Schl Grt | G378: Undergraduate | H378: Undergraduates | I378: All | J378: All | K378: All | L378: x
A380: H1308 | B380: Other (specify): | D380: Financial Aid | E380: Aid Available | F380: Need Based Schl Grt | G380: Undergraduate | H380: Undergraduates | I380: All | J380: All | K380: All | L380: Text
A389: H1401 | B389: Academics | C389: x | D389: Financial Aid | E389: Institutional Aid | F389: Non-Need Based Criteria | G389: Undergraduate | H389: Undergraduates | I389: All | J389: All | K389: All | L389: x
A390: H1402 | B390: Alumni affiliation | C390: x | D390: Financial Aid | E390: Institutional Aid | F390: Non-Need Based Criteria | G390: Undergraduate | H390: Undergraduates | I390: All | J390: All | K390: All | L390: x
A391: H1403 | B391: Art | C391: x | D391: Financial Aid | E391: Institutional Aid | F391: Non-Need Based Criteria | G391: Undergraduate | H391: Undergraduates | I391: All | J391: All | K391: All | L391: x
A392: H1404 | B392: Athletics | C392: x | D392: Financial Aid | E392: Institutional Aid | F392: Non-Need Based Criteria | G392: Undergraduate | H392: Undergraduates | I392: All | J392: All | K392: All | L392: x
A393: H1405 | B393: Job skills | D393: Financial Aid | E393: Institutional Aid | F393: Non-Need Based Criteria | G393: Undergraduate | H393: Undergraduates | I393: All | J393: All | K393: All | L393: x
A394: H1406 | B394: ROTC | C394: x | D394: Financial Aid | E394: Institutional Aid | F394: Non-Need Based Criteria | G394: Undergraduate | H394: Undergraduates | I394: All | J394: All | K394: All | L394: x
A395: H1407 | B395: Leadership | C395: x | D395: Financial Aid | E395: Institutional Aid | F395: Non-Need Based Criteria | G395: Undergraduate | H395: Undergraduates | I395: All | J395: All | K395: All | L395: x
A396: H1408 | B396: Music/drama | C396: x | D396: Financial Aid | E396: Institutional Aid | F396: Non-Need Based Criteria | G396: Undergraduate | H396: Undergraduates | I396: All | J396: All | K396: All | L396: x
A397: H1409 | B397: Religious affiliation | D397: Financial Aid | E397: Institutional Aid | F397: Non-Need Based Criteria | G397: Undergraduate | H397: Undergraduates | I397: All | J397: All | K397: All | L397: x
A398: H1410 | B398: State/district residency | C398: x | D398: Financial Aid | E398: Institutional Aid | F398: Non-Need Based Criteria | G398: Undergraduate | H398: Undergraduates | I398: All | J398: All | K398: All | L398: x
A401: H1411 | B401: Academics | C401: x | D401: Financial Aid | E401: Institutional Aid | F401: Need Based Criteria | G401: Undergraduate | H401: Undergraduates | I401: All | J401: All | K401: All | L401: x
A402: H1412 | B402: Alumni affiliation | C402: x | D402: Financial Aid | E402: Institutional Aid | F402: Need Based Criteria | G402: Undergraduate | H402: Undergraduates | I402: All | J402: All | K402: All | L402: x
A403: H1413 | B403: Art | D403: Financial Aid | E403: Institutional Aid | F403: Need Based Criteria | G403: Undergraduate | H403: Undergraduates | I403: All | J403: All | K403: All | L403: x
A404: H1414 | B404: Athletics | D404: Financial Aid | E404: Institutional Aid | F404: Need Based Criteria | G404: Undergraduate | H404: Undergraduates | I404: All | J404: All | K404: All | L404: x
A405: H1415 | B405: Job skills | D405: Financial Aid | E405: Institutional Aid | F405: Need Based Criteria | G405: Undergraduate | H405: Undergraduates | I405: All | J405: All | K405: All | L405: x
A406: H1416 | B406: Leadership | D406: Financial Aid | E406: Institutional Aid | F406: Need Based Criteria | G406: Undergraduate | H406: Undergraduates | I406: All | J406: All | K406: All | L406: x
A407: H1417 | B407: Music/drama | D407: Financial Aid | E407: Institutional Aid | F407: Need Based Criteria | G407: Undergraduate | H407: Undergraduates | I407: All | J407: All | K407: All | L407: x
...

Sheet CDS-I
A1: Question Number | B1: Question | C1: Answer | D1: Section | E1: Sub-Section | F1: Category | G1: Student Group | H1: Cohort | I1: Residency | J1: Unit load | K1: Gender | L1: Value type
A55: I101 | B55: A. Total number of instructional faculty | C55: 2825 | D55: Instructional Faculty And Class Size | E55: Instructional Faculty | F55: Full-Time | G55: Undergraduates | H55: Faculty | I55: All | J55: All | K55: All | L55: Number
A56: I102 | B56: B. Total number who are members of minority groups | C56: 730 | D56: Instructional Faculty And Class Size | E56: Instructional Faculty | F56: Full-Time | G56: Undergraduates | H56: Faculty | I56: All | J56: All | K56: All | L56: Number
A57: I103 | B57: C. Total number who are women | C57: 1302 | D57: Instructional Faculty And Class Size | E57: Instructional Faculty | F57: Full-Time | G57: Undergraduates | H57: Faculty | I57: All | J57: All | K57: All | L57: Number
A58: I104 | B58: D. Total number who are men | C58: 1523 | D58: Instructional Faculty And Class Size | E58: Instructional Faculty | F58: Full-Time | G58: Undergraduates | H58: Faculty | I58: All | J58: All | K58: All | L58: Number
A59: I105 | B59: E. Total number who are nonresidents (international) | C59: 102 | D59: Instructional Faculty And Class Size | E59: Instructional Faculty | F59: Full-Time | G59: Undergraduates | H59: Faculty | I59: All | J59: All | K59: All | L59: Number
A60: I106 | B60: F. Total number with doctorate, or other terminal degree | C60: 2555 | D60: Instructional Faculty And Class Size | E60: Instructional Faculty | F60: Full-Time | G60: Undergraduates | H60: Faculty | I60: All | J60: All | K60: All | L60: Number
A61: I107 | B61: G. Total number whose highest degree is a master’s but not a terminal master’s | C61: 240 | D61: Instructional Faculty And Class Size | E61: Instructional Faculty | F61: Full-Time | G61: Undergraduates | H61: Faculty | I61: All | J61: All | K61: All | L61: Number
A62: I108 | B62: H. Total number whose highest degree is a bachelor’s | C62: 30 | D62: Instructional Faculty And Class Size | E62: Instructional Faculty | F62: Full-Time | G62: Undergraduates | H62: Faculty | I62: All | J62: All | K62: All | L62: Number
A63: I109 | B63: I. Total number whose highest degree is unknown or other (Note: Items f, g, h, and i must sum up to item a.) | C63: 0 | D63: Instructional Faculty And Class Size | E63: Instructional Faculty | F63: Full-Time | G63: Undergraduates | H63: Faculty | I63: All | J63: All | K63: All | L63: Number
A64: I110 | B64: J. Total number in stand-alone graduate/professional programs in which faculty teach virtually only graduate-level students | C64: 433 | D64: Instructional Faculty And Class Size | E64: Instructional Faculty | F64: Full-Time | G64: Undergraduates | H64: Faculty | I64: All | J64: All | K64: All | L64: Number
A68: I111 | B68: A. Total number of instructional faculty | C68: 446 | D68: Instructional Faculty And Class Size | E68: Instructional Faculty | F68: Part-Time | G68: Undergraduates | H68: Faculty | I68: All | J68: All | K68: All | L68: Number
A69: I112 | B69: B. Total number who are members of minority groups | C69: 53 | D69: Instructional Faculty And Class Size | E69: Instructional Faculty | F69: Part-Time | G69: Undergraduates | H69: Faculty | I69: All | J69: All | K69: All | L69: Number
... A141: I307 | B141: 100+ | C141: 383 | D141: Instructional Faculty And Class Size | E141: Undergraduate Class Size | F141: Class Sections | G141: Undergraduates | H141: Faculty | I141: All | J141: All | K141: All | L141: Number
A142: I308 | B142: Total | C142: =SUM(C135:C141) | D142: Instructional Faculty And Class Size | E142: Undergraduate Class Size | F142: Class Sections | G142: Undergraduates | H142: Faculty | I142: All | J142: All | K142: All | L142: Number
A145: I309 | B145: 2-9 | C145: 245 | D145: Instructional Faculty And Class Size | E145: Undergraduate Class Size | F145: Class Sub-Sections | G145: Undergraduates | H145: Faculty | I145: All | J145: All | K145: All | L145: Number
A146: I310 | B146: 10-19 | C146: 1366 | D146: Instructional Faculty And Class Size | E146: Undergraduate Class Size | F146: Class Sub-Sections | G146: Undergraduates | H146: Faculty | I146: All | J146: All | K146: All | L146: Number
A147: I311 | B147: 20-29 | C147: 1814 | D147: Instructional Faculty And Class Size | E147: Undergraduate Class Size | F147: Class Sub-Sections | G147: Undergraduates | H147: Faculty | I147: All | J147: All | K147: All | L147: Number
A148: I312 | B148: 30-39 | C148: 295 | D148: Instructional Faculty And Class Size | E148: Undergraduate Class Size | F148: Class Sub-Sections | G148: Undergraduates | H148: Faculty | I148: All | J148: All | K148: All | L148: Number
A149: I313 | B149: 40-49 | C149: 61 | D149: Instructional Faculty And Class Size | E149: Undergraduate Class Size | F149: Class Sub-Sections | G149: Undergraduates | H149: Faculty | I149: All | J149: All | K149: All | L149: Number
A150: I314 | B150: 50-99 | C150: 22 | D150: Instructional Faculty And Class Size | E150: Undergraduate Class Size | F150: Class Sub-Sections | G150: Undergraduates | H150: Faculty | I150: All | J150: All | K150: All | L150: Number
A151: I315 | B151: 100+ | C151: 9 | D151: Instructional Faculty And Class Size | E151: Undergraduate Class Size | F151: Class Sub-Sections | G151: Undergraduates | H151: Faculty | I151: All | J151: All | K151: All | L151: Number
A152: I316 | B152: Total | C152: =SUM(C145:C151) | D152: Instructional Faculty And Class Size | E152: Undergraduate Class Size | F152: Class Sub-Sections | G152: Undergraduates | H152: Faculty | I152: All | J152: All | K152: All | L152: Number

Sheet CDS-J
A1: Question Number | B1: Question | C1: Answer | D1: Section | E1: Sub-Section | F1: Category | G1: Student Group | H1: Cohort | I1: Residency | J1: Unit load | K1: Gender | L1: Value type
A17: J101 | B17: Agriculture | D17: Disciplinary Areas of Degrees Conferred | E17: Diploma/Certificates | F17: 01 | G17: Undergraduates | H17: All | I17: All | J17: All | K17: All | L17: Whole Number or Round to Nearest Tenths
A18: J102 | B18: Natural resources and conservation | D18: Disciplinary Areas of Degrees Conferred | E18: Diploma/Certificates | F18: 03 | G18: Undergraduates | H18: All | I18: All | J18: All | K18: All | L18: Whole Number or Round to Nearest Tenths
A19: J103 | B19: Architecture | D19: Disciplinary Areas of Degrees Conferred | E19: Diploma/Certificates | F19: 04 | G19: Undergraduates | H19: All | I19: All | J19: All | K19: All | L19: Whole Number or Round to Nearest Tenths
A20: J104 | B20: Area, ethnic, and gender studies | D20: Disciplinary Areas of Degrees Conferred | E20: Diploma/Certificates | F20: 05 | G20: Undergraduates | H20: All | I20: All | J20: All | K20: All | L20: Whole Number or Round to Nearest Tenths
A21: J105 | B21: Communication/journalism | D21: Disciplinary Areas of Degrees Conferred | E21: Diploma/Certificates | F21: 09 | G21: Undergraduates | H21: All | I21: All | J21: All | K21: All | L21: Whole Number or Round to Nearest Tenths
A22: J106 | B22: Communication technologies | D22: Disciplinary Areas of Degrees Conferred | E22: Diploma/Certificates | F22: 10 | G22: Undergraduates | H22: All | I22: All | J22: All | K22: All | L22: Whole Number or Round to Nearest Tenths
A23: J107 | B23: Computer and information sciences | D23: Disciplinary Areas of Degrees Conferred | E23: Diploma/Certificates | F23: 11 | G23: Undergraduates | H23: All | I23: All | J23: All | K23: All | L23: Whole Number or Round to Nearest Tenths
A24: J108 | B24: Personal and culinary services | D24: Disciplinary Areas of Degrees Conferred | E24: Diploma/Certificates | F24: 12 | G24: Undergraduates | H24: All | I24: All | J24: All | K24: All | L24: Whole Number or Round to Nearest Tenths
A25: J109 | B25: Education | D25: Disciplinary Areas of Degrees Conferred | E25: Diploma/Certificates | F25: 13 | G25: Undergraduates | H25: All | I25: All | J25: All | K25: All | L25: Whole Number or Round to Nearest Tenths
A26: J110 | B26: Engineering | D26: Disciplinary Areas of Degrees Conferred | E26: Diploma/Certificates | F26: 14 | G26: Undergraduates | H26: All | I26: All | J26: All | K26: All | L26: Whole Number or Round to Nearest Tenths
A27: J111 | B27: Engineering technologies | D27: Disciplinary Areas of Degrees Conferred | E27: Diploma/Certificates | F27: 15 | G27: Undergraduates | H27: All | I27: All | J27: All | K27: All | L27: Whole Number or Round to Nearest Tenths
A28: J112 | B28: Foreign languages, literatures, and linguistics | D28: Disciplinary Areas of Degrees Conferred | E28: Diploma/Certificates | F28: 16 | G28: Undergraduates | H28: All | I28: All | J28: All | K28: All | L28: Whole Number or Round to Nearest Tenths
A29: J113 | B29: Family and consumer sciences | D29: Disciplinary Areas of Degrees Conferred | E29: Diploma/Certificates | F29: 19 | G29: Undergraduates | H29: All | I29: All | J29: All | K29: All | L29: Whole Number or Round to Nearest Tenths
A30: J114 | B30: Law/legal studies | D30: Disciplinary Areas of Degrees Conferred | E30: Diploma/Certificates | F30: 22 | G30: Undergraduates | H30: All | I30: All | J30: All | K30: All | L30: Whole Number or Round to Nearest Tenths
A31: J115 | B31: English | D31: Disciplinary Areas of Degrees Conferred | E31: Diploma/Certificates | F31: 23 | G31: Undergraduates | H31: All | I31: All | J31: All | K31: All | L31: Whole Number or Round to Nearest Tenths
A32: J116 | B32: Liberal arts/general studies | D32: Disciplinary Areas of Degrees Conferred | E32: Diploma/Certificates | F32: 24 | G32: Undergraduates | H32: All | I32: All | J32: All | K32: All | L32: Whole Number or Round to Nearest Tenths
A33: J117 | B33: Library science | D33: Disciplinary Areas of Degrees Conferred | E33: Diploma/Certificates | F33: 25 | G33: Undergraduates | H33: All | I33: All | J33: All | K33: All | L33: Whole Number or Round to Nearest Tenths
... A35: J119 | B35: Mathematics and statistics | D35: Disciplinary Areas of Degrees Conferred | E35: Diploma/Certificates | F35: 27 | G35: Undergraduates | H35: All | I35: All | J35: All | K35: All | L35: Whole Number or Round to Nearest Tenths
A36: J120 | B36: Military science and military technologies | D36: Disciplinary Areas of Degrees Conferred | E36: Diploma/Certificates | F36: 28 & 29 | G36: Undergraduates | H36: All | I36: All | J36: All | K36: All | L36: Whole Number or Round to Nearest Tenths
A37: J121 | B37: Interdisciplinary studies | D37: Disciplinary Areas of Degrees Conferred | E37: Diploma/Certificates | F37: 30 | G37: Undergraduates | H37: All | I37: All | J37: All | K37: All | L37: Whole Number or Round to Nearest Tenths
A38: J122 | B38: Parks and recreation | D38: Disciplinary Areas of Degrees Conferred | E38: Diploma/Certificates | F38: 31 | G38: Undergraduates | H38: All | I38: All | J38: All | K38: All | L38: Whole Number or Round to Nearest Tenths
A39: J123 | B39: Philosophy and religious studies | D39: Disciplinary Areas of Degrees Conferred | E39: Diploma/Certificates | F39: 38 | G39: Undergraduates | H39: All | I39: All | J39: All | K39: All | L39: Whole Number or Round to Nearest Tenths
A40: J124 | B40: Theology and religious vocations | D40: Disciplinary Areas of Degrees Conferred | E40: Diploma/Certificates | F40: 39 | G40: Undergraduates | H40: All | I40: All | J40: All | K40: All | L40: Whole Number or Round to Nearest Tenths
A41: J125 | B41: Physical sciences | D41: Disciplinary Areas of Degrees Conferred | E41: Diploma/Certificates | F41: 40 | G41: Undergraduates | H41: All | I41: All | J41: All | K41: All | L41: Whole Number or Round to Nearest Tenths
A42: J126 | B42: Science technologies | D42: Disciplinary Areas of Degrees Conferred | E42: Diploma/Certificates | F42: 41 | G42: Undergraduates | H42: All | I42: All | J42: All | K42: All | L42: Whole Number or Round to Nearest Tenths
A43: J127 | B43: Psychology | D43: Disciplinary Areas of Degrees Conferred | E43: Diploma/Certificates | F43: 42 | G43: Undergraduates | H43: All | I43: All | J43: All | K43: All | L43: Whole Number or Round to Nearest Tenths
A44: J128 | B44: Homeland Security, law enforcement, firefighting, and protective services | D44: Disciplinary Areas of Degrees Conferred | E44: Diploma/Certificates | F44: 43 | G44: Undergraduates | H44: All | I44: All | J44: All | K44: All | L44: Whole Number or Round to Nearest Tenths
A45: J129 | B45: Public administration and social services | D45: Disciplinary Areas of Degrees Conferred | E45: Diploma/Certificates | F45: 44 | G45: Undergraduates | H45: All | I45: All | J45: All | K45: All | L45: Whole Number or Round to Nearest Tenths
A46: J130 | B46: Social sciences | D46: Disciplinary Areas of Degrees Conferred | E46: Diploma/Certificates | F46: 45 | G46: Undergraduates | H46: All | I46: All | J46: All | K46: All | L46: Whole Number or Round to Nearest Tenths
A47: J131 | B47: Construction trades | D47: Disciplinary Areas of Degrees Conferred | E47: Diploma/Certificates | F47: 46 | G47: Undergraduates | H47: All | I47: All | J47: All | K47: All | L47: Whole Number or Round to Nearest Tenths
A48: J132 | B48: Mechanic and repair technologies | D48: Disciplinary Areas of Degrees Conferred | E48: Diploma/Certificates | F48: 47 | G48: Undergraduates | H48: All | I48: All | J48: All | K48: All | L48: Whole Number or Round to Nearest Tenths
... A54: J138 | B54: History | D54: Disciplinary Areas of Degrees Conferred | E54: Diploma/Certificates | F54: 54 | G54: Undergraduates | H54: All | I54: All | J54: All | K54: All | L54: Whole Number or Round to Nearest Tenths
A55: J139 | B55: Other | D55: Disciplinary Areas of Degrees Conferred | E55: Diploma/Certificates | F55: Other | G55: Undergraduates | H55: All | I55: All | J55: All | K55: All | L55: Whole Number or Round to Nearest Tenths
A56: J140 | B56: TOTAL (should = 100%) | D56: Disciplinary Areas of Degrees Conferred | E56: Diploma/Certificates | F56: Total | G56: Undergraduates | H56: All | I56: All | J56: All | K56: All | L56: Whole Number or Round to Nearest Tenths
A64: J141 | B64: Agriculture | D64: Disciplinary Areas of Degrees Conferred | E64: Associate | F64: 01 | G64: Undergraduates | H64: All | I64: All | J64: All | K64: All | L64: Whole Number or Round to Nearest Tenths
A65: J142 | B65: Natural resources and conservation | D65: Disciplinary Areas of Degrees Conferred | E65: Associate | F65: 03 | G65: Undergraduates | H65: All | I65: All | J65: All | K65: All | L65: Whole Number or Round to Nearest Tenths
A66: J143 | B66: Architecture | D66: Disciplinary Areas of Degrees Conferred | E66: Associate | F66: 04 | G66: Undergraduates | H66: All | I66: All | J66: All | K66: All | L66: Whole Number or Round to Nearest Tenths
A67: J144 | B67: Area, ethnic, and gender studies | D67: Disciplinary Areas of Degrees Conferred | E67: Associate | F67: 05 | G67: Undergraduates | H67: All | I67: All | J67: All | K67: All | L67: Whole Number or Round to Nearest Tenths
A68: J145 | B68: Communication/journalism | D68: Disciplinary Areas of Degrees Conferred | E68: Associate | F68: 09 | G68: Undergraduates | H68: All | I68: All | J68: All | K68: All | L68: Whole Number or Round to Nearest Tenths
A69: J146 | B69: Communication technologies | D69: Disciplinary Areas of Degrees Conferred | E69: Associate | F69: 10 | G69: Undergraduates | H69: All | I69: All | J69: All | K69: All | L69: Whole Number or Round to Nearest Tenths
A70: J147 | B70: Computer and information sciences | D70: Disciplinary Areas of Degrees Conferred | E70: Associate | F70: 11 | G70: Undergraduates | H70: All | I70: All | J70: All | K70: All | L70: Whole Number or Round to Nearest Tenths
A71: J148 | B71: Personal and culinary services | D71: Disciplinary Areas of Degrees Conferred | E71: Associate | F71: 12 | G71: Undergraduates | H71: All | I71: All | J71: All | K71: All | L71: Whole Number or Round to Nearest Tenths
A72: J149 | B72: Education | D72: Disciplinary Areas of Degrees Conferred | E72: Associate | F72: 13 | G72: Undergraduates | H72: All | I72: All | J72: All | K72: All | L72: Whole Number or Round to Nearest Tenths
A73: J150 | B73: Engineering | D73: Disciplinary Areas of Degrees Conferred | E73: Associate | F73: 14 | G73: Undergraduates | H73: All | I73: All | J73: All | K73: All | L73: Whole Number or Round to Nearest Tenths
A74: J151 | B74: Engineering technologies | D74: Disciplinary Areas of Degrees Conferred | E74: Associate | F74: 15 | G74: Undergraduates | H74: All | I74: All | J74: All | K74: All | L74: Whole Number or Round to Nearest Tenths
A75: J152 | B75: Foreign languages, literatures, and linguistics | D75: Disciplinary Areas of Degrees Conferred | E75: Associate | F75: 16 | G75: Undergraduates | H75: All | I75: All | J75: All | K75: All | L75: Whole Number or Round to Nearest Tenths
A76: J153 | B76: Family and consumer sciences | D76: Disciplinary Areas of Degrees Conferred | E76: Associate | F76: 19 | G76: Undergraduates | H76: All | I76: All | J76: All | K76: All | L76: Whole Number or Round to Nearest Tenths
A77: J154 | B77: Law/legal studies | D77: Disciplinary Areas of Degrees Conferred | E77: Associate | F77: 22 | G77: Undergraduates | H77: All | I77: All | J77: All | K77: All | L77: Whole Number or Round to Nearest Tenths
A78: J155 | B78: English | D78: Disciplinary Areas of Degrees Conferred | E78: Associate | F78: 23 | G78: Undergraduates | H78: All | I78: All | J78: All | K78: All | L78: Whole Number or Round to Nearest Tenths
A79: J156 | B79: Liberal arts/general studies | D79: Disciplinary Areas of Degrees Conferred | E79: Associate | F79: 24 | G79: Undergraduates | H79: All | I79: All | J79: All | K79: All | L79: Whole Number or Round to Nearest Tenths
A80: J157 | B80: Library science | D80: Disciplinary Areas of Degrees Conferred | E80: Associate | F80: 25 | G80: Undergraduates | H80: All | I80: All | J80: All | K80: All | L80: Whole Number or Round to Nearest Tenths
... A82: J159 | B82: Mathematics and statistics | D82: Disciplinary Areas of Degrees Conferred | E82: Associate | F82: 27 | G82: Undergraduates | H82: All | I82: All | J82: All | K82: All | L82: Whole Number or Round to Nearest Tenths
A83: J160 | B83: Military science and military technologies | D83: Disciplinary Areas of Degrees Conferred | E83: Associate | F83: 28 & 29 | G83: Undergraduates | H83: All | I83: All | J83: All | K83: All | L83: Whole Number or Round to Nearest Tenths
A84: J161 | B84: Interdisciplinary studies | D84: Disciplinary Areas of Degrees Conferred | E84: Associate | F84: 30 | G84: Undergraduates | H84: All | I84: All | J84: All | K84: All | L84: Whole Number or Round to Nearest Tenths
A85: J162 | B85: Parks and recreation | D85: Disciplinary Areas of Degrees Conferred | E85: Associate | F85: 31 | G85: Undergraduates | H85: All | I85: All | J85: All | K85: All | L85: Whole Number or Round to Nearest Tenths
A86: J163 | B86: Philosophy and religious studies | D86: Disciplinary Areas of Degrees Conferred | E86: Associate | F86: 38 | G86: Undergraduates | H86: All | I86: All | J86: All | K86: All | L86: Whole Number or Round to Nearest Tenths
A87: J164 | B87: Theology and religious vocations | D87: Disciplinary Areas of Degrees Conferred | E87: Associate | F87: 39 | G87: Undergraduates | H87: All | I87: All | J87: All | K87: All | L87: Whole Number or Round to Nearest Tenths
A88: J165 | B88: Physical sciences | D88: Disciplinary Areas of Degrees Conferred | E88: Associate | F88: 40 | G88: Undergraduates | H88: All | I88: All | J88: All | K88: All | L88: Whole Number or Round to Nearest Tenths
A89: J166 | B89: Science technologies | D89: Disciplinary Areas of Degrees Conferred | E89: Associate | F89: 41 | G89: Undergraduates | H89: All | I89: All | J89: All | K89: All | L89: Whole Number or Round to Nearest Tenths
A90: J167 | B90: Psychology | D90: Disciplinary Areas of Degrees Conferred | E90: Associate | F90: 42 | G90: Undergraduates | H90: All | I90: All | J90: All | K90: All | L90: Whole Number or Round to Nearest Tenths
A91: J168 | B91: Homeland Security, law enforcement, firefighting, and protective services | D91: Disciplinary Areas of Degrees Conferred | E91: Associate | F91: 43 | G91: Undergraduates | H91: All | I91: All | J91: All | K91: All | L91: Whole Number or Round to Nearest Tenths
A92: J169 | B92: Public administration and social services | D92: Disciplinary Areas of Degrees Conferred | E92: Associate | F92: 44 | G92: Undergraduates | H92: All | I92: All | J92: All | K92: All | L92: Whole Number or Round to Nearest Tenths
A93: J170 | B93: Social sciences | D93: Disciplinary Areas of Degrees Conferred | E93: Associate | F93: 45 | G93: Undergraduates | H93: All | I93: All | J93: All | K93: All | L93: Whole Number or Round to Nearest Tenths
A94: J171 | B94: Construction trades | D94: Disciplinary Areas of Degrees Conferred | E94: Associate | F94: 46 | G94: Undergraduates | H94: All | I94: All | J94: All | K94: All | L94: Whole Number or Round to Nearest Tenths
A95: J172 | B95: Mechanic and repair technologies | D95: Disciplinary Areas of Degrees Conferred | E95: Associate | F95: 47 | G95: Undergraduates | H95: All | I95: All | J95: All | K95: All | L95: Whole Number or Round to Nearest Tenths
... A101: J178 | B101: History | D101: Disciplinary Areas of Degrees Conferred | E101: Associate | F101: 54 | G101: Undergraduates | H101: All | I101: All | J101: All | K101: All | L101: Whole Number or Round to Nearest Tenths
A102: J179 | B102: Other | D102: Disciplinary Areas of Degrees Conferred | E102: Associate | F102: Other | G102: Undergraduates | H102: All | I102: All | J102: All | K102: All | L102: Whole Number or Round to Nearest Tenths
A103: J180 | B103: TOTAL (should = 100%) | C103: =SUM(C64:C102) | D103: Disciplinary Areas of Degrees Conferred | E103: Associate | F103: Total | G103: Undergraduates | H103: All | I103: All | J103: All | K103: All | L103: Whole Number or Round to Nearest Tenths
A110: J181 | B110: Agriculture | C110: 1.6 | D110: Disciplinary Areas of Degrees Conferred | E110: Bachelors | F110: 01 | G110: Undergraduates | H110: All | I110: All | J110: All | K110: All | L110: Whole Number or Round to Nearest Tenths
A111: J182 | B111: Natural resources and conservation | C111: 1.9 | D111: Disciplinary Areas of Degrees Conferred | E111: Bachelors | F111: 03 | G111: Undergraduates | H111: All | I111: All | J111: All | K111: All | L111: Whole Number or Round to Nearest Tenths
A112: J183 | B112: Architecture | C112: 0.2 | D112: Disciplinary Areas of Degrees Conferred | E112: Bachelors | F112: 04 | G112: Undergraduates | H112: All | I112: All | J112: All | K112: All | L112: Whole Number or Round to Nearest Tenths
A113: J184 | B113: Area, ethnic, and gender studies | C113: 0.7 | D113: Disciplinary Areas of Degrees Conferred | E113: Bachelors | F113: 05 | G113: Undergraduates | H113: All | I113: All | J113: All | K113: All | L113: Whole Number or Round to Nearest Tenths
A114: J185 | B114: Communication/journalism | C114: 4.1 | D114: Disciplinary Areas of Degrees Conferred | E114: Bachelors | F114: 09 | G114: Undergraduates | H114: All | I114: All | J114: All | K114: All | L114: Whole Number or Round to Nearest Tenths
A115: J186 | B115: Communication technologies | D115: Disciplinary Areas of Degrees Conferred | E115: Bachelors | F115: 10 | G115: Undergraduates | H115: All | I115: All | J115: All | K115: All | L115: Whole Number or Round to Nearest Tenths
A116: J187 | B116: Computer and information sciences | C116: 8.6 | D116: Disciplinary Areas of Degrees Conferred | E116: Bachelors | F116: 11 | G116: Undergraduates | H116: All | I116: All | J116: All | K116: All | L116: Whole Number or Round to Nearest Tenths
A117: J188 | B117: Personal and culinary services | D117: Disciplinary Areas of Degrees Conferred | E117: Bachelors | F117: 12 | G117: Undergraduates | H117: All | I117: All | J117: All | K117: All | L117: Whole Number or Round to Nearest Tenths
A118: J189 | B118: Education | C118: 2.1 | D118: Disciplinary Areas of Degrees Conferred | E118: Bachelors | F118: 13 | G118: Undergraduates | H118: All | I118: All | J118: All | K118: All | L118: Whole Number or Round to Nearest Tenths
A119: J190 | B119: Engineering | C119: 9.7 | D119: Disciplinary Areas of Degrees Conferred | E119: Bachelors | F119: 14 | G119: Undergraduates | H119: All | I119: All | J119: All | K119: All | L119: Whole Number or Round to Nearest Tenths
A120: J191 | B120: Engineering technologies | D120: Disciplinary Areas of Degrees Conferred | E120: Bachelors | F120: 15 | G120: Undergraduates | H120: All | I120: All | J120: All | K120: All | L120: Whole Number or Round to Nearest Tenths
A121: J192 | B121: Foreign languages, literatures, and linguistics | C121: 2.1 | D121: Disciplinary Areas of Degrees Conferred | E121: Bachelors | F121: 16 | G121: Undergraduates | H121: All | I121: All | J121: All | K121: All | L121: Whole Number or Round to Nearest Tenths
A122: J193 | B122: Family and consumer sciences | C122: 1.5 | D122: Disciplinary Areas of Degrees Conferred | E122: Bachelors | F122: 19 | G122: Undergraduates | H122: All | I122: All | J122: All | K122: All | L122: Whole Number or Round to Nearest Tenths
A123: J194 | B123: Law/legal studies | C123: 1.4 | D123: Disciplinary Areas of Degrees Conferred | E123: Bachelors | F123: 22 | G123: Undergraduates | H123: All | I123: All | J123: All | K123: All | L123: Whole Number or Round to Nearest Tenths
A124: J195 | B124: English | C124: 0.9 | D124: Disciplinary Areas of Degrees Conferred | E124: Bachelors | F124: 23 | G124: Undergraduates | H124: All | I124: All | J124: All | K124: All | L124: Whole Number or Round to Nearest Tenths
A125: J196 | B125: Liberal arts/general studies | D125: Disciplinary Areas of Degrees Conferred | E125: Bachelors | F125: 24 | G125: Undergraduates | H125: All | I125: All | J125: All | K125: All | L125: Whole Number or Round to Nearest Tenths
A126: J197 | B126: Library science | D126: Disciplinary Areas of Degrees Conferred | E126: Bachelors | F126: 25 | G126: Undergraduates | H126: All | I126: All | J126: All | K126: All | L126: Whole Number or Round to Nearest Tenths
A127: J198 | B127: Biological/life sciences | C127: 11.4 | D127: Disciplinary Areas of Degrees Conferred | E127: Bachelors | F127: 26 | G127: Undergraduates | H127: All | I127: All | J127: All | K127: All | L127: Whole Number or Round to Nearest Tenths
A128: J199 | B128: Mathematics and statistics | C128: 2.8 | D128: Disciplinary Areas of Degrees Conferred | E128: Bachelors | F128: 27 | G128: Undergraduates | H128: All | I128: All | J128: All | K128: All | L128: Whole Number or Round to Nearest Tenths
A129: J200 | B129: Military science and military technologies | D129: Disciplinary Areas of Degrees Conferred | E129: Bachelors | F129: 28 & 29 | G129: Undergraduates | H129: All | I129: All | J129: All | K129: All | L129: Whole Number or Round to Nearest Tenths
A130: J201 | B130: Interdisciplinary studies | C130: 6.6 | D130: Disciplinary Areas of Degrees Conferred | E130: Bachelors | F130: 30 | G130: Undergraduates | H130: All | I130: All | J130: All | K130: All | L130: Whole Number or Round to Nearest Tenths
A131: J202 | B131: Parks and recreation | C131: 2 | D131: Disciplinary Areas of Degrees Conferred | E131: Bachelors | F131: 31 | G131: Undergraduates | H131: All | I131: All | J131: All | K131: All | L131: Whole Number or Round to Nearest Tenths
A132: J203 | B132: Philosophy and religious studies | C132: 0.6 | D132: Disciplinary Areas of Degrees Conferred | E132: Bachelors | F132: 38 | G132: Undergraduates | H132: All | I132: All | J132: All | K132: All | L132: Whole Number or Round to Nearest Tenths
A133: J204 | B133: Theology and religious vocations | D133: Disciplinary Areas of Degrees Conferred | E133: Bachelors | F133: 39 | G133: Undergraduates | H133: All | I133: All | J133: All | K133: All | L133: Whole Number or Round to Nearest Tenths
A134: J205 | B134: Physical sciences | C134: 1.7 | D134: Disciplinary Areas of Degrees Conferred | E134: Bachelors | F134: 40 | G134: Undergraduates | H134: All | I134: All | J134: All | K134: All | L134: Whole Number or Round to Nearest Tenths
A135: J206 | B135: Science technologies | D135: Disciplinary Areas of Degrees Conferred | E135: Bachelors | F135: 41 | G135: Undergraduates | H135: All | I135: All | J135: All | K135: All | L135: Whole Number or Round to Nearest Tenths
A136: J207 | B136: Psychology | C136: 5.1 | D136: Disciplinary Areas of Degrees Conferred | E136: Bachelors | F136: 42 | G136: Undergraduates | H136: All | I136: All | J136: All | K136: All | L136: Whole Number or Round to Nearest Tenths
A137: J208 | B137: Homeland Security, law enforcement, firefighting, and protective services | D137: Disciplinary Areas of Degrees Conferred | E137: Bachelors | F137: 43 | G137: Undergraduates | H137: All | I137: All | J137: All | K137: All | L137: Whole Number or Round to Nearest Tenths
A138: J209 | B138: Public administration and social services | C138: 0.6 | D138: Disciplinary Areas of Degrees Conferred | E138: Bachelors | F138: 44 | G138: Undergraduates | H138: All | I138: All | J138: All | K138: All | L138: Whole Number or Round to Nearest Tenths
A139: J210 | B139: Social sciences | C139: 10.5 | D139: Disciplinary Areas of Degrees Conferred | E139: Bachelors | F139: 45 | G139: Undergraduates | H139: All | I139: All | J139: All | K139: All | L139: Whole Number or Round to Nearest Tenths
A140: J211 | B140: Construction trades | D140: Disciplinary Areas of Degrees Conferred | E140: Bachelors | F140: 46 | G140: Undergraduates | H140: All | I140: All | J140: All | K140: All | L140: Whole Number or Round to Nearest Tenths
...

Sheet CDS Definitions
A1: Common Data Set Definitions
A2: ¨ All definitions related to the financial aid section appear at the end of the Definitions document.
A4: ¨ Items preceded by an asterisk (*) represent definitions agreed to among publishers which do not appear on the CDS document but may be present on individual publishers’ surveys.
A6: ¨ Additional guidance for some terms, particularly those common with the IPEDS survey, may be found here: https://surveys.nces.ed.gov/ipeds/public/glossary
A8: *Academic advisement: Plan under which each student is assigned to a faculty member or a trained adviser, who, through regular meetings, helps the student plan and implement immediate and long-term academic and vocational goals.
A9: Accelerated program: Completion of a college program of study in fewer than the usual number of years, most often by attending summer sessions and carrying extra courses during the regular academic term.
A10: Admitted student: Applicant who is offered admission to a degree-granting program at your institution.
A12: *Adult student services: Admission assistance, support, orientation, and other services expressly for adults who have started college for the first time, or who are re-entering after a lapse of a few years.
A13: American Indian or Alaska Native: A person having origins in any of the original peoples of North and South America (including Central America) and maintaining tribal affiliation or community attachment.
A14: Applicant (first-time, first year): An individual who has fulfilled the institution’s requirements to be considered for admission (including payment or waiving of the application fee, if any) and who has been notified of one of the following actions: admission, nonadmission, placement on waiting list, or application withdrawn (by applicant or institution).
A15: Application fee: That amount of money that an institution charges for processing a student’s application for acceptance. This amount is not creditable toward tuition and required fees, nor is it refundable if the student is not admitted to the institution.
A16: Asian: A person having origins in any of the original peoples of the Far East, Southeast Asia, or the Indian subcontinent, including, for example, Cambodia, China, India, Japan, Korea, Malaysia, Pakistan, the Philippine Islands, Thailand, and Vietnam.
... A190: Work study and employment: Federal and state work study aid, and any employment packaged by your institution in financial aid awards.

Sheet Answer Sheet
A1: Question Number | B1: Question | C1: Answer | D1: Section | E1: Sub-Section | F1: Category | G1: Student Group | H1: Cohort | I1: Residency | J1: Unit load | K1: Gender | L1: Value type
A2: A01 | B2: Name: | C2: =IFERROR(IF(VLOOKUP($A2,'CDS-A'!$A:$L,3,FALSE)="","",(VLOOKUP($A2,'CDS-A'!$A:$L,3,FALSE))),"") | D2: General Information | E2: Respondent Information | F2: All | G2: All | H2: All | I2: All | J2: All | K2: All | L2: Text
A3: A02 | B3: Title: | C3: =IFERROR(IF(VLOOKUP($A3,'CDS-A'!$A:$L,3,FALSE)="","",(VLOOKUP($A3,'CDS-A'!$A:$L,3,FALSE))),"") | D3: General Information | E3: Respondent Information | F3: All | G3: All | H3: All | I3: All | J3: All | K3: All | L3: Text
A4: A03 | B4: Office: | C4: =IFERROR(IF(VLOOKUP($A4,'CDS-A'!$A:$L,3,FALSE)="","",(VLOOKUP($A4,'CDS-A'!$A:$L,3,FALSE))),"") | D4: General Information | E4: Respondent Information | F4: All | G4: All | H4: All | I4: All | J4: All | K4: All | L4: Text
A5: A04 | B5: Mailing Address: | C5: =IFERROR(IF(VLOOKUP($A5,'CDS-A'!$A:$L,3,FALSE)="","",(VLOOKUP($A5,'CDS-A'!$A:$L,3,FALSE))),"") | D5: General Information | E5: Respondent Information | F5: All | G5: All | H5: All | I5: All | J5: All | K5: All | L5: Text
A6: A05 | B6: City/State/Zip/Country: | C6: =IFERROR(IF(VLOOKUP($A6,'CDS-A'!$A:$L,3,FALSE)="","",(VLOOKUP($A6,'CDS-A'!$A:$L,3,FALSE))),"") | D6: General Information | E6: Respondent Information | F6: All | G6: All | H6: All | I6: All | J6: All | K6: All | L6: Text
A7: A06 | B7: Phone: | C7: =IFERROR(IF(VLOOKUP($A7,'CDS-A'!$A:$L,3,FALSE)="","",(VLOOKUP($A7,'CDS-A'!$A:$L,3,FALSE))),"") | D7: General Information | E7: Respondent Information | F7: All | G7: All | H7: All | I7: All | J7: All | K7: All | L7: Text
A8: A07 | B8: Fax: | C8: =IFERROR(IF(VLOOKUP($A8,'CDS-A'!$A:$L,3,FALSE)="","",(VLOOKUP($A8,'CDS-A'!$A:$L,3,FALSE))),"") | D8: General Information | E8: Respondent Information | F8: All | G8: All | H8: All | I8: All | J8: All | K8: All | L8: Text
A9: A08 | B9: E-mail Address: | C9: =IFERROR(IF(VLOOKUP($A9,'CDS-A'!$A:$L,3,FALSE)="","",(VLOOKUP($A9,'CDS-A'!$A:$L,3,FALSE))),"") | D9: General Information | E9: Respondent Information | F9: All | G9: All | H9: All | I9: All | J9: All | K9: All | L9: Email Address
A10: A09 | B10: Are your responses to the CDS posted for reference on your institution's Web site? | C10: =IFERROR(IF(VLOOKUP($A10,'CDS-A'!$A:$L,3,FALSE)="","",(VLOOKUP($A10,'CDS-A'!$A:$L,3,FALSE))),"") | D10: General Information | E10: Respondent Information | F10: All | G10: All | H10: All | I10: All | J10: All | K10: All | L10: YN
A11: A010 | B11: If yes, please provide the URL of the corresponding Web page: | C11: =IFERROR(IF(VLOOKUP($A11,'CDS-A'!$A:$L,3,FALSE)="","",(VLOOKUP($A11,'CDS-A'!$A:$L,3,FALSE))),"") | D11: General Information | E11: Respondent Information | F11: All | G11: All | H11: All | I11: All | J11: All | K11: All | L11: URL
A12: A0A | B12: We invite you to indicate if there are items on the CDS for which you cannot use the requested analytic convention, cannot provide data for the cohort requested, whose methodology is unclear, or about which you have questions or comments in general. This information will not be published but will help the publishers further refine CDS items. | C12: =IFERROR(IF(VLOOKUP($A12,'CDS-A'!$A:$L,3,FALSE)="","",(VLOOKUP($A12,'CDS-A'!$A:$L,3,FALSE))),"") | D12: General Information | E12: Respondent Information | F12: All | G12: All | H12: All | I12: All | J12: All | K12: All | L12: Text
A13: A101 | B13: Name of College/University: | C13: =IFERROR(IF(VLOOKUP($A13,'CDS-A'!$A:$L,3,FALSE)="","",(VLOOKUP($A13,'CDS-A'!$A:$L,3,FALSE))),"") | D13: General Information | E13: Address Information | F13: All | G13: All | H13: All | I13: All | J13: All | K13: All | L13: Text
... A52: A601 | B52: If you have a diversity, equity, and inclusion office or department, please provide the URL of the corresponding Web page: | C52: =IFERROR(IF(VLOOKUP($A52,'CDS-A'!$A:$L,3,FALSE)="","",(VLOOKUP($A52,'CDS-A'!$A:$L,3,FALSE))),"") | D52: General Information | E52: DEI | F52: All | G52: All | H52: All | I52: All | J52: All | K52: All | L52: URL
A53: B101 | B53: Degree-seeking, first-time first-year students: men | C53: =IFERROR(IF(VLOOKUP($A53,'CDS-B'!$A:$L,3,FALSE)="","",(VLOOKUP($A53,'CDS-B'!$A:$L,3,FALSE))),"") | D53: Enrollment And Persistence | E53: Institutional Enrollment | F53: Degree-seeking | G53: Undergraduates | H53: First-time, first-year | I53: All | J53: FT | K53: Men | L53: Number
A54: B102 | B54: Degree-seeking, first-time first-year students: women | C54: =IFERROR(IF(VLOOKUP($A54,'CDS-B'!$A:$L,3,FALSE)="","",(VLOOKUP($A54,'CDS-B'!$A:$L,3,FALSE))),"") | D54: Enrollment And Persistence | E54: Institutional Enrollment | F54: Degree-seeking | G54: Undergraduates | H54: First-time, first-year | I54: All | J54: FT | K54: Women | L54: Number
A55: B103 | B55: Degree-seeking, first-time first-year students: another gender | C55: =IFERROR(IF(VLOOKUP($A55,'CDS-B'!$A:$L,3,FALSE)="","",(VLOOKUP($A55,'CDS-B'!$A:$L,3,FALSE))),"") | D55: Enrollment And Persistence | E55: Institutional Enrollment | F55: Degree-seeking | G55: Undergraduates | H55: First-time, first-year | I55: All | J55: FT | K55: Another Gender | L55: Number
A56: B104 | B56: Degree-seeking, first-time first-year students: unknown | C56: =IFERROR(IF(VLOOKUP($A56,'CDS-B'!$A:$L,3,FALSE)="","",(VLOOKUP($A56,'CDS-B'!$A:$L,3,FALSE))),"") | D56: Enrollment And Persistence | E56: Institutional Enrollment | F56: Degree-seeking | G56: Undergraduates | H56: First-time, first-year | I56: All | J56: FT | K56: Unknown | L56: Number
A57: B105 | B57: Other first-year, degree-seeking: men | C57: =IFERROR(IF(VLOOKUP($A57,'CDS-B'!$A:$L,3,FALSE)="","",(VLOOKUP($A57,'CDS-B'!$A:$L,3,FALSE))),"") | D57: Enrollment And Persistence | E57: Institutional Enrollment | F57: Degree-seeking | G57: Undergraduates | H57: Other first-year | I57: All | J57: FT | K57: Men | L57: Number
A58: B106 | B58: Other first-year, degree-seeking: women | C58: =IFERROR(IF(VLOOKUP($A58,'CDS-B'!$A:$L,3,FALSE)="","",(VLOOKUP($A58,'CDS-B'!$A:$L,3,FALSE))),"") | D58: Enrollment And Persistence | E58: Institutional Enrollment | F58: Degree-seeking | G58: Undergraduates | H58: Other first-year | I58: All | J58: FT | K58: Women | L58: Number
A59: B107 | B59: Other first-year, degree-seeking: another gender | C59: =IFERROR(IF(VLOOKUP($A59,'CDS-B'!$A:$L,3,FALSE)="","",(VLOOKUP($A59,'CDS-B'!$A:$L,3,FALSE))),"") | D59: Enrollment And Persistence | E59: Institutional Enrollment | F59: Degree-seeking | G59: Undergraduates | H59: Other first-year | I59: All | J59: FT | K59: Another Gender | L59: Number
A60: B108 | B60: Other first-year, degree-seeking: unknown | C60: =IFERROR(IF(VLOOKUP($A60,'CDS-B'!$A:$L,3,FALSE)="","",(VLOOKUP($A60,'CDS-B'!$A:$L,3,FALSE))),"") | D60: Enrollment And Persistence | E60: Institutional Enrollment | F60: Degree-seeking | G60: Undergraduates | H60: Other first-year | I60: All | J60: FT | K60: Unknown | L60: Number
A61: B109 | B61: All other degree-seeking: men | C61: =IFERROR(IF(VLOOKUP($A61,'CDS-B'!$A:$L,3,FALSE)="","",(VLOOKUP($A61,'CDS-B'!$A:$L,3,FALSE))),"") | D61: Enrollment And Persistence | E61: Institutional Enrollment | F61: Degree-seeking | G61: Undergraduates | H61: All other | I61: All | J61: FT | K61: Men | L61: Number
A62: B110 | B62: All other degree-seeking: women | C62: =IFERROR(IF(VLOOKUP($A62,'CDS-B'!$A:$L,3,FALSE)="","",(VLOOKUP($A62,'CDS-B'!$A:$L,3,FALSE))),"") | D62: Enrollment And Persistence | E62: Institutional Enrollment | F62: Degree-seeking | G62: Undergraduates | H62: All other | I62: All | J62: FT | K62: Women | L62: Number
A63: B111 | B63: All other degree-seeking: another gender | C63: =IFERROR(IF(VLOOKUP($A63,'CDS-B'!$A:$L,3,FALSE)="","",(VLOOKUP($A63,'CDS-B'!$A:$L,3,FALSE))),"") | D63: Enrollment And Persistence | E63: Institutional Enrollment | F63: Degree-seeking | G63: Undergraduates | H63: All other | I63: All | J63: FT | K63: Another Gender | L63: Number
A64: B112 | B64: All other degree-seeking: unknown | C64: =IFERROR(IF(VLOOKUP($A64,'CDS-B'!$A:$L,3,FALSE)="","",(VLOOKUP($A64,'CDS-B'!$A:$L,3,FALSE))),"") | D64: Enrollment And Persistence | E64: Institutional Enrollment | F64: Degree-seeking | G64: Undergraduates | H64: All other | I64: All | J64: FT | K64: Unknown | L64: Number
... A270: B2102 | B270: 2020 Cohort | C270: =IFERROR(IF(VLOOKUP($A270,'CDS-B'!$A:$L,3,FALSE)="","",(VLOOKUP($A270,'CDS-B'!$A:$L,3,FALSE))),"") | D270: Enrollment And Persistence | E270: Graduation Rates | F270: Two Year | G270: Transfers Out Four | H270: Previous Year | I270: All | J270: All | K270: All | L270: Number
A271: C101 | B271: Total first-time, first-year men who applied | C271: =IFERROR(IF(VLOOKUP($A271,'CDS-C'!$A:$L,3,FALSE)="","",(VLOOKUP($A271,'CDS-C'!$A:$L,3,FALSE))),"") | D271: First-Time, First-Year Admission | E271: Applications | F271: Applied | G271: Undergraduates | H271: First-time, first-year | I271: All | J271: All | K271: Men | L271: Number
A272: C102 | B272: Total first-time, first-year women who applied | C272: =IFERROR(IF(VLOOKUP($A272,'CDS-C'!$A:$L,3,FALSE)="","",(VLOOKUP($A272,'CDS-C'!$A:$L,3,FALSE))),"") | D272: First-Time, First-Year Admission | E272: Applications | F272: Applied | G272: Undergraduates | H272: First-time, first-year | I272: All | J272: All | K272: Women | L272: Number
A273: C103 | B273: Total first-time, first-year another gender who applied | C273: =IFERROR(IF(VLOOKUP($A273,'CDS-C'!$A:$L,3,FALSE)="","",(VLOOKUP($A273,'CDS-C'!$A:$L,3,FALSE))),"") | D273: First-Time, First-Year Admission | E273: Applications | F273: Applied | G273: Undergraduates | H273: First-time, first-year | I273: All | J273: All | K273: Another Gender | L273: Number
A274: C104 | B274: Total first-time, first-year unknown gender who applied | C274: =IFERROR(IF(VLOOKUP($A274,'CDS-C'!$A:$L,3,FALSE)="","",(VLOOKUP($A274,'CDS-C'!$A:$L,3,FALSE))),"") | D274: First-Time, First-Year Admission | E274: Applications | F274: Applied | G274: Undergraduates | H274: First-time, first-year | I274: All | J274: All | K274: Unknown | L274: Number
A275: C105 | B275: Total first-time, first-year men who were admitted | C275: =IFERROR(IF(VLOOKUP($A275,'CDS-C'!$A:$L,3,FALSE)="","",(VLOOKUP($A275,'CDS-C'!$A:$L,3,FALSE))),"") | D275: First-Time, First-Year Admission | E275: Applications | F275: Admitted | G275: Undergraduates | H275: First-time, first-year | I275: All | J275: All | K275: Men | L275: Number
A276: C106 | B276: Total first-time, first-year women who were admitted | C276: =IFERROR(IF(VLOOKUP($A276,'CDS-C'!$A:$L,3,FALSE)="","",(VLOOKUP($A276,'CDS-C'!$A:$L,3,FALSE))),"") | D276: First-Time, First-Year Admission | E276: Applications | F276: Admitted | G276: Undergraduates | H276: First-time, first-year | I276: All | J276: All | K276: Women | L276: Number
A277: C107 | B277: Total first-time, first-year another gender who were admitted | C277: =IFERROR(IF(VLOOKUP($A277,'CDS-C'!$A:$L,3,FALSE)="","",(VLOOKUP($A277,'CDS-C'!$A:$L,3,FALSE))),"") | D277: First-Time, First-Year Admission | E277: Applications | F277: Admitted | G277: Undergraduates | H277: First-time, first-year | I277: All | J277: All | K277: Another Gender | L277: Number
A278: C108 | B278: Total first-time, first-year unknown gender who were admitted | C278: =IFERROR(IF(VLOOKUP($A278,'CDS-C'!$A:$L,3,FALSE)="","",(VLOOKUP($A278,'CDS-C'!$A:$L,3,FALSE))),"") | D278: First-Time, First-Year Admission | E278: Applications | F278: Admitted | G278: Undergraduates | H278: First-time, first-year | I278: All | J278: All | K278: Unknown | L278: Number
A279: C109 | B279: Total full-time, first-time, first-year men who enrolled | C279: =IFERROR(IF(VLOOKUP($A279,'CDS-C'!$A:$L,3,FALSE)="","",(VLOOKUP($A279,'CDS-C'!$A:$L,3,FALSE))),"") | D279: First-Time, First-Year Admission | E279: Applications | F279: Enrolled | G279: Undergraduates | H279: First-time, first-year | I279: All | J279: All | K279: Men | L279: Number
A280: C110 | B280: Total part-time, first-time, first-year men who enrolled | C280: =IFERROR(IF(VLOOKUP($A280,'CDS-C'!$A:$L,3,FALSE)="","",(VLOOKUP($A280,'CDS-C'!$A:$L,3,FALSE))),"") | D280: First-Time, First-Year Admission | E280: Applications | F280: Enrolled | G280: Undergraduates | H280: First-time, first-year | I280: All | J280: PT | K280: Men | L280: Number
A281: C111 | B281: Total full-time, first-time, first-year women who enrolled | C281: =IFERROR(IF(VLOOKUP($A281,'CDS-C'!$A:$L,3,FALSE)="","",(VLOOKUP($A281,'CDS-C'!$A:$L,3,FALSE))),"") | D281: First-Time, First-Year Admission | E281: Applications | F281: Enrolled | G281: Undergraduates | H281: First-time, first-year | I281: All | J281: FT | K281: Women | L281: Number
A282: C112 | B282: Total part-time, first-time, first-year women who enrolled | C282: =IFERROR(IF(VLOOKUP($A282,'CDS-C'!$A:$L,3,FALSE)="","",(VLOOKUP($A282,'CDS-C'!$A:$L,3,FALSE))),"") | D282: First-Time, First-Year Admission | E282: Applications | F282: Enrolled | G282: Undergraduates | H282: First-time, first-year | I282: All | J282: PT | K282: Women | L282: Number
... A548: C2204 | B548: Is your early action plan a “restrictive” plan under which you limit students from applying to other early plans? | C548: =IFERROR(IF(VLOOKUP($A548,'CDS-C'!$A:$L,3,FALSE)="","",(VLOOKUP($A548,'CDS-C'!$A:$L,3,FALSE))),"") | D548: First-Time, First-Year Admission | E548: Admission Policies | F548: Early Action | G548: Undergraduates | H548: First-time, first-year | I548: All | J548: All | K548: All | L548: YN
A549: D101 | B549: Does your institution enroll transfer students? (If no, please skip to Section E) | C549: =IFERROR(IF(VLOOKUP($A549,'CDS-D'!$A:$L,3,FALSE)="","",(VLOOKUP($A549,'CDS-D'!$A:$L,3,FALSE))),"") | D549: Transfer Admission | E549: Fall Applicants | F549: All | G549: Undergraduates | H549: Transfer | I549: All | J549: All | K549: All | L549: YN
A550: D102 | B550: If yes, may transfer students earn advanced standing credit by transferring credits earned from course work completed at other colleges/universities? | C550: =IFERROR(IF(VLOOKUP($A550,'CDS-D'!$A:$L,3,FALSE)="","",(VLOOKUP($A550,'CDS-D'!$A:$L,3,FALSE))),"") | D550: Transfer Admission | E550: Fall Applicants | F550: All | G550: Undergraduates | H550: Transfer | I550: All | J550: All | K550: All | L550: YN
A551: D201 | B551: Men | C551: =IFERROR(IF(VLOOKUP($A551,'CDS-D'!$A:$L,3,FALSE)="","",(VLOOKUP($A551,'CDS-D'!$A:$L,3,FALSE))),"") | D551: Transfer Admission | E551: Fall Applicants | F551: Applied | G551: Undergraduates | H551: Transfer | I551: All | J551: All | K551: Men | L551: Number
A552: D202 | B552: Women | C552: =IFERROR(IF(VLOOKUP($A552,'CDS-D'!$A:$L,3,FALSE)="","",(VLOOKUP($A552,'CDS-D'!$A:$L,3,FALSE))),"") | D552: Transfer Admission | E552: Fall Applicants | F552: Applied | G552: Undergraduates | H552: Transfer | I552: All | J552: All | K552: Women | L552: Number
A553: D203 | B553: Another Gender | C553: =IFERROR(IF(VLOOKUP($A553,'CDS-D'!$A:$L,3,FALSE)="","",(VLOOKUP($A553,'CDS-D'!$A:$L,3,FALSE))),"") | D553: Transfer Admission | E553: Fall Applicants | F553: Applied | G553: Undergraduates | H553: Transfer | I553: All | J553: All | K553: Another Gender | L553: Number
A554: D204 | B554: Unknown | C554: =IFERROR(IF(VLOOKUP($A554,'CDS-D'!$A:$L,3,FALSE)="","",(VLOOKUP($A554,'CDS-D'!$A:$L,3,FALSE))),"") | D554: Transfer Admission | E554: Fall Applicants | F554: Applied | G554: Undergraduates | H554: Transfer | I554: All | J554: All | K554: Unknown | L554: Number
A555: D205 | B555: Total | C555: =IFERROR(IF(VLOOKUP($A555,'CDS-D'!$A:$L,3,FALSE)="","",(VLOOKUP($A555,'CDS-D'!$A:$L,3,FALSE))),"") | D555: Transfer Admission | E555: Fall Applicants | F555: Applied | G555: Undergraduates | H555: Transfer | I555: All | J555: All | K555: All | L555: Number
A556: D206 | B556: Men | C556: =IFERROR(IF(VLOOKUP($A556,'CDS-D'!$A:$L,3,FALSE)="","",(VLOOKUP($A556,'CDS-D'!$A:$L,3,FALSE))),"") | D556: Transfer Admission | E556: Fall Applicants | F556: Admitted | G556: Undergraduates | H556: Transfer | I556: All | J556: All | K556: Men | L556: Number
A557: D207 | B557: Women | C557: =IFERROR(IF(VLOOKUP($A557,'CDS-D'!$A:$L,3,FALSE)="","",(VLOOKUP($A557,'CDS-D'!$A:$L,3,FALSE))),"") | D557: Transfer Admission | E557: Fall Applicants | F557: Admitted | G557: Undergraduates | H557: Transfer | I557: All | J557: All | K557: Women | L557: Number
A558: D208 | B558: Another Gender | C558: =IFERROR(IF(VLOOKUP($A558,'CDS-D'!$A:$L,3,FALSE)="","",(VLOOKUP($A558,'CDS-D'!$A:$L,3,FALSE))),"") | D558: Transfer Admission | E558: Fall Applicants | F558: Admitted | G558: Undergraduates | H558: Transfer | I558: All | J558: All | K558: Another Gender | L558: Number
A559: D209 | B559: Unknown | C559: =IFERROR(IF(VLOOKUP($A559,'CDS-D'!$A:$L,3,FALSE)="","",(VLOOKUP($A559,'CDS-D'!$A:$L,3,FALSE))),"") | D559: Transfer Admission | E559: Fall Applicants | F559: Admitted | G559: Undergraduates | H559: Transfer | I559: All | J559: All | K559: Unknown | L559: Number
A560: D210 | B560: Total | C560: =IFERROR(IF(VLOOKUP($A560,'CDS-D'!$A:$L,3,FALSE)="","",(VLOOKUP($A560,'CDS-D'!$A:$L,3,FALSE))),"") | D560: Transfer Admission | E560: Fall Applicants | F560: Admitted | G560: Undergraduates | H560: Transfer | I560: All | J560: All | K560: All | L560: Number
... A621: D2202 | B621: Describe other military/veteran transfer credit policies unique to your institution: | C621: =IFERROR(IF(VLOOKUP($A621,'CDS-D'!$A:$L,3,FALSE)="","",(VLOOKUP($A621,'CDS-D'!$A:$L,3,FALSE))),"") | D621: Transfer Admission | E621: Transfer Credit Policies | F621: Military Service | G621: Undergraduates | H621: Transfer | I621: All | J621: All | K621: All | L621: Text
A622: E101 | B622: Accelerated program | C622: =IFERROR(IF(VLOOKUP($A622,'CDS-E'!$A:$L,3,FALSE)="","",(VLOOKUP($A622,'CDS-E'!$A:$L,3,FALSE))),"") | D622: Academic Offerings and Policies | E622: Special Study Options | F622: All | G622: All | H622: All | I622: All | J622: All | K622: All | L622: x
A623: E102 | B623: Comprehensive transition and postsecondary program for students with intellectual disabilities | C623: =IFERROR(IF(VLOOKUP($A623,'CDS-E'!$A:$L,3,FALSE)="","",(VLOOKUP($A623,'CDS-E'!$A:$L,3,FALSE))),"") | D623: Academic Offerings and Policies | E623: Special Study Options | F623: All | G623: All | H623: All | I623: All | J623: All | K623: All | L623: x
A624: E103 | B624: Cross-registration | C624: =IFERROR(IF(VLOOKUP($A624,'CDS-E'!$A:$L,3,FALSE)="","",(VLOOKUP($A624,'CDS-E'!$A:$L,3,FALSE))),"") | D624: Academic Offerings and Policies | E624: Special Study Options | F624: All | G624: All | H624: All | I624: All | J624: All | K624: All | L624: x
A625: E104 | B625: Distance learning | C625: =IFERROR(IF(VLOOKUP($A625,'CDS-E'!$A:$L,3,FALSE)="","",(VLOOKUP($A625,'CDS-E'!$A:$L,3,FALSE))),"") | D625: Academic Offerings and Policies | E625: Special Study Options | F625: All | G625: All | H625: All | I625: All | J625: All | K625: All | L625: x
A626: E105 | B626: Double major | C626: =IFERROR(IF(VLOOKUP($A626,'CDS-E'!$A:$L,3,FALSE)="","",(VLOOKUP($A626,'CDS-E'!$A:$L,3,FALSE))),"") | D626: Academic Offerings and Policies | E626: Special Study Options | F626: All | G626: All | H626: All | I626: All | J626: All | K626: All | L626: x
A627: E106 | B627: Dual enrollment | C627: =IFERROR(IF(VLOOKUP($A627,'CDS-E'!$A:$L,3,FALSE)="","",(VLOOKUP($A627,'CDS-E'!$A:$L,3,FALSE))),"") | D627: Academic Offerings and Policies | E627: Special Study Options | F627: All | G627: All | H627: All | I627: All | J627: All | K627: All | L627: x
A628: E107 | B628: English as a Second Language (ESL) | C628: =IFERROR(IF(VLOOKUP($A628,'CDS-E'!$A:$L,3,FALSE)="","",(VLOOKUP($A628,'CDS-E'!$A:$L,3,FALSE))),"") | D628: Academic Offerings and Policies | E628: Special Study Options | F628: All | G628: All | H628: All | I628: All | J628: All | K628: All | L628: x
A629: E108 | B629: Exchange student program (domestic) | C629: =IFERROR(IF(VLOOKUP($A629,'CDS-E'!$A:$L,3,FALSE)="","",(VLOOKUP($A629,'CDS-E'!$A:$L,3,FALSE))),"") | D629: Academic Offerings and Policies | E629: Special Study Options | F629: All | G629: All | H629: All | I629: All | J629: All | K629: All | L629: x
A630: E109 | B630: External degree program | C630: =IFERROR(IF(VLOOKUP($A630,'CDS-E'!$A:$L,3,FALSE)="","",(VLOOKUP($A630,'CDS-E'!$A:$L,3,FALSE))),"") | D630: Academic Offerings and Policies | E630: Special Study Options | F630: All | G630: All | H630: All | I630: All | J630: All | K630: All | L630: x
A631: E110 | B631: Honors Program | C631: =IFERROR(IF(VLOOKUP($A631,'CDS-E'!$A:$L,3,FALSE)="","",(VLOOKUP($A631,'CDS-E'!$A:$L,3,FALSE))),"") | D631: Academic Offerings and Policies | E631: Special Study Options | F631: All | G631: All | H631: All | I631: All | J631: All | K631: All | L631: x
A632: E111 | B632: Independent study | C632: =IFERROR(IF(VLOOKUP($A632,'CDS-E'!$A:$L,3,FALSE)="","",(VLOOKUP($A632,'CDS-E'!$A:$L,3,FALSE))),"") | D632: Academic Offerings and Policies | E632: Special Study Options | F632: All | G632: All | H632: All | I632: All | J632: All | K632: All | L632: x
A633: E112 | B633: Internships | C633: =IFERROR(IF(VLOOKUP($A633,'CDS-E'!$A:$L,3,FALSE)="","",(VLOOKUP($A633,'CDS-E'!$A:$L,3,FALSE))),"") | D633: Academic Offerings and Policies | E633: Special Study Options | F633: All | G633: All | H633: All | I633: All | J633: All | K633: All | L633: x
... A653: E313 | B653: Other (describe): | C653: =IFERROR(IF(VLOOKUP($A653,'CDS-E'!$A:$L,3,FALSE)="","",(VLOOKUP($A653,'CDS-E'!$A:$L,3,FALSE))),"") | D653: Academic Offerings and Policies | E653: Required Course Work | F653: All | G653: All | H653: All | I653: All | J653: All | K653: All | L653: Text
A654: F101 | B654: Percent who are from out of state (exclude international/nonresidents from the numerator and denominator) | C654: =IFERROR(IF(VLOOKUP($A654,'CDS-F'!$A:$L,3,FALSE)="","",(VLOOKUP($A654,'CDS-F'!$A:$L,3,FALSE))),"") | D654: Student Life | E654: Percent Participating | F654: Degree-Seeking | G654: Undergraduates | H654: First-time, first-year | I654: All | J654: All | K654: All | L654: Nearest 1%
A655: F102 | B655: Percent of men who join fraternities | C655: =IFERROR(IF(VLOOKUP($A655,'CDS-F'!$A:$L,3,FALSE)="","",(VLOOKUP($A655,'CDS-F'!$A:$L,3,FALSE))),"") | D655: Student Life | E655: Percent Participating | F655: Degree-Seeking | G655: Undergraduates | H655: First-time, first-year | I655: All | J655: All | K655: All | L655: Nearest 1%
A656: F103 | B656: Percent of women who join sororities | C656: =IFERROR(IF(VLOOKUP($A656,'CDS-F'!$A:$L,3,FALSE)="","",(VLOOKUP($A656,'CDS-F'!$A:$L,3,FALSE))),"") | D656: Student Life | E656: Percent Participating | F656: Degree-Seeking | G656: Undergraduates | H656: First-time, first-year | I656: All | J656: All | K656: All | L656: Nearest 1%
A657: F104 | B657: Percent who live in college-owned, -operated, or -affiliated housing | C657: =IFERROR(IF(VLOOKUP($A657,'CDS-F'!$A:$L,3,FALSE)="","",(VLOOKUP($A657,'CDS-F'!$A:$L,3,FALSE))),"") | D657: Student Life | E657: Percent Participating | F657: Degree-Seeking | G657: Undergraduates | H657: First-time, first-year | I657: All | J657: All | K657: All | L657: Nearest 1%
A658: F105 | B658: Percent who live off campus or commute | C658: =IFERROR(IF(VLOOKUP($A658,'CDS-F'!$A:$L,3,FALSE)="","",(VLOOKUP($A658,'CDS-F'!$A:$L,3,FALSE))),"") | D658: Student Life | E658: Percent Participating | F658: Degree-Seeking | G658: Undergraduates | H658: First-time, first-year | I658: All | J658: All | K658: All | L658: Nearest 1%
A659: F106 | B659: Percent of students age 25 and older | C659: =IFERROR(IF(VLOOKUP($A659,'CDS-F'!$A:$L,3,FALSE)="","",(VLOOKUP($A659,'CDS-F'!$A:$L,3,FALSE))),"") | D659: Student Life | E659: Percent Participating | F659: Degree-Seeking | G659: Undergraduates | H659: First-time, first-year | I659: All | J659: All | K659: All | L659: Nearest 1%
A660: F107 | B660: Average age of full-time students | C660: =IFERROR(IF(VLOOKUP($A660,'CDS-F'!$A:$L,3,FALSE)="","",(VLOOKUP($A660,'CDS-F'!$A:$L,3,FALSE))),"") | D660: Student Life | E660: Average Age | F660: Degree-Seeking | G660: Undergraduates | H660: First-time, first-year | I660: All | J660: All | K660: All | L660: Whole Number or Round to Nearest Tenths
A661: F108 | B661: Average age of all students (full- and part-time) | C661: =IFERROR(IF(VLOOKUP($A661,'CDS-F'!$A:$L,3,FALSE)="","",(VLOOKUP($A661,'CDS-F'!$A:$L,3,FALSE))),"") | D661: Student Life | E661: Average Age | F661: Degree-Seeking | G661: Undergraduates | H661: First-time, first-year | I661: All | J661: All | K661: All | L661: Whole Number or Round to Nearest Tenths
A662: F109 | B662: Percent who are from out of state (exclude international/nonresidents from the numerator and denominator) | C662: =IFERROR(IF(VLOOKUP($A662,'CDS-F'!$A:$L,3,FALSE)="","",(VLOOKUP($A662,'CDS-F'!$A:$L,3,FALSE))),"") | D662: Student Life | E662: Percent Participating | F662: Degree-Seeking | G662: Undergraduates | H662: Undergraduates | I662: All | J662: All | K662: All | L662: Nearest 1%
A663: F110 | B663: Percent of men who join fraternities | C663: =IFERROR(IF(VLOOKUP($A663,'CDS-F'!$A:$L,3,FALSE)="","",(VLOOKUP($A663,'CDS-F'!$A:$L,3,FALSE))),"") | D663: Student Life | E663: Percent Participating | F663: Degree-Seeking | G663: Undergraduates | H663: Undergraduates | I663: All | J663: All | K663: All | L663: Nearest 1%
A664: F111 | B664: Percent of women who join sororities | C664: =IFERROR(IF(VLOOKUP($A664,'CDS-F'!$A:$L,3,FALSE)="","",(VLOOKUP($A664,'CDS-F'!$A:$L,3,FALSE))),"") | D664: Student Life | E664: Percent Participating | F664: Degree-Seeking | G664: Undergraduates | H664: Undergraduates | I664: All | J664: All | K664: All | L664: Nearest 1%
A665: F112 | B665: Percent who live in college-owned, -operated, or -affiliated housing | C665: =IFERROR(IF(VLOOKUP($A665,'CDS-F'!$A:$L,3,FALSE)="","",(VLOOKUP($A665,'CDS-F'!$A:$L,3,FALSE))),"") | D665: Student Life | E665: Percent Participating | F665: Degree-Seeking | G665: Undergraduates | H665: Undergraduates | I665: All | J665: All | K665: All | L665: Nearest 1%
... A713: F413 | B713: Other housing options (specify): | C713: =IFERROR(IF(VLOOKUP($A713,'CDS-F'!$A:$L,3,FALSE)="","",(VLOOKUP($A713,'CDS-F'!$A:$L,3,FALSE))),"") | D713: Student Life | E713: Housing | F713: All | G713: All | H713: All | I713: All | J713: All | K713: All | L713: Text
A714: G001 | B714: Please provide the URL of your institution’s net price calculator: | C714: =IFERROR(IF(VLOOKUP($A714,'CDS-G'!$A:$L,3,FALSE)="","",(VLOOKUP($A714,'CDS-G'!$A:$L,3,FALSE))),"") | D714: Annual Expenses | E714: Information | F714: All | G714: All | H714: All | I714: All | J714: All | K714: All | L714: URL
A715: G002 | B715: If your institution's 2025-2026 academic year costs of attendance are not available at this time please respond. | C715: =IFERROR(IF(VLOOKUP($A715,'CDS-G'!$A:$L,3,FALSE)="","",(VLOOKUP($A715,'CDS-G'!$A:$L,3,FALSE))),"") | D715: Annual Expenses | E715: Information | F715: All | G715: All | H715: All | I715: All | J715: All | K715: All | L715: x
A716: G003 | B716: Please provide an approximate date (i.e., month/day) when your institution's final 2025-2026 academic year costs of attendance will be available: | C716: =IFERROR(IF(VLOOKUP($A716,'CDS-G'!$A:$L,3,FALSE)="","",(VLOOKUP($A716,'CDS-G'!$A:$L,3,FALSE))),"") | D716: Annual Expenses | E716: Information | F716: All | G716: All | H716: All | I716: All | J716: All | K716: All | L716: MM-DD
A717: G101 | B717: Tuition | C717: =IFERROR(IF(VLOOKUP($A717,'CDS-G'!$A:$L,3,FALSE)="","",(VLOOKUP($A717,'CDS-G'!$A:$L,3,FALSE))),"") | D717: Annual Expenses | E717: Private Tuition | F717: Full-Time | G717: Undergraduate | H717: First-year | I717: All | J717: All | K717: All | L717: Nearest $1
A718: G102 | B718: Tuition | C718: =IFERROR(IF(VLOOKUP($A718,'CDS-G'!$A:$L,3,FALSE)="","",(VLOOKUP($A718,'CDS-G'!$A:$L,3,FALSE))),"") | D718: Annual Expenses | E718: Private Tuition | F718: Full-Time | G718: Undergraduate | H718: Undergraduates | I718: All | J718: All | K718: All | L718: Nearest $1
A719: G103 | B719: Tuition: In-district | C719: =IFERROR(IF(VLOOKUP($A719,'CDS-G'!$A:$L,3,FALSE)="","",(VLOOKUP($A719,'CDS-G'!$A:$L,3,FALSE))),"") | D719: Annual Expenses | E719: Public Tuition | F719: Full-Time | G719: Undergraduate | H719: First-year | I719: All | J719: All | K719: All | L719: Nearest $1
A720: G104 | B720: Tuition: In-state (out-of-district): | C720: =IFERROR(IF(VLOOKUP($A720,'CDS-G'!$A:$L,3,FALSE)="","",(VLOOKUP($A720,'CDS-G'!$A:$L,3,FALSE))),"") | D720: Annual Expenses | E720: Public Tuition | F720: Full-Time | G720: Undergraduate | H720: First-year | I720: All | J720: All | K720: All | L720: Nearest $1
A721: G105 | B721: Tuition: Out-of-state: | C721: =IFERROR(IF(VLOOKUP($A721,'CDS-G'!$A:$L,3,FALSE)="","",(VLOOKUP($A721,'CDS-G'!$A:$L,3,FALSE))),"") | D721: Annual Expenses | E721: Public Tuition | F721: Full-Time | G721: Undergraduate | H721: First-year | I721: All | J721: All | K721: All | L721: Nearest $1
A722: G106 | B722: Tuition: Non-resident | C722: =IFERROR(IF(VLOOKUP($A722,'CDS-G'!$A:$L,3,FALSE)="","",(VLOOKUP($A722,'CDS-G'!$A:$L,3,FALSE))),"") | D722: Annual Expenses | E722: Public Tuition | F722: Full-Time | G722: Undergraduate | H722: First-year | I722: All | J722: All | K722: All | L722: Nearest $1
A723: G107 | B723: Tuition: In-district | C723: =IFERROR(IF(VLOOKUP($A723,'CDS-G'!$A:$L,3,FALSE)="","",(VLOOKUP($A723,'CDS-G'!$A:$L,3,FALSE))),"") | D723: Annual Expenses | E723: Public Tuition | F723: Full-Time | G723: Undergraduate | H723: Undergraduates | I723: All | J723: All | K723: All | L723: Nearest $1
A724: G108 | B724: Tuition: In-state (out-of-district): | C724: =IFERROR(IF(VLOOKUP($A724,'CDS-G'!$A:$L,3,FALSE)="","",(VLOOKUP($A724,'CDS-G'!$A:$L,3,FALSE))),"") | D724: Annual Expenses | E724: Public Tuition | F724: Full-Time | G724: Undergraduate | H724: Undergraduates | I724: All | J724: All | K724: All | L724: Nearest $1
A725: G109 | B725: Tuition: Out-of-state: | C725: =IFERROR(IF(VLOOKUP($A725,'CDS-G'!$A:$L,3,FALSE)="","",(VLOOKUP($A725,'CDS-G'!$A:$L,3,FALSE))),"") | D725: Annual Expenses | E725: Public Tuition | F725: Full-Time | G725: Undergraduate | H725: Undergraduates | I725: All | J725: All | K725: All | L725: Nearest $1
... A760: G606 | B760: NONRESIDENTS: | C760: =IFERROR(IF(VLOOKUP($A760,'CDS-G'!$A:$L,3,FALSE)="","",(VLOOKUP($A760,'CDS-G'!$A:$L,3,FALSE))),"") | D760: Annual Expenses | E760: Per-Credit-Hour Charges | F760: Full-Time | G760: Undergraduate | H760: All | I760: All | J760: All | K760: All | L760: Nearest $1
A761: H101 | B761: 2024-2025 | C761: =IFERROR(IF(VLOOKUP($A761,'CDS-H'!$A:$L,3,FALSE)="","",(VLOOKUP($A761,'CDS-H'!$A:$L,3,FALSE))),"") | D761: Financial Aid | E761: Reporting Year | F761: All | G761: All | H761: All | I761: All | J761: All | K761: All | L761: x
A762: H102 | B762: 2023-2024 Final | C762: =IFERROR(IF(VLOOKUP($A762,'CDS-H'!$A:$L,3,FALSE)="","",(VLOOKUP($A762,'CDS-H'!$A:$L,3,FALSE))),"") | D762: Financial Aid | E762: Reporting Year | F762: All | G762: All | H762: All | I762: All | J762: All | K762: All | L762: x
A763: H103 | B763: Federal methodology (FM) | C763: =IFERROR(IF(VLOOKUP($A763,'CDS-H'!$A:$L,3,FALSE)="","",(VLOOKUP($A763,'CDS-H'!$A:$L,3,FALSE))),"") | D763: Financial Aid | E763: Methodology | F763: All | G763: All | H763: All | I763: All | J763: All | K763: All | L763: x
A764: H104 | B764: Institutional methodology (IM) | C764: =IFERROR(IF(VLOOKUP($A764,'CDS-H'!$A:$L,3,FALSE)="","",(VLOOKUP($A764,'CDS-H'!$A:$L,3,FALSE))),"") | D764: Financial Aid | E764: Methodology | F764: All | G764: All | H764: All | I764: All | J764: All | K764: All | L764: x
A765: H105 | B765: Both FM and IM | C765: =IFERROR(IF(VLOOKUP($A765,'CDS-H'!$A:$L,3,FALSE)="","",(VLOOKUP($A765,'CDS-H'!$A:$L,3,FALSE))),"") | D765: Financial Aid | E765: Methodology | F765: All | G765: All | H765: All | I765: All | J765: All | K765: All | L765: x
A766: H106 | B766: Federal | C766: =IFERROR(IF(VLOOKUP($A766,'CDS-H'!$A:$L,3,FALSE)="","",(VLOOKUP($A766,'CDS-H'!$A:$L,3,FALSE))),"") | D766: Financial Aid | E766: Need-based Aid Awarded | F766: Degree-seeking | G766: Undergraduate | H766: Undergraduates | I766: All | J766: All | K766: All | L766: Nearest $1
A767: H107 | B767: State all states, not only the state in which your institution is located | C767: =IFERROR(IF(VLOOKUP($A767,'CDS-H'!$A:$L,3,FALSE)="","",(VLOOKUP($A767,'CDS-H'!$A:$L,3,FALSE))),"") | D767: Financial Aid | E767: Need-based Aid Awarded | F767: Degree-seeking | G767: Undergraduate | H767: Undergraduates | I767: All | J767: All | K767: All | L767: Nearest $1
A768: H108 | B768: Institutional: Endowed scholarships, annual gifts and tuition funded grants, awarded by the college, excluding athletic aid and tuition waivers (which are reported below). | C768: =IFERROR(IF(VLOOKUP($A768,'CDS-H'!$A:$L,3,FALSE)="","",(VLOOKUP($A768,'CDS-H'!$A:$L,3,FALSE))),"") | D768: Financial Aid | E768: Need-based Aid Awarded | F768: Degree-seeking | G768: Undergraduate | H768: Undergraduates | I768: All | J768: All | K768: All | L768: Nearest $1
...
